Workbook

Sheet Crowdfunding
A1: id | B1: name | C1: blurb | D1: goal | E1: pledged | F1: percent_funded | G1: outcome | H1: backers_count | I1: average_donation | J1: country | K1: currency | L1: launched_at | M1: deadline | N1: date_created | O1: date_ended | P1: weekday_created | Q1: duration | R1: staff_pick | S1: spotlight | T1: category_and_subcategory | U1: primary_category | V1: subcategory
A2: 0 | B2: Baldwin, Riley and Jackson | C2: Pre-emptive tertiary standardization | D2: 100 | E2: 0 | F2: =E2/D2 -> 0 | G2: failed | H2: 0 | I2: =IF(H2<>0,E2/H2,0) -> 0 | J2: CA | K2: CAD | L2: 1448690400 | M2: 1450159200 | N2: =(((L2/60)/60)/24)+DATE(1970,1,1) -> 42336.25 | O2: =(((M2/60)/60)/24)+DATE(1970,1,1) -> 42353.25 | P2: =TEXT(CrowdfundingTable[[#This Row],[date_created]],"ddd") -> Sat | Q2: =_xlfn.DAYS(CrowdfundingTable[[#This Row],[date_ended]],CrowdfundingTable[[#This Row],[date_created]]) -> 17 | R2: FALSE | S2: FALSE | T2: food/food trucks | U2: food | V2: food trucks
A3: 1 | B3: Odom Inc | C3: Managed bottom-line architecture | D3: 1400 | E3: 14560 | F3: =E3/D3 -> 10.4 | G3: successful | H3: 158 | I3: =IF(H3<>0,E3/H3,0) -> 92.151899 | J3: US | K3: USD | L3: 1408424400 | M3: 1408597200 | N3: =(((L3/60)/60)/24)+DATE(1970,1,1) -> 41870.208 | O3: =(((M3/60)/60)/24)+DATE(1970,1,1) -> 41872.208 | P3: =TEXT(CrowdfundingTable[[#This Row],[date_created]],"ddd") -> Tue | Q3: =_xlfn.DAYS(CrowdfundingTable[[#This Row],[date_ended]],CrowdfundingTable[[#This Row],[date_created]]) -> 2 | R3: FALSE | S3: TRUE | T3: music/rock | U3: music | V3: rock
A4: 2 | B4: Melton, Robinson and Fritz | C4: Function-based leadingedge pricing structure | D4: 108400 | E4: 142523 | F4: 1.31 | G4: successful | H4: 1425 | I4: =IF(H4<>0,E4/H4,0) -> 100.01614 | J4: AU | K4: AUD | L4: 1384668000 | M4: 1384840800 | N4: =(((L4/60)/60)/24)+DATE(1970,1,1) -> 41595.25 | O4: =(((M4/60)/60)/24)+DATE(1970,1,1) -> 41597.25 | P4: =TEXT(CrowdfundingTable[[#This Row],[date_created]],"ddd") -> Sun | Q4: =_xlfn.DAYS(CrowdfundingTable[[#This Row],[date_ended]],CrowdfundingTable[[#This Row],[date_created]]) -> 2 | R4: FALSE | S4: FALSE | T4: technology/web | U4: technology | V4: web
A5: 3 | B5: Mcdonald, Gonzalez and Ross | C5: Vision-oriented fresh-thinking conglomeration | D5: 4200 | E5: 2477 | F5: =E5/D5 -> 0.5897619 | G5: failed | H5: 24 | I5: =IF(H5<>0,E5/H5,0) -> 103.20833 | J5: US | K5: USD | L5: 1565499600 | M5: 1568955600 | N5: =(((L5/60)/60)/24)+DATE(1970,1,1) -> 43688.208 | O5: =(((M5/60)/60)/24)+DATE(1970,1,1) -> 43728.208 | P5: =TEXT(CrowdfundingTable[[#This Row],[date_created]],"ddd") -> Sun | Q5: =_xlfn.DAYS(CrowdfundingTable[[#This Row],[date_ended]],CrowdfundingTable[[#This Row],[date_created]]) -> 40 | R5: FALSE | S5: FALSE | T5: music/rock | U5: music | V5: rock
A6: 4 | B6: Larson-Little | C6: Proactive foreground core | D6: 7600 | E6: 5265 | F6: =E6/D6 -> 0.69276316 | G6: failed | H6: 53 | I6: =IF(H6<>0,E6/H6,0) -> 99.339623 | J6: US | K6: USD | L6: 1547964000 | M6: 1548309600 | N6: =(((L6/60)/60)/24)+DATE(1970,1,1) -> 43485.25 | O6: =(((M6/60)/60)/24)+DATE(1970,1,1) -> 43489.25 | P6: =TEXT(CrowdfundingTable[[#This Row],[date_created]],"ddd") -> Sun | Q6: =_xlfn.DAYS(CrowdfundingTable[[#This Row],[date_ended]],CrowdfundingTable[[#This Row],[date_created]]) -> 4 | R6: FALSE | S6: FALSE | T6: theater/plays | U6: theater | V6: plays
A7: 5 | B7: Harris Group | C7: Open-source optimizing database | D7: 7600 | E7: 13195 | F7: =E7/D7 -> 1.7361842 | G7: successful | H7: 174 | I7: =IF(H7<>0,E7/H7,0) -> 75.833333 | J7: DK | K7: DKK | L7: 1346130000 | M7: 1347080400 | N7: =(((L7/60)/60)/24)+DATE(1970,1,1) -> 41149.208 | O7: =(((M7/60)/60)/24)+DATE(1970,1,1) -> 41160.208 | P7: =TEXT(CrowdfundingTable[[#This Row],[date_created]],"ddd") -> Tue | Q7: =_xlfn.DAYS(CrowdfundingTable[[#This Row],[date_ended]],CrowdfundingTable[[#This Row],[date_created]]) -> 11 | R7: FALSE | S7: FALSE | T7: theater/plays | U7: theater | V7: plays
A8: 6 | B8: Ortiz, Coleman and Mitchell | C8: Operative upward-trending algorithm | D8: 5200 | E8: 1090 | F8: =E8/D8 -> 0.20961538 | G8: failed | H8: 18 | I8: =IF(H8<>0,E8/H8,0) -> 60.555556 | J8: GB | K8: GBP | L8: 1505278800 | M8: 1505365200 | N8: =(((L8/60)/60)/24)+DATE(1970,1,1) -> 42991.208 | O8: =(((M8/60)/60)/24)+DATE(1970,1,1) -> 42992.208 | P8: =TEXT(CrowdfundingTable[[#This Row],[date_created]],"ddd") -> Wed | Q8: =_xlfn.DAYS(CrowdfundingTable[[#This Row],[date_ended]],CrowdfundingTable[[#This Row],[date_created]]) -> 1 | R8: FALSE | S8: FALSE | T8: film & video/documentary | U8: film & video | V8: documentary
A9: 7 | B9: Carter-Guzman | C9: Centralized cohesive challenge | D9: 4500 | E9: 14741 | F9: =E9/D9 -> 3.2757778 | G9: successful | H9: 227 | I9: =IF(H9<>0,E9/H9,0) -> 64.938326 | J9: DK | K9: DKK | L9: 1439442000 | M9: 1439614800 | N9: =(((L9/60)/60)/24)+DATE(1970,1,1) -> 42229.208 | O9: =(((M9/60)/60)/24)+DATE(1970,1,1) -> 42231.208 | P9: =TEXT(CrowdfundingTable[[#This Row],[date_created]],"ddd") -> Thu | Q9: =_xlfn.DAYS(CrowdfundingTable[[#This Row],[date_ended]],CrowdfundingTable[[#This Row],[date_created]]) -> 2 | R9: FALSE | S9: FALSE | T9: theater/plays | U9: theater | V9: plays
A10: 8 | B10: Nunez-Richards | C10: Exclusive attitude-oriented intranet | D10: 110100 | E10: 21946 | F10: =E10/D10 -> 0.19932788 | G10: live | H10: 708 | I10: =IF(H10<>0,E10/H10,0) -> 30.997175 | J10: DK | K10: DKK | L10: 1281330000 | M10: 1281502800 | N10: =(((L10/60)/60)/24)+DATE(1970,1,1) -> 40399.208 | O10: =(((M10/60)/60)/24)+DATE(1970,1,1) -> 40401.208 | P10: =TEXT(CrowdfundingTable[[#This Row],[date_created]],"ddd") -> Mon | Q10: =_xlfn.DAYS(CrowdfundingTable[[#This Row],[date_ended]],CrowdfundingTable[[#This Row],[date_created]]) -> 2 | R10: FALSE | S10: FALSE | T10: theater/plays | U10: theater | V10: plays
A11: 9 | B11: Rangel, Holt and Jones | C11: Open-source fresh-thinking model | D11: 6200 | E11: 3208 | F11: =E11/D11 -> 0.51741935 | G11: failed | H11: 44 | I11: =IF(H11<>0,E11/H11,0) -> 72.909091 | J11: US | K11: USD | L11: 1379566800 | M11: 1383804000 | N11: =(((L11/60)/60)/24)+DATE(1970,1,1) -> 41536.208 | O11: =(((M11/60)/60)/24)+DATE(1970,1,1) -> 41585.25 | P11: =TEXT(CrowdfundingTable[[#This Row],[date_created]],"ddd") -> Thu | Q11: =_xlfn.DAYS(CrowdfundingTable[[#This Row],[date_ended]],CrowdfundingTable[[#This Row],[date_created]]) -> 49 | R11: FALSE | S11: FALSE | T11: music/electric music | U11: music | V11: electric music
A12: 10 | B12: Green Ltd | C12: Monitored empowering installation | D12: 5200 | E12: 13838 | F12: =E12/D12 -> 2.6611538 | G12: successful | H12: 220 | I12: =IF(H12<>0,E12/H12,0) -> 62.9 | J12: US | K12: USD | L12: 1281762000 | M12: 1285909200 | N12: =(((L12/60)/60)/24)+DATE(1970,1,1) -> 40404.208 | O12: =(((M12/60)/60)/24)+DATE(1970,1,1) -> 40452.208 | P12: =TEXT(CrowdfundingTable[[#This Row],[date_created]],"ddd") -> Sat | Q12: =_xlfn.DAYS(CrowdfundingTable[[#This Row],[date_ended]],CrowdfundingTable[[#This Row],[date_created]]) -> 48 | R12: FALSE | S12: FALSE | T12: film & video/drama | U12: film & video | V12: drama
A13: 11 | B13: Perez, Johnson and Gardner | C13: Grass-roots zero administration system engine | D13: 6300 | E13: 3030 | F13: =E13/D13 -> 0.48095238 | G13: failed | H13: 27 | I13: =IF(H13<>0,E13/H13,0) -> 112.22222 | J13: US | K13: USD | L13: 1285045200 | M13: 1285563600 | N13: =(((L13/60)/60)/24)+DATE(1970,1,1) -> 40442.208 | O13: =(((M13/60)/60)/24)+DATE(1970,1,1) -> 40448.208 | P13: =TEXT(CrowdfundingTable[[#This Row],[date_created]],"ddd") -> Tue | Q13: =_xlfn.DAYS(CrowdfundingTable[[#This Row],[date_ended]],CrowdfundingTable[[#This Row],[date_created]]) -> 6 | R13: FALSE | S13: TRUE | T13: theater/plays | U13: theater | V13: plays
A14: 12 | B14: Kim Ltd | C14: Assimilated hybrid intranet | D14: 6300 | E14: 5629 | F14: =E14/D14 -> 0.89349206 | G14: failed | H14: 55 | I14: =IF(H14<>0,E14/H14,0) -> 102.34545 | J14: US | K14: USD | L14: 1571720400 | M14: 1572411600 | N14: =(((L14/60)/60)/24)+DATE(1970,1,1) -> 43760.208 | O14: =(((M14/60)/60)/24)+DATE(1970,1,1) -> 43768.208 | P14: =TEXT(CrowdfundingTable[[#This Row],[date_created]],"ddd") -> Tue | Q14: =_xlfn.DAYS(CrowdfundingTable[[#This Row],[date_ended]],CrowdfundingTable[[#This Row],[date_created]]) -> 8 | R14: FALSE | S14: FALSE | T14: film & video/drama | U14: film & video | V14: drama
A15: 13 | B15: Walker, Taylor and Coleman | C15: Multi-tiered directional open architecture | D15: 4200 | E15: 10295 | F15: =E15/D15 -> 2.4511905 | G15: successful | H15: 98 | I15: =IF(H15<>0,E15/H15,0) -> 105.05102 | J15: US | K15: USD | L15: 1465621200 | M15: 1466658000 | N15: =(((L15/60)/60)/24)+DATE(1970,1,1) -> 42532.208 | O15: =(((M15/60)/60)/24)+DATE(1970,1,1) -> 42544.208 | P15: =TEXT(CrowdfundingTable[[#This Row],[date_created]],"ddd") -> Sat | Q15: =_xlfn.DAYS(CrowdfundingTable[[#This Row],[date_ended]],CrowdfundingTable[[#This Row],[date_created]]) -> 12 | R15: FALSE | S15: FALSE | T15: music/indie rock | U15: music | V15: indie rock
A16: 14 | B16: Rodriguez, Rose and Stewart | C16: Cloned directional synergy | D16: 28200 | E16: 18829 | F16: =E16/D16 -> 0.66769504 | G16: failed | H16: 200 | I16: =IF(H16<>0,E16/H16,0) -> 94.145 | J16: US | K16: USD | L16: 1331013600 | M16: 1333342800 | N16: =(((L16/60)/60)/24)+DATE(1970,1,1) -> 40974.25 | O16: =(((M16/60)/60)/24)+DATE(1970,1,1) -> 41001.208 | P16: =TEXT(CrowdfundingTable[[#This Row],[date_created]],"ddd") -> Tue | Q16: =_xlfn.DAYS(CrowdfundingTable[[#This Row],[date_ended]],CrowdfundingTable[[#This Row],[date_created]]) -> 27 | R16: FALSE | S16: FALSE | T16: music/indie rock | U16: music | V16: indie rock
... A1001: 999 | B1001: Hernandez, Norton and Kelley | C1001: Expanded eco-centric policy | D1001: 111100 | E1001: 62819 | F1001: =E1001/D1001 -> 0.56542754 | G1001: canceled | H1001: 1122 | I1001: =IF(H1001<>0,E1001/H1001,0) -> 55.988414 | J1001: US | K1001: USD | L1001: 1467176400 | M1001: 1467781200 | N1001: =(((L1001/60)/60)/24)+DATE(1970,1,1) -> 42550.208 | O1001: =(((M1001/60)/60)/24)+DATE(1970,1,1) -> 42557.208 | P1001: =TEXT(CrowdfundingTable[[#This Row],[date_created]],"ddd") -> Wed | Q1001: =_xlfn.DAYS(CrowdfundingTable[[#This Row],[date_ended]],CrowdfundingTable[[#This Row],[date_created]]) -> 7 | R1001: FALSE | S1001: FALSE | T1001: food/food trucks | U1001: food | V1001: food trucks

Sheet Outcomes vs. Categories
A1: country | B1: (All)
A2: Years | B2: (All)
A4: Count of outcome | B4: Column Labels
A5: Row Labels | B5: canceled | C5: failed | D5: live | E5: successful | F5: Grand Total
A6: film & video | B6: 11 | C6: 60 | D6: 5 | E6: 102 | F6: 178
A7: animation | B7: 1 | C7: 10 | D7: 2 | E7: 21 | F7: 34
A8: documentary | B8: 4 | C8: 21 | D8: 1 | E8: 34 | F8: 60
A9: drama | B9: 2 | C9: 12 | D9: 1 | E9: 22 | F9: 37
A10: science fiction | C10: 9 | E10: 5 | F10: 14
A11: shorts | B11: 1 | C11: 5 | D11: 1 | E11: 9 | F11: 16
A12: television | B12: 3 | C12: 3 | E12: 11 | F12: 17
A13: food | B13: 4 | C13: 20 | E13: 22 | F13: 46
A14: food trucks | B14: 4 | C14: 20 | E14: 22 | F14: 46
A15: games | B15: 1 | C15: 23 | D15: 3 | E15: 21 | F15: 48
A16: mobile games | C16: 8 | D16: 1 | E16: 4 | F16: 13
A17: video games | B17: 1 | C17: 15 | D17: 2 | E17: 17 | F17: 35
A18: journalism | E18: 4 | F18: 4
A19: audio | E19: 4 | F19: 4
A20: music | B20: 10 | C20: 66 | E20: 99 | F20: 175
A21: electric music | C21: 8 | E21: 10 | F21: 18
A22: indie rock | B22: 3 | C22: 19 | E22: 23 | F22: 45
A23: jazz | B23: 1 | C23: 6 | E23: 10 | F23: 17
A24: metal | C24: 3 | E24: 4 | F24: 7
A25: rock | B25: 6 | C25: 30 | E25: 49 | F25: 85
A26: world music | E26: 3 | F26: 3
A27: photography | B27: 4 | C27: 11 | D27: 1 | E27: 26 | F27: 42
A28: photography books | B28: 4 | C28: 11 | D28: 1 | E28: 26 | F28: 42
A29: publishing | B29: 2 | C29: 24 | D29: 1 | E29: 40 | F29: 67
A30: fiction | B30: 1 | C30: 7 | E30: 9 | F30: 17
A31: nonfiction | B31: 1 | C31: 6 | D31: 1 | E31: 13 | F31: 21
A32: radio & podcasts | C32: 4 | E32: 4 | F32: 8
A33: translations | C33: 7 | E33: 14 | F33: 21
A34: technology | B34: 2 | C34: 28 | D34: 2 | E34: 64 | F34: 96
A35: wearables | C35: 16 | D35: 1 | E35: 28 | F35: 45
A36: web | B36: 2 | C36: 12 | D36: 1 | E36: 36 | F36: 51
A37: theater | B37: 23 | C37: 132 | D37: 2 | E37: 187 | F37: 344
A38: plays | B38: 23 | C38: 132 | D38: 2 | E38: 187 | F38: 344
A39: Grand Total | B39: 57 | C39: 364 | D39: 14 | E39: 565 | F39: 1000

Sheet Mean Funding Ratio
A1: country | B1: (All)
A2: Years | B2: (All)
A4: Average of percent_funded | B4: Column Labels
A5: Row Labels | B5: canceled | C5: failed | D5: live | E5: successful | F5: Grand Total
A6: film & video | B6: 0.45857998 | C6: 0.51656024 | D6: 0.57172845 | E6: 3.0380113 | F6: 1.9594033
A7: animation | B7: 0.34959979 | C7: 0.44051363 | D7: 0.75119745 | E7: 3.3387929 | F7: 2.2462289
A8: documentary | B8: 0.70523298 | C8: 0.53165931 | D8: 0.21188689 | E8: 3.0038866 | F8: 1.9388301
A9: drama | B9: 0.10627538 | C9: 0.5633952 | D9: 0.56186047 | E9: 3.1334786 | F9: 2.0668022
A10: science fiction | C10: 0.39775079 | E10: 2.4974338 | F10: 1.1476376
A11: shorts | B11: 0.23995288 | C11: 0.69915253 | D11: 0.5825 | E11: 3.3460966 | F11: 2.1520678
A12: television | B12: 0.47378147 | C12: 0.52912343 | E12: 2.371981 | F12: 1.7117944
A13: food | B13: 0.50408392 | C13: 0.4962951 | E13: 3.9271729 | F13: 2.137827
A14: food trucks | B14: 0.50408392 | C14: 0.4962951 | E14: 3.9271729 | F14: 2.137827
A15: games | B15: 0.27176538 | C15: 0.51149586 | D15: 0.51516824 | E15: 4.2327345 | F15: 2.1347729
A16: mobile games | C16: 0.5194476 | D16: 0.36132726 | E16: 1.8081137 | F16: 0.90379715
A17: video games | B17: 0.27176538 | C17: 0.50725493 | D17: 0.59208873 | E17: 4.8032335 | F17: 2.5919925
A18: journalism | E18: 1.5062985 | F18: 1.5062985
A19: audio | E19: 1.5062985 | F19: 1.5062985
A20: music | B20: 0.38498633 | C20: 0.45803203 | E20: 3.2937501 | F20: 2.0580642
A21: electric music | C21: 0.37679821 | E21: 3.7954948 | F21: 2.2760741
A22: indie rock | B22: 0.30187573 | C22: 0.51243169 | E22: 2.850915 | F22: 1.6936194
A23: jazz | B23: 0.18853659 | C23: 0.29131793 | E23: 4.6720698 | F23: 2.8621848
A24: metal | C24: 0.45755732 | E24: 3.2015425 | F24: 2.0255489
A25: rock | B25: 0.45928325 | C25: 0.47863155 | E25: 3.1998112 | F25: 2.0459458
A26: world music | E26: 2.0792167 | F26: 2.0792167
A27: photography | B27: 0.61272047 | C27: 0.46863595 | D27: 0.012706571 | E27: 2.6819133 | F27: 1.8416269
A28: photography books | B28: 0.61272047 | C28: 0.46863595 | D28: 0.012706571 | E28: 2.6819133 | F28: 1.8416269
A29: publishing | B29: 0.35870274 | C29: 0.4224918 | D29: 0.017292683 | E29: 2.9800017 | F29: 1.9414115
A30: fiction | B30: 0.38844444 | C30: 0.546806 | E30: 3.3985746 | F30: 2.0472505
A31: nonfiction | B31: 0.32896104 | C31: 0.40494185 | D31: 0.017292683 | E31: 3.6593226 | F31: 2.3974809
A32: radio & podcasts | C32: 0.4006924 | E32: 1.7630795 | F32: 1.081886
A33: translations | C33: 0.32567722 | E33: 2.4278133 | F33: 1.7271013
A34: technology | B34: 0.6447619 | C34: 0.56331661 | D34: 0.60603004 | E34: 3.0988806 | F34: 2.2562792
A35: wearables | C35: 0.55778883 | D35: 0.58973684 | E35: 2.8267161 | F35: 1.9702757
A36: web | B36: 0.6447619 | C36: 0.57068697 | D36: 0.62232323 | E36: 3.3105641 | F36: 2.5086353
A37: theater | B37: 0.45757574 | C37: 0.49562153 | D37: 0.31396353 | E37: 3.1446431 | F37: 1.932042
A38: plays | B38: 0.45757574 | C38: 0.49562153 | D38: 0.31396353 | E38: 3.1446431 | F38: 1.932042
A39: Grand Total | B39: 0.45902452 | C39: 0.49286742 | D39: 0.44815238 | E39: 3.1726996 | F39: 2.0044175

Sheet Median Funding Ratio
A2: Row Labels | B2: canceled | C2: failed | D2: live | E2: successful | F2: Grand Total
A3: film & video | B3: {=IFERROR(ROUND(MEDIAN(_xlfn._xlws.FILTER(CrowdfundingTable[percent_funded],(CrowdfundingTable[primary_category]=$A3)*(CrowdfundingTable[outcome]=$B$2))),2),"")} -> 0.39 | C3: {=IFERROR(ROUND(MEDIAN(_xlfn._xlws.FILTER(CrowdfundingTable[percent_funded],(CrowdfundingTable[primary_category]=$A3)*(CrowdfundingTable[outcome]=$C$2))),2),"")} -> 0.52 | D3: {=IFERROR(ROUND(MEDIAN(_xlfn._xlws.FILTER(CrowdfundingTable[percent_funded],(CrowdfundingTable[primary_category]=$A3)*(CrowdfundingTable[outcome]=$D$2))),2),"")} -> 0.58 | E3: {=IFERROR(ROUND(MEDIAN(_xlfn._xlws.FILTER(CrowdfundingTable[percent_funded],(CrowdfundingTable[primary_category]=$A3)*(CrowdfundingTable[outcome]=$E$2))),2),"")} -> 2.07 | F3: {=IFERROR(ROUND(MEDIAN(_xlfn._xlws.FILTER(CrowdfundingTable[percent_funded],CrowdfundingTable[primary_category]=$A3)),2),"")} -> 1.23
A4: animation | B4: {=IFERROR(ROUND(MEDIAN(_xlfn._xlws.FILTER(CrowdfundingTable[percent_funded],(CrowdfundingTable[subcategory]=$A4)*(CrowdfundingTable[outcome]=$B$2))),2),"")} -> 0.35 | C4: {=IFERROR(ROUND(MEDIAN(_xlfn._xlws.FILTER(CrowdfundingTable[percent_funded],(CrowdfundingTable[subcategory]=$A4)*(CrowdfundingTable[outcome]=$C$2))),2),"")} -> 0.46 | D4: {=IFERROR(ROUND(MEDIAN(_xlfn._xlws.FILTER(CrowdfundingTable[percent_funded],(CrowdfundingTable[subcategory]=$A4)*(CrowdfundingTable[outcome]=$D$2))),2),"")} -> 0.75 | E4: {=IFERROR(ROUND(MEDIAN(_xlfn._xlws.FILTER(CrowdfundingTable[percent_funded],(CrowdfundingTable[subcategory]=$A4)*(CrowdfundingTable[outcome]=$E$2))),2),"")} -> 1.93 | F4: {=IFERROR(ROUND(MEDIAN(_xlfn._xlws.FILTER(CrowdfundingTable[percent_funded],CrowdfundingTable[subcategory]=$A4)),2),"")} -> 1.39
A5: documentary | B5: {=IFERROR(ROUND(MEDIAN(_xlfn._xlws.FILTER(CrowdfundingTable[percent_funded],(CrowdfundingTable[subcategory]=$A5)*(CrowdfundingTable[outcome]=$B$2))),2),"")} -> 0.67 | C5: {=IFERROR(ROUND(MEDIAN(_xlfn._xlws.FILTER(CrowdfundingTable[percent_funded],(CrowdfundingTable[subcategory]=$A5)*(CrowdfundingTable[outcome]=$C$2))),2),"")} -> 0.54 | D5: {=IFERROR(ROUND(MEDIAN(_xlfn._xlws.FILTER(CrowdfundingTable[percent_funded],(CrowdfundingTable[subcategory]=$A5)*(CrowdfundingTable[outcome]=$D$2))),2),"")} -> 0.21 | E5: {=IFERROR(ROUND(MEDIAN(_xlfn._xlws.FILTER(CrowdfundingTable[percent_funded],(CrowdfundingTable[subcategory]=$A5)*(CrowdfundingTable[outcome]=$E$2))),2),"")} -> 2.03 | F5: {=IFERROR(ROUND(MEDIAN(_xlfn._xlws.FILTER(CrowdfundingTable[percent_funded],CrowdfundingTable[subcategory]=$A5)),2),"")} -> 1.26
A6: drama | B6: {=IFERROR(ROUND(MEDIAN(_xlfn._xlws.FILTER(CrowdfundingTable[percent_funded],(CrowdfundingTable[subcategory]=$A6)*(CrowdfundingTable[outcome]=$B$2))),2),"")} -> 0.11 | C6: {=IFERROR(ROUND(MEDIAN(_xlfn._xlws.FILTER(CrowdfundingTable[percent_funded],(CrowdfundingTable[subcategory]=$A6)*(CrowdfundingTable[outcome]=$C$2))),2),"")} -> 0.57 | D6: {=IFERROR(ROUND(MEDIAN(_xlfn._xlws.FILTER(CrowdfundingTable[percent_funded],(CrowdfundingTable[subcategory]=$A6)*(CrowdfundingTable[outcome]=$D$2))),2),"")} -> 0.56 | E6: {=IFERROR(ROUND(MEDIAN(_xlfn._xlws.FILTER(CrowdfundingTable[percent_funded],(CrowdfundingTable[subcategory]=$A6)*(CrowdfundingTable[outcome]=$E$2))),2),"")} -> 1.82 | F6: {=IFERROR(ROUND(MEDIAN(_xlfn._xlws.FILTER(CrowdfundingTable[percent_funded],CrowdfundingTable[subcategory]=$A6)),2),"")} -> 1.4
A7: science fiction | B7: {=IFERROR(ROUND(MEDIAN(_xlfn._xlws.FILTER(CrowdfundingTable[percent_funded],(CrowdfundingTable[subcategory]=$A7)*(CrowdfundingTable[outcome]=$B$2))),2),"")} | C7: {=IFERROR(ROUND(MEDIAN(_xlfn._xlws.FILTER(CrowdfundingTable[percent_funded],(CrowdfundingTable[subcategory]=$A7)*(CrowdfundingTable[outcome]=$C$2))),2),"")} -> 0.45 | D7: {=IFERROR(ROUND(MEDIAN(_xlfn._xlws.FILTER(CrowdfundingTable[percent_funded],(CrowdfundingTable[subcategory]=$A7)*(CrowdfundingTable[outcome]=$D$2))),2),"")} | E7: {=IFERROR(ROUND(MEDIAN(_xlfn._xlws.FILTER(CrowdfundingTable[percent_funded],(CrowdfundingTable[subcategory]=$A7)*(CrowdfundingTable[outcome]=$E$2))),2),"")} -> 1.99 | F7: {=IFERROR(ROUND(MEDIAN(_xlfn._xlws.FILTER(CrowdfundingTable[percent_funded],CrowdfundingTable[subcategory]=$A7)),2),"")} -> 0.58
A8: shorts | B8: {=IFERROR(ROUND(MEDIAN(_xlfn._xlws.FILTER(CrowdfundingTable[percent_funded],(CrowdfundingTable[subcategory]=$A8)*(CrowdfundingTable[outcome]=$B$2))),2),"")} -> 0.24 | C8: {=IFERROR(ROUND(MEDIAN(_xlfn._xlws.FILTER(CrowdfundingTable[percent_funded],(CrowdfundingTable[subcategory]=$A8)*(CrowdfundingTable[outcome]=$C$2))),2),"")} -> 0.88 | D8: {=IFERROR(ROUND(MEDIAN(_xlfn._xlws.FILTER(CrowdfundingTable[percent_funded],(CrowdfundingTable[subcategory]=$A8)*(CrowdfundingTable[outcome]=$D$2))),2),"")} -> 0.58 | E8: {=IFERROR(ROUND(MEDIAN(_xlfn._xlws.FILTER(CrowdfundingTable[percent_funded],(CrowdfundingTable[subcategory]=$A8)*(CrowdfundingTable[outcome]=$E$2))),2),"")} -> 3.29 | F8: {=IFERROR(ROUND(MEDIAN(_xlfn._xlws.FILTER(CrowdfundingTable[percent_funded],CrowdfundingTable[subcategory]=$A8)),2),"")} -> 1.78
A9: television | B9: {=IFERROR(ROUND(MEDIAN(_xlfn._xlws.FILTER(CrowdfundingTable[percent_funded],(CrowdfundingTable[subcategory]=$A9)*(CrowdfundingTable[outcome]=$B$2))),2),"")} -> 0.39 | C9: {=IFERROR(ROUND(MEDIAN(_xlfn._xlws.FILTER(CrowdfundingTable[percent_funded],(CrowdfundingTable[subcategory]=$A9)*(CrowdfundingTable[outcome]=$C$2))),2),"")} -> 0.59 | D9: {=IFERROR(ROUND(MEDIAN(_xlfn._xlws.FILTER(CrowdfundingTable[percent_funded],(CrowdfundingTable[subcategory]=$A9)*(CrowdfundingTable[outcome]=$D$2))),2),"")} | E9: {=IFERROR(ROUND(MEDIAN(_xlfn._xlws.FILTER(CrowdfundingTable[percent_funded],(CrowdfundingTable[subcategory]=$A9)*(CrowdfundingTable[outcome]=$E$2))),2),"")} -> 1.89 | F9: {=IFERROR(ROUND(MEDIAN(_xlfn._xlws.FILTER(CrowdfundingTable[percent_funded],CrowdfundingTable[subcategory]=$A9)),2),"")} -> 1.56
A10: food | B10: {=IFERROR(ROUND(MEDIAN(_xlfn._xlws.FILTER(CrowdfundingTable[percent_funded],(CrowdfundingTable[primary_category]=$A10)*(CrowdfundingTable[outcome]=$B$2))),2),"")} -> 0.6 | C10: {=IFERROR(ROUND(MEDIAN(_xlfn._xlws.FILTER(CrowdfundingTable[percent_funded],(CrowdfundingTable[primary_category]=$A10)*(CrowdfundingTable[outcome]=$C$2))),2),"")} -> 0.59 | D10: {=IFERROR(ROUND(MEDIAN(_xlfn._xlws.FILTER(CrowdfundingTable[percent_funded],(CrowdfundingTable[primary_category]=$A10)*(CrowdfundingTable[outcome]=$D$2))),2),"")} | E10: {=IFERROR(ROUND(MEDIAN(_xlfn._xlws.FILTER(CrowdfundingTable[percent_funded],(CrowdfundingTable[primary_category]=$A10)*(CrowdfundingTable[outcome]=$E$2))),2),"")} -> 3.29 | F10: {=IFERROR(ROUND(MEDIAN(_xlfn._xlws.FILTER(CrowdfundingTable[percent_funded],CrowdfundingTable[primary_category]=$A10)),2),"")} -> 0.97
A11: food trucks | B11: {=IFERROR(ROUND(MEDIAN(_xlfn._xlws.FILTER(CrowdfundingTable[percent_funded],(CrowdfundingTable[subcategory]=$A11)*(CrowdfundingTable[outcome]=$B$2))),2),"")} -> 0.6 | C11: {=IFERROR(ROUND(MEDIAN(_xlfn._xlws.FILTER(CrowdfundingTable[percent_funded],(CrowdfundingTable[subcategory]=$A11)*(CrowdfundingTable[outcome]=$C$2))),2),"")} -> 0.59 | D11: {=IFERROR(ROUND(MEDIAN(_xlfn._xlws.FILTER(CrowdfundingTable[percent_funded],(CrowdfundingTable[subcategory]=$A11)*(CrowdfundingTable[outcome]=$D$2))),2),"")} | E11: {=IFERROR(ROUND(MEDIAN(_xlfn._xlws.FILTER(CrowdfundingTable[percent_funded],(CrowdfundingTable[subcategory]=$A11)*(CrowdfundingTable[outcome]=$E$2))),2),"")} -> 3.29 | F11: {=IFERROR(ROUND(MEDIAN(_xlfn._xlws.FILTER(CrowdfundingTable[percent_funded],CrowdfundingTable[subcategory]=$A11)),2),"")} -> 0.97
A12: games | B12: {=IFERROR(ROUND(MEDIAN(_xlfn._xlws.FILTER(CrowdfundingTable[percent_funded],(CrowdfundingTable[primary_category]=$A12)*(CrowdfundingTable[outcome]=$B$2))),2),"")} -> 0.27 | C12: {=IFERROR(ROUND(MEDIAN(_xlfn._xlws.FILTER(CrowdfundingTable[percent_funded],(CrowdfundingTable[primary_category]=$A12)*(CrowdfundingTable[outcome]=$C$2))),2),"")} -> 0.5 | D12: {=IFERROR(ROUND(MEDIAN(_xlfn._xlws.FILTER(CrowdfundingTable[percent_funded],(CrowdfundingTable[primary_category]=$A12)*(CrowdfundingTable[outcome]=$D$2))),2),"")} -> 0.36 | E12: {=IFERROR(ROUND(MEDIAN(_xlfn._xlws.FILTER(CrowdfundingTable[percent_funded],(CrowdfundingTable[primary_category]=$A12)*(CrowdfundingTable[outcome]=$E$2))),2),"")} -> 2.39 | F12: {=IFERROR(ROUND(MEDIAN(_xlfn._xlws.FILTER(CrowdfundingTable[percent_funded],CrowdfundingTable[primary_category]=$A12)),2),"")} -> 0.96
A13: mobile games | B13: {=IFERROR(ROUND(MEDIAN(_xlfn._xlws.FILTER(CrowdfundingTable[percent_funded],(CrowdfundingTable[subcategory]=$A13)*(CrowdfundingTable[outcome]=$B$2))),2),"")} | C13: {=IFERROR(ROUND(MEDIAN(_xlfn._xlws.FILTER(CrowdfundingTable[percent_funded],(CrowdfundingTable[subcategory]=$A13)*(CrowdfundingTable[outcome]=$C$2))),2),"")} -> 0.44 | D13: {=IFERROR(ROUND(MEDIAN(_xlfn._xlws.FILTER(CrowdfundingTable[percent_funded],(CrowdfundingTable[subcategory]=$A13)*(CrowdfundingTable[outcome]=$D$2))),2),"")} -> 0.36 | E13: {=IFERROR(ROUND(MEDIAN(_xlfn._xlws.FILTER(CrowdfundingTable[percent_funded],(CrowdfundingTable[subcategory]=$A13)*(CrowdfundingTable[outcome]=$E$2))),2),"")} -> 1.81 | F13: {=IFERROR(ROUND(MEDIAN(_xlfn._xlws.FILTER(CrowdfundingTable[percent_funded],CrowdfundingTable[subcategory]=$A13)),2),"")} -> 0.55
A14: video games | B14: {=IFERROR(ROUND(MEDIAN(_xlfn._xlws.FILTER(CrowdfundingTable[percent_funded],(CrowdfundingTable[subcategory]=$A14)*(CrowdfundingTable[outcome]=$B$2))),2),"")} -> 0.27 | C14: {=IFERROR(ROUND(MEDIAN(_xlfn._xlws.FILTER(CrowdfundingTable[percent_funded],(CrowdfundingTable[subcategory]=$A14)*(CrowdfundingTable[outcome]=$C$2))),2),"")} -> 0.5 | D14: {=IFERROR(ROUND(MEDIAN(_xlfn._xlws.FILTER(CrowdfundingTable[percent_funded],(CrowdfundingTable[subcategory]=$A14)*(CrowdfundingTable[outcome]=$D$2))),2),"")} -> 0.59 | E14: {=IFERROR(ROUND(MEDIAN(_xlfn._xlws.FILTER(CrowdfundingTable[percent_funded],(CrowdfundingTable[subcategory]=$A14)*(CrowdfundingTable[outcome]=$E$2))),2),"")} -> 3.1 | F14: {=IFERROR(ROUND(MEDIAN(_xlfn._xlws.FILTER(CrowdfundingTable[percent_funded],CrowdfundingTable[subcategory]=$A14)),2),"")} -> 0.97
A15: journalism | B15: {=IFERROR(ROUND(MEDIAN(_xlfn._xlws.FILTER(CrowdfundingTable[percent_funded],(CrowdfundingTable[primary_category]=$A15)*(CrowdfundingTable[outcome]=$B$2))),2),"")} | C15: {=IFERROR(ROUND(MEDIAN(_xlfn._xlws.FILTER(CrowdfundingTable[percent_funded],(CrowdfundingTable[primary_category]=$A15)*(CrowdfundingTable[outcome]=$C$2))),2),"")} | D15: {=IFERROR(ROUND(MEDIAN(_xlfn._xlws.FILTER(CrowdfundingTable[percent_funded],(CrowdfundingTable[primary_category]=$A15)*(CrowdfundingTable[outcome]=$D$2))),2),"")} | E15: {=IFERROR(ROUND(MEDIAN(_xlfn._xlws.FILTER(CrowdfundingTable[percent_funded],(CrowdfundingTable[primary_category]=$A15)*(CrowdfundingTable[outcome]=$E$2))),2),"")} -> 1.5 | F15: {=IFERROR(ROUND(MEDIAN(_xlfn._xlws.FILTER(CrowdfundingTable[percent_funded],CrowdfundingTable[primary_category]=$A15)),2),"")} -> 1.5
A16: audio | B16: {=IFERROR(ROUND(MEDIAN(_xlfn._xlws.FILTER(CrowdfundingTable[percent_funded],(CrowdfundingTable[subcategory]=$A16)*(CrowdfundingTable[outcome]=$B$2))),2),"")} | C16: {=IFERROR(ROUND(MEDIAN(_xlfn._xlws.FILTER(CrowdfundingTable[percent_funded],(CrowdfundingTable[subcategory]=$A16)*(CrowdfundingTable[outcome]=$C$2))),2),"")} | D16: {=IFERROR(ROUND(MEDIAN(_xlfn._xlws.FILTER(CrowdfundingTable[percent_funded],(CrowdfundingTable[subcategory]=$A16)*(CrowdfundingTable[outcome]=$D$2))),2),"")} | E16: {=IFERROR(ROUND(MEDIAN(_xlfn._xlws.FILTER(CrowdfundingTable[percent_funded],(CrowdfundingTable[subcategory]=$A16)*(CrowdfundingTable[outcome]=$E$2))),2),"")} -> 1.5 | F16: {=IFERROR(ROUND(MEDIAN(_xlfn._xlws.FILTER(CrowdfundingTable[percent_funded],CrowdfundingTable[subcategory]=$A16)),2),"")} -> 1.5
A17: music | B17: {=IFERROR(ROUND(MEDIAN(_xlfn._xlws.FILTER(CrowdfundingTable[percent_funded],(CrowdfundingTable[primary_category]=$A17)*(CrowdfundingTable[outcome]=$B$2))),2),"")} -> 0.38 | C17: {=IFERROR(ROUND(MEDIAN(_xlfn._xlws.FILTER(CrowdfundingTable[percent_funded],(CrowdfundingTable[primary_category]=$A17)*(CrowdfundingTable[outcome]=$C$2))),2),"")} -> 0.45 | D17: {=IFERROR(ROUND(MEDIAN(_xlfn._xlws.FILTER(CrowdfundingTable[percent_funded],(CrowdfundingTable[primary_category]=$A17)*(CrowdfundingTable[outcome]=$D$2))),2),"")} | E17: {=IFERROR(ROUND(MEDIAN(_xlfn._xlws.FILTER(CrowdfundingTable[percent_funded],(CrowdfundingTable[primary_category]=$A17)*(CrowdfundingTable[outcome]=$E$2))),2),"")} -> 2.08 | F17: {=IFERROR(ROUND(MEDIAN(_xlfn._xlws.FILTER(CrowdfundingTable[percent_funded],CrowdfundingTable[primary_category]=$A17)),2),"")} -> 1.23
A18: electric music | B18: {=IFERROR(ROUND(MEDIAN(_xlfn._xlws.FILTER(CrowdfundingTable[percent_funded],(CrowdfundingTable[subcategory]=$A18)*(CrowdfundingTable[outcome]=$B$2))),2),"")} | C18: {=IFERROR(ROUND(MEDIAN(_xlfn._xlws.FILTER(CrowdfundingTable[percent_funded],(CrowdfundingTable[subcategory]=$A18)*(CrowdfundingTable[outcome]=$C$2))),2),"")} -> 0.41 | D18: {=IFERROR(ROUND(MEDIAN(_xlfn._xlws.FILTER(CrowdfundingTable[percent_funded],(CrowdfundingTable[subcategory]=$A18)*(CrowdfundingTable[outcome]=$D$2))),2),"")} | E18: {=IFERROR(ROUND(MEDIAN(_xlfn._xlws.FILTER(CrowdfundingTable[percent_funded],(CrowdfundingTable[subcategory]=$A18)*(CrowdfundingTable[outcome]=$E$2))),2),"")} -> 2.09 | F18: {=IFERROR(ROUND(MEDIAN(_xlfn._xlws.FILTER(CrowdfundingTable[percent_funded],CrowdfundingTable[subcategory]=$A18)),2),"")} -> 1.46
A19: indie rock | B19: {=IFERROR(ROUND(MEDIAN(_xlfn._xlws.FILTER(CrowdfundingTable[percent_funded],(CrowdfundingTable[subcategory]=$A19)*(CrowdfundingTable[outcome]=$B$2))),2),"")} -> 0.11 | C19: {=IFERROR(ROUND(MEDIAN(_xlfn._xlws.FILTER(CrowdfundingTable[percent_funded],(CrowdfundingTable[subcategory]=$A19)*(CrowdfundingTable[outcome]=$C$2))),2),"")} -> 0.57 | D19: {=IFERROR(ROUND(MEDIAN(_xlfn._xlws.FILTER(CrowdfundingTable[percent_funded],(CrowdfundingTable[subcategory]=$A19)*(CrowdfundingTable[outcome]=$D$2))),2),"")} | E19: {=IFERROR(ROUND(MEDIAN(_xlfn._xlws.FILTER(CrowdfundingTable[percent_funded],(CrowdfundingTable[subcategory]=$A19)*(CrowdfundingTable[outcome]=$E$2))),2),"")} -> 1.76 | F19: {=IFERROR(ROUND(MEDIAN(_xlfn._xlws.FILTER(CrowdfundingTable[percent_funded],CrowdfundingTable[subcategory]=$A19)),2),"")} -> 1.04
A20: jazz | B20: {=IFERROR(ROUND(MEDIAN(_xlfn._xlws.FILTER(CrowdfundingTable[percent_funded],(CrowdfundingTable[subcategory]=$A20)*(CrowdfundingTable[outcome]=$B$2))),2),"")} -> 0.19 | C20: {=IFERROR(ROUND(MEDIAN(_xlfn._xlws.FILTER(CrowdfundingTable[percent_funded],(CrowdfundingTable[subcategory]=$A20)*(CrowdfundingTable[outcome]=$C$2))),2),"")} -> 0.19 | D20: {=IFERROR(ROUND(MEDIAN(_xlfn._xlws.FILTER(CrowdfundingTable[percent_funded],(CrowdfundingTable[subcategory]=$A20)*(CrowdfundingTable[outcome]=$D$2))),2),"")} | E20: {=IFERROR(ROUND(MEDIAN(_xlfn._xlws.FILTER(CrowdfundingTable[percent_funded],(CrowdfundingTable[subcategory]=$A20)*(CrowdfundingTable[outcome]=$E$2))),2),"")} -> 3.46 | F20: {=IFERROR(ROUND(MEDIAN(_xlfn._xlws.FILTER(CrowdfundingTable[percent_funded],CrowdfundingTable[subcategory]=$A20)),2),"")} -> 1.77
A21: metal | B21: {=IFERROR(ROUND(MEDIAN(_xlfn._xlws.FILTER(CrowdfundingTable[percent_funded],(CrowdfundingTable[subcategory]=$A21)*(CrowdfundingTable[outcome]=$B$2))),2),"")} | C21: {=IFERROR(ROUND(MEDIAN(_xlfn._xlws.FILTER(CrowdfundingTable[percent_funded],(CrowdfundingTable[subcategory]=$A21)*(CrowdfundingTable[outcome]=$C$2))),2),"")} -> 0.37 | D21: {=IFERROR(ROUND(MEDIAN(_xlfn._xlws.FILTER(CrowdfundingTable[percent_funded],(CrowdfundingTable[subcategory]=$A21)*(CrowdfundingTable[outcome]=$D$2))),2),"")} | E21: {=IFERROR(ROUND(MEDIAN(_xlfn._xlws.FILTER(CrowdfundingTable[percent_funded],(CrowdfundingTable[subcategory]=$A21)*(CrowdfundingTable[outcome]=$E$2))),2),"")} -> 3.16 | F21: {=IFERROR(ROUND(MEDIAN(_xlfn._xlws.FILTER(CrowdfundingTable[percent_funded],CrowdfundingTable[subcategory]=$A21)),2),"")} -> 1.22
A22: rock | B22: {=IFERROR(ROUND(MEDIAN(_xlfn._xlws.FILTER(CrowdfundingTable[percent_funded],(CrowdfundingTable[subcategory]=$A22)*(CrowdfundingTable[outcome]=$B$2))),2),"")} -> 0.57 | C22: {=IFERROR(ROUND(MEDIAN(_xlfn._xlws.FILTER(CrowdfundingTable[percent_funded],(CrowdfundingTable[subcategory]=$A22)*(CrowdfundingTable[outcome]=$C$2))),2),"")} -> 0.45 | D22: {=IFERROR(ROUND(MEDIAN(_xlfn._xlws.FILTER(CrowdfundingTable[percent_funded],(CrowdfundingTable[subcategory]=$A22)*(CrowdfundingTable[outcome]=$D$2))),2),"")} | E22: {=IFERROR(ROUND(MEDIAN(_xlfn._xlws.FILTER(CrowdfundingTable[percent_funded],(CrowdfundingTable[subcategory]=$A22)*(CrowdfundingTable[outcome]=$E$2))),2),"")} -> 2.13 | F22: {=IFERROR(ROUND(MEDIAN(_xlfn._xlws.FILTER(CrowdfundingTable[percent_funded],CrowdfundingTable[subcategory]=$A22)),2),"")} -> 1.25
A23: world music | B23: {=IFERROR(ROUND(MEDIAN(_xlfn._xlws.FILTER(CrowdfundingTable[percent_funded],(CrowdfundingTable[subcategory]=$A23)*(CrowdfundingTable[outcome]=$B$2))),2),"")} | C23: {=IFERROR(ROUND(MEDIAN(_xlfn._xlws.FILTER(CrowdfundingTable[percent_funded],(CrowdfundingTable[subcategory]=$A23)*(CrowdfundingTable[outcome]=$C$2))),2),"")} | D23: {=IFERROR(ROUND(MEDIAN(_xlfn._xlws.FILTER(CrowdfundingTable[percent_funded],(CrowdfundingTable[subcategory]=$A23)*(CrowdfundingTable[outcome]=$D$2))),2),"")} | E23: {=IFERROR(ROUND(MEDIAN(_xlfn._xlws.FILTER(CrowdfundingTable[percent_funded],(CrowdfundingTable[subcategory]=$A23)*(CrowdfundingTable[outcome]=$E$2))),2),"")} -> 1.76 | F23: {=IFERROR(ROUND(MEDIAN(_xlfn._xlws.FILTER(CrowdfundingTable[percent_funded],CrowdfundingTable[subcategory]=$A23)),2),"")} -> 1.76
A24: photography | B24: {=IFERROR(ROUND(MEDIAN(_xlfn._xlws.FILTER(CrowdfundingTable[percent_funded],(CrowdfundingTable[primary_category]=$A24)*(CrowdfundingTable[outcome]=$B$2))),2),"")} -> 0.6 | C24: {=IFERROR(ROUND(MEDIAN(_xlfn._xlws.FILTER(CrowdfundingTable[percent_funded],(CrowdfundingTable[primary_category]=$A24)*(CrowdfundingTable[outcome]=$C$2))),2),"")} -> 0.36 | D24: {=IFERROR(ROUND(MEDIAN(_xlfn._xlws.FILTER(CrowdfundingTable[percent_funded],(CrowdfundingTable[primary_category]=$A24)*(CrowdfundingTable[outcome]=$D$2))),2),"")} -> 0.01 | E24: {=IFERROR(ROUND(MEDIAN(_xlfn._xlws.FILTER(CrowdfundingTable[percent_funded],(CrowdfundingTable[primary_category]=$A24)*(CrowdfundingTable[outcome]=$E$2))),2),"")} -> 2.55 | F24: {=IFERROR(ROUND(MEDIAN(_xlfn._xlws.FILTER(CrowdfundingTable[percent_funded],CrowdfundingTable[primary_category]=$A24)),2),"")} -> 1.44
A25: photography books | B25: {=IFERROR(ROUND(MEDIAN(_xlfn._xlws.FILTER(CrowdfundingTable[percent_funded],(CrowdfundingTable[subcategory]=$A25)*(CrowdfundingTable[outcome]=$B$2))),2),"")} -> 0.6 | C25: {=IFERROR(ROUND(MEDIAN(_xlfn._xlws.FILTER(CrowdfundingTable[percent_funded],(CrowdfundingTable[subcategory]=$A25)*(CrowdfundingTable[outcome]=$C$2))),2),"")} -> 0.36 | D25: {=IFERROR(ROUND(MEDIAN(_xlfn._xlws.FILTER(CrowdfundingTable[percent_funded],(CrowdfundingTable[subcategory]=$A25)*(CrowdfundingTable[outcome]=$D$2))),2),"")} -> 0.01 | E25: {=IFERROR(ROUND(MEDIAN(_xlfn._xlws.FILTER(CrowdfundingTable[percent_funded],(CrowdfundingTable[subcategory]=$A25)*(CrowdfundingTable[outcome]=$E$2))),2),"")} -> 2.55 | F25: {=IFERROR(ROUND(MEDIAN(_xlfn._xlws.FILTER(CrowdfundingTable[percent_funded],CrowdfundingTable[subcategory]=$A25)),2),"")} -> 1.44
A26: publishing | B26: {=IFERROR(ROUND(MEDIAN(_xlfn._xlws.FILTER(CrowdfundingTable[percent_funded],(CrowdfundingTable[primary_category]=$A26)*(CrowdfundingTable[outcome]=$B$2))),2),"")} -> 0.36 | C26: {=IFERROR(ROUND(MEDIAN(_xlfn._xlws.FILTER(CrowdfundingTable[percent_funded],(CrowdfundingTable[primary_category]=$A26)*(CrowdfundingTable[outcome]=$C$2))),2),"")} -> 0.42 | D26: {=IFERROR(ROUND(MEDIAN(_xlfn._xlws.FILTER(CrowdfundingTable[percent_funded],(CrowdfundingTable[primary_category]=$A26)*(CrowdfundingTable[outcome]=$D$2))),2),"")} -> 0.02 | E26: {=IFERROR(ROUND(MEDIAN(_xlfn._xlws.FILTER(CrowdfundingTable[percent_funded],(CrowdfundingTable[primary_category]=$A26)*(CrowdfundingTable[outcome]=$E$2))),2),"")} -> 2.28 | F26: {=IFERROR(ROUND(MEDIAN(_xlfn._xlws.FILTER(CrowdfundingTable[percent_funded],CrowdfundingTable[primary_category]=$A26)),2),"")} -> 1.26
A27: fiction | B27: {=IFERROR(ROUND(MEDIAN(_xlfn._xlws.FILTER(CrowdfundingTable[percent_funded],(CrowdfundingTable[subcategory]=$A27)*(CrowdfundingTable[outcome]=$B$2))),2),"")} -> 0.39 | C27: {=IFERROR(ROUND(MEDIAN(_xlfn._xlws.FILTER(CrowdfundingTable[percent_funded],(CrowdfundingTable[subcategory]=$A27)*(CrowdfundingTable[outcome]=$C$2))),2),"")} -> 0.64 | D27: {=IFERROR(ROUND(MEDIAN(_xlfn._xlws.FILTER(CrowdfundingTable[percent_funded],(CrowdfundingTable[subcategory]=$A27)*(CrowdfundingTable[outcome]=$D$2))),2),"")} | E27: {=IFERROR(ROUND(MEDIAN(_xlfn._xlws.FILTER(CrowdfundingTable[percent_funded],(CrowdfundingTable[subcategory]=$A27)*(CrowdfundingTable[outcome]=$E$2))),2),"")} -> 1.5 | F27: {=IFERROR(ROUND(MEDIAN(_xlfn._xlws.FILTER(CrowdfundingTable[percent_funded],CrowdfundingTable[subcategory]=$A27)),2),"")} -> 1.1
A28: nonfiction | B28: {=IFERROR(ROUND(MEDIAN(_xlfn._xlws.FILTER(CrowdfundingTable[percent_funded],(CrowdfundingTable[subcategory]=$A28)*(CrowdfundingTable[outcome]=$B$2))),2),"")} -> 0.33 | C28: {=IFERROR(ROUND(MEDIAN(_xlfn._xlws.FILTER(CrowdfundingTable[percent_funded],(CrowdfundingTable[subcategory]=$A28)*(CrowdfundingTable[outcome]=$C$2))),2),"")} -> 0.41 | D28: {=IFERROR(ROUND(MEDIAN(_xlfn._xlws.FILTER(CrowdfundingTable[percent_funded],(CrowdfundingTable[subcategory]=$A28)*(CrowdfundingTable[outcome]=$D$2))),2),"")} -> 0.02 | E28: {=IFERROR(ROUND(MEDIAN(_xlfn._xlws.FILTER(CrowdfundingTable[percent_funded],(CrowdfundingTable[subcategory]=$A28)*(CrowdfundingTable[outcome]=$E$2))),2),"")} -> 2.32 | F28: {=IFERROR(ROUND(MEDIAN(_xlfn._xlws.FILTER(CrowdfundingTable[percent_funded],CrowdfundingTable[subcategory]=$A28)),2),"")} -> 1.46
A29: radio & podcasts | B29: {=IFERROR(ROUND(MEDIAN(_xlfn._xlws.FILTER(CrowdfundingTable[percent_funded],(CrowdfundingTable[subcategory]=$A29)*(CrowdfundingTable[outcome]=$B$2))),2),"")} | C29: {=IFERROR(ROUND(MEDIAN(_xlfn._xlws.FILTER(CrowdfundingTable[percent_funded],(CrowdfundingTable[subcategory]=$A29)*(CrowdfundingTable[outcome]=$C$2))),2),"")} -> 0.33 | D29: {=IFERROR(ROUND(MEDIAN(_xlfn._xlws.FILTER(CrowdfundingTable[percent_funded],(CrowdfundingTable[subcategory]=$A29)*(CrowdfundingTable[outcome]=$D$2))),2),"")} | E29: {=IFERROR(ROUND(MEDIAN(_xlfn._xlws.FILTER(CrowdfundingTable[percent_funded],(CrowdfundingTable[subcategory]=$A29)*(CrowdfundingTable[outcome]=$E$2))),2),"")} -> 1.74 | F29: {=IFERROR(ROUND(MEDIAN(_xlfn._xlws.FILTER(CrowdfundingTable[percent_funded],CrowdfundingTable[subcategory]=$A29)),2),"")} -> 1.01
A30: translations | B30: {=IFERROR(ROUND(MEDIAN(_xlfn._xlws.FILTER(CrowdfundingTable[percent_funded],(CrowdfundingTable[subcategory]=$A30)*(CrowdfundingTable[outcome]=$B$2))),2),"")} | C30: {=IFERROR(ROUND(MEDIAN(_xlfn._xlws.FILTER(CrowdfundingTable[percent_funded],(CrowdfundingTable[subcategory]=$A30)*(CrowdfundingTable[outcome]=$C$2))),2),"")} -> 0.41 | D30: {=IFERROR(ROUND(MEDIAN(_xlfn._xlws.FILTER(CrowdfundingTable[percent_funded],(CrowdfundingTable[subcategory]=$A30)*(CrowdfundingTable[outcome]=$D$2))),2),"")} | E30: {=IFERROR(ROUND(MEDIAN(_xlfn._xlws.FILTER(CrowdfundingTable[percent_funded],(CrowdfundingTable[subcategory]=$A30)*(CrowdfundingTable[outcome]=$E$2))),2),"")} -> 2.41 | F30: {=IFERROR(ROUND(MEDIAN(_xlfn._xlws.FILTER(CrowdfundingTable[percent_funded],CrowdfundingTable[subcategory]=$A30)),2),"")} -> 1.58
A31: technology | B31: {=IFERROR(ROUND(MEDIAN(_xlfn._xlws.FILTER(CrowdfundingTable[percent_funded],(CrowdfundingTable[primary_category]=$A31)*(CrowdfundingTable[outcome]=$B$2))),2),"")} -> 0.64 | C31: {=IFERROR(ROUND(MEDIAN(_xlfn._xlws.FILTER(CrowdfundingTable[percent_funded],(CrowdfundingTable[primary_category]=$A31)*(CrowdfundingTable[outcome]=$C$2))),2),"")} -> 0.62 | D31: {=IFERROR(ROUND(MEDIAN(_xlfn._xlws.FILTER(CrowdfundingTable[percent_funded],(CrowdfundingTable[primary_category]=$A31)*(CrowdfundingTable[outcome]=$D$2))),2),"")} -> 0.61 | E31: {=IFERROR(ROUND(MEDIAN(_xlfn._xlws.FILTER(CrowdfundingTable[percent_funded],(CrowdfundingTable[primary_category]=$A31)*(CrowdfundingTable[outcome]=$E$2))),2),"")} -> 1.99 | F31: {=IFERROR(ROUND(MEDIAN(_xlfn._xlws.FILTER(CrowdfundingTable[percent_funded],CrowdfundingTable[primary_category]=$A31)),2),"")} -> 1.32
A32: wearables | B32: {=IFERROR(ROUND(MEDIAN(_xlfn._xlws.FILTER(CrowdfundingTable[percent_funded],(CrowdfundingTable[subcategory]=$A32)*(CrowdfundingTable[outcome]=$B$2))),2),"")} | C32: {=IFERROR(ROUND(MEDIAN(_xlfn._xlws.FILTER(CrowdfundingTable[percent_funded],(CrowdfundingTable[subcategory]=$A32)*(CrowdfundingTable[outcome]=$C$2))),2),"")} -> 0.59 | D32: {=IFERROR(ROUND(MEDIAN(_xlfn._xlws.FILTER(CrowdfundingTable[percent_funded],(CrowdfundingTable[subcategory]=$A32)*(CrowdfundingTable[outcome]=$D$2))),2),"")} -> 0.59 | E32: {=IFERROR(ROUND(MEDIAN(_xlfn._xlws.FILTER(CrowdfundingTable[percent_funded],(CrowdfundingTable[subcategory]=$A32)*(CrowdfundingTable[outcome]=$E$2))),2),"")} -> 2.21 | F32: {=IFERROR(ROUND(MEDIAN(_xlfn._xlws.FILTER(CrowdfundingTable[percent_funded],CrowdfundingTable[subcategory]=$A32)),2),"")} -> 1.44
A33: web | B33: {=IFERROR(ROUND(MEDIAN(_xlfn._xlws.FILTER(CrowdfundingTable[percent_funded],(CrowdfundingTable[subcategory]=$A33)*(CrowdfundingTable[outcome]=$B$2))),2),"")} -> 0.64 | C33: {=IFERROR(ROUND(MEDIAN(_xlfn._xlws.FILTER(CrowdfundingTable[percent_funded],(CrowdfundingTable[subcategory]=$A33)*(CrowdfundingTable[outcome]=$C$2))),2),"")} -> 0.63 | D33: {=IFERROR(ROUND(MEDIAN(_xlfn._xlws.FILTER(CrowdfundingTable[percent_funded],(CrowdfundingTable[subcategory]=$A33)*(CrowdfundingTable[outcome]=$D$2))),2),"")} -> 0.62 | E33: {=IFERROR(ROUND(MEDIAN(_xlfn._xlws.FILTER(CrowdfundingTable[percent_funded],(CrowdfundingTable[subcategory]=$A33)*(CrowdfundingTable[outcome]=$E$2))),2),"")} -> 1.88 | F33: {=IFERROR(ROUND(MEDIAN(_xlfn._xlws.FILTER(CrowdfundingTable[percent_funded],CrowdfundingTable[subcategory]=$A33)),2),"")} -> 1.28
A34: theater | B34: {=IFERROR(ROUND(MEDIAN(_xlfn._xlws.FILTER(CrowdfundingTable[percent_funded],(CrowdfundingTable[primary_category]=$A34)*(CrowdfundingTable[outcome]=$B$2))),2),"")} -> 0.48 | C34: {=IFERROR(ROUND(MEDIAN(_xlfn._xlws.FILTER(CrowdfundingTable[percent_funded],(CrowdfundingTable[primary_category]=$A34)*(CrowdfundingTable[outcome]=$C$2))),2),"")} -> 0.51 | D34: {=IFERROR(ROUND(MEDIAN(_xlfn._xlws.FILTER(CrowdfundingTable[percent_funded],(CrowdfundingTable[primary_category]=$A34)*(CrowdfundingTable[outcome]=$D$2))),2),"")} -> 0.31 | E34: {=IFERROR(ROUND(MEDIAN(_xlfn._xlws.FILTER(CrowdfundingTable[percent_funded],(CrowdfundingTable[primary_category]=$A34)*(CrowdfundingTable[outcome]=$E$2))),2),"")} -> 2.02 | F34: {=IFERROR(ROUND(MEDIAN(_xlfn._xlws.FILTER(CrowdfundingTable[percent_funded],CrowdfundingTable[primary_category]=$A34)),2),"")} -> 1.13
A35: plays | B35: {=IFERROR(ROUND(MEDIAN(_xlfn._xlws.FILTER(CrowdfundingTable[percent_funded],(CrowdfundingTable[subcategory]=$A35)*(CrowdfundingTable[outcome]=$B$2))),2),"")} -> 0.48 | C35: {=IFERROR(ROUND(MEDIAN(_xlfn._xlws.FILTER(CrowdfundingTable[percent_funded],(CrowdfundingTable[subcategory]=$A35)*(CrowdfundingTable[outcome]=$C$2))),2),"")} -> 0.51 | D35: {=IFERROR(ROUND(MEDIAN(_xlfn._xlws.FILTER(CrowdfundingTable[percent_funded],(CrowdfundingTable[subcategory]=$A35)*(CrowdfundingTable[outcome]=$D$2))),2),"")} -> 0.31 | E35: {=IFERROR(ROUND(MEDIAN(_xlfn._xlws.FILTER(CrowdfundingTable[percent_funded],(CrowdfundingTable[subcategory]=$A35)*(CrowdfundingTable[outcome]=$E$2))),2),"")} -> 2.02 | F35: {=IFERROR(ROUND(MEDIAN(_xlfn._xlws.FILTER(CrowdfundingTable[percent_funded],CrowdfundingTable[subcategory]=$A35)),2),"")} -> 1.13
A36: Grand Total | B36: {=IFERROR(ROUND(MEDIAN(_xlfn._xlws.FILTER(CrowdfundingTable[percent_funded],CrowdfundingTable[outcome]=$B$2)),2),"")} -> 0.43 | C36: {=IFERROR(ROUND(MEDIAN(_xlfn._xlws.FILTER(CrowdfundingTable[percent_funded],CrowdfundingTable[outcome]=$C$2)),2),"")} -> 0.51 | D36: {=IFERROR(ROUND(MEDIAN(_xlfn._xlws.FILTER(CrowdfundingTable[percent_funded],CrowdfundingTable[outcome]=$D$2)),2),"")} -> 0.5 | E36: {=IFERROR(ROUND(MEDIAN(_xlfn._xlws.FILTER(CrowdfundingTable[percent_funded],CrowdfundingTable[outcome]=$E$2)),2),"")} -> 2.12 | F36: =IFERROR(ROUND(MEDIAN(CrowdfundingTable[percent_funded]),2),"") -> 1.22

Sheet Outcomes vs. Weekdays
A1: country | B1: (All) | I1: country | J1: (All)
A2: Years | B2: (All) | I2: Years | J2: (All)
A4: Count of outcome | B4: Column Labels | I4: Count of outcome | J4: Column Labels | N4: Confidence Interval
A5: Row Labels | B5: canceled | C5: failed | D5: successful | E5: Grand Total | I5: Row Labels | J5: canceled | K5: failed | L5: successful | M5: Grand Total | N5: (successful)
A6: Sun | B6: 8 | C6: 47 | D6: 78 | E6: 133 | I6: Sun | J6: 0.060150376 | K6: 0.35338346 | L6: 0.58646617 | M6: 1 | N6: =GETPIVOTDATA("outcome",$I$4,"outcome","successful","weekday_created","Sun")-1.96*GETPIVOTDATA("outcome",$I$4,"outcome","successful","weekday_created","Sun")*(1-GETPIVOTDATA("outcome",$I$4,"outcome","successful","weekday_created","Sun"))/GETPIVOTDATA("outcome",$A$4,"weekday_created","Sun") -> 0.58289213 | O6: =GETPIVOTDATA("outcome",$I$4,"outcome","successful","weekday_created","Sun")+1.96*GETPIVOTDATA("outcome",$I$4,"outcome","successful","weekday_created","Sun")*(1-GETPIVOTDATA("outcome",$I$4,"outcome","successful","weekday_created","Sun"))/GETPIVOTDATA("outcome",$A$4,"weekday_created","Sun") -> 0.5900402
A7: Mon | B7: 6 | C7: 46 | D7: 100 | E7: 152 | I7: Mon | J7: 0.039473684 | K7: 0.30263158 | L7: 0.65789474 | M7: 1 | N7: =GETPIVOTDATA("outcome",$I$4,"outcome","successful","weekday_created","Mon")-1.96*GETPIVOTDATA("outcome",$I$4,"outcome","successful","weekday_created","Mon")*(1-GETPIVOTDATA("outcome",$I$4,"outcome","successful","weekday_created","Mon"))/GETPIVOTDATA("outcome",$A$4,"weekday_created","Mon") -> 0.65499253 | O7: =GETPIVOTDATA("outcome",$I$4,"outcome","successful","weekday_created","Mon")+1.96*GETPIVOTDATA("outcome",$I$4,"outcome","successful","weekday_created","Mon")*(1-GETPIVOTDATA("outcome",$I$4,"outcome","successful","weekday_created","Mon"))/GETPIVOTDATA("outcome",$A$4,"weekday_created","Mon") -> 0.66079695
A8: Tue | B8: 7 | C8: 58 | D8: 84 | E8: 149 | I8: Tue | J8: 0.046979866 | K8: 0.38926174 | L8: 0.56375839 | M8: 1 | N8: =GETPIVOTDATA("outcome",$I$4,"outcome","successful","weekday_created","Tue")-1.96*GETPIVOTDATA("outcome",$I$4,"outcome","successful","weekday_created","Tue")*(1-GETPIVOTDATA("outcome",$I$4,"outcome","successful","weekday_created","Tue"))/GETPIVOTDATA("outcome",$A$4,"weekday_created","Tue") -> 0.56052327 | O8: =GETPIVOTDATA("outcome",$I$4,"outcome","successful","weekday_created","Tue")+1.96*GETPIVOTDATA("outcome",$I$4,"outcome","successful","weekday_created","Tue")*(1-GETPIVOTDATA("outcome",$I$4,"outcome","successful","weekday_created","Tue"))/GETPIVOTDATA("outcome",$A$4,"weekday_created","Tue") -> 0.56699351
A9: Wed | B9: 9 | C9: 51 | D9: 76 | E9: 136 | I9: Wed | J9: 0.066176471 | K9: 0.375 | L9: 0.55882353 | M9: 1 | N9: =GETPIVOTDATA("outcome",$I$4,"outcome","successful","weekday_created","Wed")-1.96*GETPIVOTDATA("outcome",$I$4,"outcome","successful","weekday_created","Wed")*(1-GETPIVOTDATA("outcome",$I$4,"outcome","successful","weekday_created","Wed"))/GETPIVOTDATA("outcome",$A$4,"weekday_created","Wed") -> 0.55527046 | O9: =GETPIVOTDATA("outcome",$I$4,"outcome","successful","weekday_created","Wed")+1.96*GETPIVOTDATA("outcome",$I$4,"outcome","successful","weekday_created","Wed")*(1-GETPIVOTDATA("outcome",$I$4,"outcome","successful","weekday_created","Wed"))/GETPIVOTDATA("outcome",$A$4,"weekday_created","Wed") -> 0.5623766
A10: Thu | B10: 11 | C10: 53 | D10: 78 | E10: 142 | I10: Thu | J10: 0.077464789 | K10: 0.37323944 | L10: 0.54929577 | M10: 1 | N10: =GETPIVOTDATA("outcome",$I$4,"outcome","successful","weekday_created","Thu")-1.96*GETPIVOTDATA("outcome",$I$4,"outcome","successful","weekday_created","Thu")*(1-GETPIVOTDATA("outcome",$I$4,"outcome","successful","weekday_created","Thu"))/GETPIVOTDATA("outcome",$A$4,"weekday_created","Thu") -> 0.54587861 | O10: =GETPIVOTDATA("outcome",$I$4,"outcome","successful","weekday_created","Thu")+1.96*GETPIVOTDATA("outcome",$I$4,"outcome","successful","weekday_created","Thu")*(1-GETPIVOTDATA("outcome",$I$4,"outcome","successful","weekday_created","Thu"))/GETPIVOTDATA("outcome",$A$4,"weekday_created","Thu") -> 0.55271294
A11: Fri | B11: 8 | C11: 64 | D11: 75 | E11: 147 | I11: Fri | J11: 0.054421769 | K11: 0.43537415 | L11: 0.51020408 | M11: 1 | N11: =GETPIVOTDATA("outcome",$I$4,"outcome","successful","weekday_created","Fri")-1.96*GETPIVOTDATA("outcome",$I$4,"outcome","successful","weekday_created","Fri")*(1-GETPIVOTDATA("outcome",$I$4,"outcome","successful","weekday_created","Fri"))/GETPIVOTDATA("outcome",$A$4,"weekday_created","Fri") -> 0.50687214 | O11: =GETPIVOTDATA("outcome",$I$4,"outcome","successful","weekday_created","Fri")+1.96*GETPIVOTDATA("outcome",$I$4,"outcome","successful","weekday_created","Fri")*(1-GETPIVOTDATA("outcome",$I$4,"outcome","successful","weekday_created","Fri"))/GETPIVOTDATA("outcome",$A$4,"weekday_created","Fri") -> 0.51353603
A12: Sat | B12: 8 | C12: 45 | D12: 74 | E12: 127 | I12: Sat | J12: 0.062992126 | K12: 0.35433071 | L12: 0.58267717 | M12: 1 | N12: =GETPIVOTDATA("outcome",$I$4,"outcome","successful","weekday_created","Sat")-1.96*GETPIVOTDATA("outcome",$I$4,"outcome","successful","weekday_created","Sat")*(1-GETPIVOTDATA("outcome",$I$4,"outcome","successful","weekday_created","Sat"))/GETPIVOTDATA("outcome",$A$4,"weekday_created","Sat") -> 0.57892439 | O12: =GETPIVOTDATA("outcome",$I$4,"outcome","successful","weekday_created","Sat")+1.96*GETPIVOTDATA("outcome",$I$4,"outcome","successful","weekday_created","Sat")*(1-GETPIVOTDATA("outcome",$I$4,"outcome","successful","weekday_created","Sat"))/GETPIVOTDATA("outcome",$A$4,"weekday_created","Sat") -> 0.58642994
A13: Grand Total | B13: 57 | C13: 364 | D13: 565 | E13: 986 | I13: Grand Total | J13: 0.057809331 | K13: 0.36916836 | L13: 0.57302231 | M13: 1 | N13: =GETPIVOTDATA("outcome",$I$4,"outcome","successful")-1.96*GETPIVOTDATA("outcome",$I$4,"outcome","successful")*(1-GETPIVOTDATA("outcome",$I$4,"outcome","successful"))/GETPIVOTDATA("outcome",$A$4) -> 0.57253595 | O13: =GETPIVOTDATA("outcome",$I$4,"outcome","successful")+1.96*GETPIVOTDATA("outcome",$I$4,"outcome","successful")*(1-GETPIVOTDATA("outcome",$I$4,"outcome","successful"))/GETPIVOTDATA("outcome",$A$4) -> 0.57350867

Sheet Outcomes vs. Months
A1: country | B1: (All) | J1: country | K1: (All)
A2: Years | B2: (All) | J2: Years | K2: (All)
A4: Count of outcome | B4: Column Labels | J4: Count of outcome | K4: Column Labels | O4: Confidence Interval
A5: Row Labels | B5: canceled | C5: failed | D5: successful | E5: Grand Total | J5: Row Labels | K5: canceled | L5: failed | M5: successful | N5: Grand Total | O5: (successful)
A6: Jan | B6: 6 | C6: 36 | D6: 49 | E6: 91 | J6: Jan | K6: 0.065934066 | L6: 0.3956044 | M6: 0.53846154 | N6: 1 | O6: =GETPIVOTDATA("outcome",$J$4,"outcome","successful","Date Created Conversion",1)-1.96*GETPIVOTDATA("outcome",$J$4,"outcome","successful","Date Created Conversion",1)*(1-GETPIVOTDATA("outcome",$J$4,"outcome","successful","Date Created Conversion",1))/GETPIVOTDATA("outcome",$A$4,"Date Created Conversion",1) -> 0.53310878 | P6: =GETPIVOTDATA("outcome",$J$4,"outcome","successful","Date Created Conversion",1)+1.96*GETPIVOTDATA("outcome",$J$4,"outcome","successful","Date Created Conversion",1)*(1-GETPIVOTDATA("outcome",$J$4,"outcome","successful","Date Created Conversion",1))/GETPIVOTDATA("outcome",$A$4,"Date Created Conversion",1) -> 0.54381429
A7: Feb | B7: 7 | C7: 28 | D7: 44 | E7: 79 | J7: Feb | K7: 0.088607595 | L7: 0.35443038 | M7: 0.55696203 | N7: 1 | O7: =GETPIVOTDATA("outcome",$J$4,"outcome","successful","Date Created Conversion",2)-1.96*GETPIVOTDATA("outcome",$J$4,"outcome","successful","Date Created Conversion",2)*(1-GETPIVOTDATA("outcome",$J$4,"outcome","successful","Date Created Conversion",2))/GETPIVOTDATA("outcome",$A$4,"Date Created Conversion",2) -> 0.55083999 | P7: =GETPIVOTDATA("outcome",$J$4,"outcome","successful","Date Created Conversion",2)+1.96*GETPIVOTDATA("outcome",$J$4,"outcome","successful","Date Created Conversion",2)*(1-GETPIVOTDATA("outcome",$J$4,"outcome","successful","Date Created Conversion",2))/GETPIVOTDATA("outcome",$A$4,"Date Created Conversion",2) -> 0.56308406
A8: Mar | B8: 4 | C8: 33 | D8: 49 | E8: 86 | J8: Mar | K8: 0.046511628 | L8: 0.38372093 | M8: 0.56976744 | N8: 1 | O8: =GETPIVOTDATA("outcome",$J$4,"outcome","successful","Date Created Conversion",3)-1.96*GETPIVOTDATA("outcome",$J$4,"outcome","successful","Date Created Conversion",3)*(1-GETPIVOTDATA("outcome",$J$4,"outcome","successful","Date Created Conversion",3))/GETPIVOTDATA("outcome",$A$4,"Date Created Conversion",3) -> 0.5641807 | P8: =GETPIVOTDATA("outcome",$J$4,"outcome","successful","Date Created Conversion",3)+1.96*GETPIVOTDATA("outcome",$J$4,"outcome","successful","Date Created Conversion",3)*(1-GETPIVOTDATA("outcome",$J$4,"outcome","successful","Date Created Conversion",3))/GETPIVOTDATA("outcome",$A$4,"Date Created Conversion",3) -> 0.57535418
A9: Apr | B9: 1 | C9: 30 | D9: 46 | E9: 77 | J9: Apr | K9: 0.012987013 | L9: 0.38961039 | M9: 0.5974026 | N9: 1 | O9: =GETPIVOTDATA("outcome",$J$4,"outcome","successful","Date Created Conversion",4)-1.96*GETPIVOTDATA("outcome",$J$4,"outcome","successful","Date Created Conversion",4)*(1-GETPIVOTDATA("outcome",$J$4,"outcome","successful","Date Created Conversion",4))/GETPIVOTDATA("outcome",$A$4,"Date Created Conversion",4) -> 0.59128046 | P9: =GETPIVOTDATA("outcome",$J$4,"outcome","successful","Date Created Conversion",4)+1.96*GETPIVOTDATA("outcome",$J$4,"outcome","successful","Date Created Conversion",4)*(1-GETPIVOTDATA("outcome",$J$4,"outcome","successful","Date Created Conversion",4))/GETPIVOTDATA("outcome",$A$4,"Date Created Conversion",4) -> 0.60352474
A10: May | B10: 3 | C10: 35 | D10: 46 | E10: 84 | J10: May | K10: 0.035714286 | L10: 0.41666667 | M10: 0.54761905 | N10: 1 | O10: =GETPIVOTDATA("outcome",$J$4,"outcome","successful","Date Created Conversion",5)-1.96*GETPIVOTDATA("outcome",$J$4,"outcome","successful","Date Created Conversion",5)*(1-GETPIVOTDATA("outcome",$J$4,"outcome","successful","Date Created Conversion",5))/GETPIVOTDATA("outcome",$A$4,"Date Created Conversion",5) -> 0.54183862 | P10: =GETPIVOTDATA("outcome",$J$4,"outcome","successful","Date Created Conversion",5)+1.96*GETPIVOTDATA("outcome",$J$4,"outcome","successful","Date Created Conversion",5)*(1-GETPIVOTDATA("outcome",$J$4,"outcome","successful","Date Created Conversion",5))/GETPIVOTDATA("outcome",$A$4,"Date Created Conversion",5) -> 0.55339947
A11: Jun | B11: 3 | C11: 28 | D11: 55 | E11: 86 | J11: Jun | K11: 0.034883721 | L11: 0.3255814 | M11: 0.63953488 | N11: 1 | O11: =GETPIVOTDATA("outcome",$J$4,"outcome","successful","Date Created Conversion",6)-1.96*GETPIVOTDATA("outcome",$J$4,"outcome","successful","Date Created Conversion",6)*(1-GETPIVOTDATA("outcome",$J$4,"outcome","successful","Date Created Conversion",6))/GETPIVOTDATA("outcome",$A$4,"Date Created Conversion",6) -> 0.63428094 | P11: =GETPIVOTDATA("outcome",$J$4,"outcome","successful","Date Created Conversion",6)+1.96*GETPIVOTDATA("outcome",$J$4,"outcome","successful","Date Created Conversion",6)*(1-GETPIVOTDATA("outcome",$J$4,"outcome","successful","Date Created Conversion",6))/GETPIVOTDATA("outcome",$A$4,"Date Created Conversion",6) -> 0.64478882
A12: Jul | B12: 4 | C12: 31 | D12: 58 | E12: 93 | J12: Jul | K12: 0.043010753 | L12: 0.33333333 | M12: 0.62365591 | N12: 1 | O12: =GETPIVOTDATA("outcome",$J$4,"outcome","successful","Date Created Conversion",7)-1.96*GETPIVOTDATA("outcome",$J$4,"outcome","successful","Date Created Conversion",7)*(1-GETPIVOTDATA("outcome",$J$4,"outcome","successful","Date Created Conversion",7))/GETPIVOTDATA("outcome",$A$4,"Date Created Conversion",7) -> 0.61870935 | P12: =GETPIVOTDATA("outcome",$J$4,"outcome","successful","Date Created Conversion",7)+1.96*GETPIVOTDATA("outcome",$J$4,"outcome","successful","Date Created Conversion",7)*(1-GETPIVOTDATA("outcome",$J$4,"outcome","successful","Date Created Conversion",7))/GETPIVOTDATA("outcome",$A$4,"Date Created Conversion",7) -> 0.62860247
A13: Aug | B13: 8 | C13: 35 | D13: 41 | E13: 84 | J13: Aug | K13: 0.095238095 | L13: 0.41666667 | M13: 0.48809524 | N13: 1 | O13: =GETPIVOTDATA("outcome",$J$4,"outcome","successful","Date Created Conversion",8)-1.96*GETPIVOTDATA("outcome",$J$4,"outcome","successful","Date Created Conversion",8)*(1-GETPIVOTDATA("outcome",$J$4,"outcome","successful","Date Created Conversion",8))/GETPIVOTDATA("outcome",$A$4,"Date Created Conversion",8) -> 0.48226521 | P13: =GETPIVOTDATA("outcome",$J$4,"outcome","successful","Date Created Conversion",8)+1.96*GETPIVOTDATA("outcome",$J$4,"outcome","successful","Date Created Conversion",8)*(1-GETPIVOTDATA("outcome",$J$4,"outcome","successful","Date Created Conversion",8))/GETPIVOTDATA("outcome",$A$4,"Date Created Conversion",8) -> 0.49392526
A14: Sep | B14: 5 | C14: 23 | D14: 45 | E14: 73 | J14: Sep | K14: 0.068493151 | L14: 0.31506849 | M14: 0.61643836 | N14: 1 | O14: =GETPIVOTDATA("outcome",$J$4,"outcome","successful","Date Created Conversion",9)-1.96*GETPIVOTDATA("outcome",$J$4,"outcome","successful","Date Created Conversion",9)*(1-GETPIVOTDATA("outcome",$J$4,"outcome","successful","Date Created Conversion",9))/GETPIVOTDATA("outcome",$A$4,"Date Created Conversion",9) -> 0.61009005 | P14: =GETPIVOTDATA("outcome",$J$4,"outcome","successful","Date Created Conversion",9)+1.96*GETPIVOTDATA("outcome",$J$4,"outcome","successful","Date Created Conversion",9)*(1-GETPIVOTDATA("outcome",$J$4,"outcome","successful","Date Created Conversion",9))/GETPIVOTDATA("outcome",$A$4,"Date Created Conversion",9) -> 0.62278666
A15: Oct | B15: 6 | C15: 26 | D15: 45 | E15: 77 | J15: Oct | K15: 0.077922078 | L15: 0.33766234 | M15: 0.58441558 | N15: 1 | O15: =GETPIVOTDATA("outcome",$J$4,"outcome","successful","Date Created Conversion",10)-1.96*GETPIVOTDATA("outcome",$J$4,"outcome","successful","Date Created Conversion",10)*(1-GETPIVOTDATA("outcome",$J$4,"outcome","successful","Date Created Conversion",10))/GETPIVOTDATA("outcome",$A$4,"Date Created Conversion",10) -> 0.57823334 | P15: =GETPIVOTDATA("outcome",$J$4,"outcome","successful","Date Created Conversion",10)+1.96*GETPIVOTDATA("outcome",$J$4,"outcome","successful","Date Created Conversion",10)*(1-GETPIVOTDATA("outcome",$J$4,"outcome","successful","Date Created Conversion",10))/GETPIVOTDATA("outcome",$A$4,"Date Created Conversion",10) -> 0.59059783
A16: Nov | B16: 3 | C16: 27 | D16: 45 | E16: 75 | J16: Nov | K16: 0.04 | L16: 0.36 | M16: 0.6 | N16: 1 | O16: =GETPIVOTDATA("outcome",$J$4,"outcome","successful","Date Created Conversion",11)-1.96*GETPIVOTDATA("outcome",$J$4,"outcome","successful","Date Created Conversion",11)*(1-GETPIVOTDATA("outcome",$J$4,"outcome","successful","Date Created Conversion",11))/GETPIVOTDATA("outcome",$A$4,"Date Created Conversion",11) -> 0.593728 | P16: =GETPIVOTDATA("outcome",$J$4,"outcome","successful","Date Created Conversion",11)+1.96*GETPIVOTDATA("outcome",$J$4,"outcome","successful","Date Created Conversion",11)*(1-GETPIVOTDATA("outcome",$J$4,"outcome","successful","Date Created Conversion",11))/GETPIVOTDATA("outcome",$A$4,"Date Created Conversion",11) -> 0.606272
A17: Dec | B17: 7 | C17: 32 | D17: 42 | E17: 81 | J17: Dec | K17: 0.086419753 | L17: 0.39506173 | M17: 0.51851852 | N17: 1 | O17: =GETPIVOTDATA("outcome",$J$4,"outcome","successful","Date Created Conversion",12)-1.96*GETPIVOTDATA("outcome",$J$4,"outcome","successful","Date Created Conversion",12)*(1-GETPIVOTDATA("outcome",$J$4,"outcome","successful","Date Created Conversion",12))/GETPIVOTDATA("outcome",$A$4,"Date Created Conversion",12) -> 0.51247743 | P17: =GETPIVOTDATA("outcome",$J$4,"outcome","successful","Date Created Conversion",12)+1.96*GETPIVOTDATA("outcome",$J$4,"outcome","successful","Date Created Conversion",12)*(1-GETPIVOTDATA("outcome",$J$4,"outcome","successful","Date Created Conversion",12))/GETPIVOTDATA("outcome",$A$4,"Date Created Conversion",12) -> 0.5245596
A18: Grand Total | B18: 57 | C18: 364 | D18: 565 | E18: 986 | J18: Grand Total | K18: 0.057809331 | L18: 0.36916836 | M18: 0.57302231 | N18: 1 | O18: =GETPIVOTDATA("outcome",$J$4,"outcome","successful")-1.96*GETPIVOTDATA("outcome",$J$4,"outcome","successful")*(1-GETPIVOTDATA("outcome",$J$4,"outcome","successful"))/GETPIVOTDATA("outcome",$A$4) -> 0.57253595 | P18: =GETPIVOTDATA("outcome",$J$4,"outcome","successful")+1.96*GETPIVOTDATA("outcome",$J$4,"outcome","successful")*(1-GETPIVOTDATA("outcome",$J$4,"outcome","successful"))/GETPIVOTDATA("outcome",$A$4) -> 0.57350867

Sheet  Outcomes vs. Years
A1: country | B1: (All) | J1: country | K1: (All)
A3: Count of outcome | B3: Column Labels | J3: Count of outcome | K3: Column Labels | O3: Confidence Interval
A4: Row Labels | B4: canceled | C4: failed | D4: successful | E4: Grand Total | J4: Row Labels | K4: canceled | L4: failed | M4: successful | N4: Grand Total | O4: (successful)
A5: 2010 | B5: 14 | C5: 35 | D5: 58 | E5: 107 | J5: 2010 | K5: 0.13084112 | L5: 0.3271028 | M5: 0.54205607 | N5: 1 | O5: =GETPIVOTDATA("outcome",$J$3,"outcome","successful","Years",2010)-1.96*GETPIVOTDATA("outcome",$J$3,"outcome","successful","Years",2010)*(1-GETPIVOTDATA("outcome",$J$3,"outcome","successful","Years",2010))/GETPIVOTDATA("outcome",$A$3,"Years",2010) -> 0.53750903 | P5: =GETPIVOTDATA("outcome",$J$3,"outcome","successful","Years",2010)+1.96*GETPIVOTDATA("outcome",$J$3,"outcome","successful","Years",2010)*(1-GETPIVOTDATA("outcome",$J$3,"outcome","successful","Years",2010))/GETPIVOTDATA("outcome",$A$3,"Years",2010) -> 0.54660312
A6: 2011 | B6: 6 | C6: 40 | D6: 56 | E6: 102 | J6: 2011 | K6: 0.058823529 | L6: 0.39215686 | M6: 0.54901961 | N6: 1 | O6: =GETPIVOTDATA("outcome",$J$3,"outcome","successful","Years",2011)-1.96*GETPIVOTDATA("outcome",$J$3,"outcome","successful","Years",2011)*(1-GETPIVOTDATA("outcome",$J$3,"outcome","successful","Years",2011))/GETPIVOTDATA("outcome",$A$3,"Years",2011) -> 0.54426186 | P6: =GETPIVOTDATA("outcome",$J$3,"outcome","successful","Years",2011)+1.96*GETPIVOTDATA("outcome",$J$3,"outcome","successful","Years",2011)*(1-GETPIVOTDATA("outcome",$J$3,"outcome","successful","Years",2011))/GETPIVOTDATA("outcome",$A$3,"Years",2011) -> 0.55377736
A7: 2012 | B7: 4 | C7: 32 | D7: 45 | E7: 81 | J7: 2012 | K7: 0.049382716 | L7: 0.39506173 | M7: 0.55555556 | N7: 1 | O7: =GETPIVOTDATA("outcome",$J$3,"outcome","successful","Years",2012)-1.96*GETPIVOTDATA("outcome",$J$3,"outcome","successful","Years",2012)*(1-GETPIVOTDATA("outcome",$J$3,"outcome","successful","Years",2012))/GETPIVOTDATA("outcome",$A$3,"Years",2012) -> 0.54958086 | P7: =GETPIVOTDATA("outcome",$J$3,"outcome","successful","Years",2012)+1.96*GETPIVOTDATA("outcome",$J$3,"outcome","successful","Years",2012)*(1-GETPIVOTDATA("outcome",$J$3,"outcome","successful","Years",2012))/GETPIVOTDATA("outcome",$A$3,"Years",2012) -> 0.56153025
A8: 2013 | B8: 4 | C8: 35 | D8: 48 | E8: 87 | J8: 2013 | K8: 0.045977011 | L8: 0.40229885 | M8: 0.55172414 | N8: 1 | O8: =GETPIVOTDATA("outcome",$J$3,"outcome","successful","Years",2013)-1.96*GETPIVOTDATA("outcome",$J$3,"outcome","successful","Years",2013)*(1-GETPIVOTDATA("outcome",$J$3,"outcome","successful","Years",2013))/GETPIVOTDATA("outcome",$A$3,"Years",2013) -> 0.54615223 | P8: =GETPIVOTDATA("outcome",$J$3,"outcome","successful","Years",2013)+1.96*GETPIVOTDATA("outcome",$J$3,"outcome","successful","Years",2013)*(1-GETPIVOTDATA("outcome",$J$3,"outcome","successful","Years",2013))/GETPIVOTDATA("outcome",$A$3,"Years",2013) -> 0.55729605
A9: 2014 | B9: 4 | C9: 37 | D9: 60 | E9: 101 | J9: 2014 | K9: 0.03960396 | L9: 0.36633663 | M9: 0.59405941 | N9: 1 | O9: =GETPIVOTDATA("outcome",$J$3,"outcome","successful","Years",2014)-1.96*GETPIVOTDATA("outcome",$J$3,"outcome","successful","Years",2014)*(1-GETPIVOTDATA("outcome",$J$3,"outcome","successful","Years",2014))/GETPIVOTDATA("outcome",$A$3,"Years",2014) -> 0.58937961 | P9: =GETPIVOTDATA("outcome",$J$3,"outcome","successful","Years",2014)+1.96*GETPIVOTDATA("outcome",$J$3,"outcome","successful","Years",2014)*(1-GETPIVOTDATA("outcome",$J$3,"outcome","successful","Years",2014))/GETPIVOTDATA("outcome",$A$3,"Years",2014) -> 0.5987392
A10: 2015 | B10: 7 | C10: 42 | D10: 54 | E10: 103 | J10: 2015 | K10: 0.067961165 | L10: 0.40776699 | M10: 0.52427184 | N10: 1 | O10: =GETPIVOTDATA("outcome",$J$3,"outcome","successful","Years",2015)-1.96*GETPIVOTDATA("outcome",$J$3,"outcome","successful","Years",2015)*(1-GETPIVOTDATA("outcome",$J$3,"outcome","successful","Years",2015))/GETPIVOTDATA("outcome",$A$3,"Years",2015) -> 0.51952577 | P10: =GETPIVOTDATA("outcome",$J$3,"outcome","successful","Years",2015)+1.96*GETPIVOTDATA("outcome",$J$3,"outcome","successful","Years",2015)*(1-GETPIVOTDATA("outcome",$J$3,"outcome","successful","Years",2015))/GETPIVOTDATA("outcome",$A$3,"Years",2015) -> 0.52901792
A11: 2016 | B11: 5 | C11: 42 | D11: 49 | E11: 96 | J11: 2016 | K11: 0.052083333 | L11: 0.4375 | M11: 0.51041667 | N11: 1 | O11: =GETPIVOTDATA("outcome",$J$3,"outcome","successful","Years",2016)-1.96*GETPIVOTDATA("outcome",$J$3,"outcome","successful","Years",2016)*(1-GETPIVOTDATA("outcome",$J$3,"outcome","successful","Years",2016))/GETPIVOTDATA("outcome",$A$3,"Years",2016) -> 0.50531472 | P11: =GETPIVOTDATA("outcome",$J$3,"outcome","successful","Years",2016)+1.96*GETPIVOTDATA("outcome",$J$3,"outcome","successful","Years",2016)*(1-GETPIVOTDATA("outcome",$J$3,"outcome","successful","Years",2016))/GETPIVOTDATA("outcome",$A$3,"Years",2016) -> 0.51551862
A12: 2017 | B12: 5 | C12: 28 | D12: 67 | E12: 100 | J12: 2017 | K12: 0.05 | L12: 0.28 | M12: 0.67 | N12: 1 | O12: =GETPIVOTDATA("outcome",$J$3,"outcome","successful","Years",2017)-1.96*GETPIVOTDATA("outcome",$J$3,"outcome","successful","Years",2017)*(1-GETPIVOTDATA("outcome",$J$3,"outcome","successful","Years",2017))/GETPIVOTDATA("outcome",$A$3,"Years",2017) -> 0.66566644 | P12: =GETPIVOTDATA("outcome",$J$3,"outcome","successful","Years",2017)+1.96*GETPIVOTDATA("outcome",$J$3,"outcome","successful","Years",2017)*(1-GETPIVOTDATA("outcome",$J$3,"outcome","successful","Years",2017))/GETPIVOTDATA("outcome",$A$3,"Years",2017) -> 0.67433356
A13: 2018 | B13: 4 | C13: 35 | D13: 61 | E13: 100 | J13: 2018 | K13: 0.04 | L13: 0.35 | M13: 0.61 | N13: 1 | O13: =GETPIVOTDATA("outcome",$J$3,"outcome","successful","Years",2018)-1.96*GETPIVOTDATA("outcome",$J$3,"outcome","successful","Years",2018)*(1-GETPIVOTDATA("outcome",$J$3,"outcome","successful","Years",2018))/GETPIVOTDATA("outcome",$A$3,"Years",2018) -> 0.60533716 | P13: =GETPIVOTDATA("outcome",$J$3,"outcome","successful","Years",2018)+1.96*GETPIVOTDATA("outcome",$J$3,"outcome","successful","Years",2018)*(1-GETPIVOTDATA("outcome",$J$3,"outcome","successful","Years",2018))/GETPIVOTDATA("outcome",$A$3,"Years",2018) -> 0.61466284
A14: 2019 | B14: 4 | C14: 36 | D14: 67 | E14: 107 | J14: 2019 | K14: 0.037383178 | L14: 0.3364486 | M14: 0.62616822 | N14: 1 | O14: =GETPIVOTDATA("outcome",$J$3,"outcome","successful","Years",2019)-1.96*GETPIVOTDATA("outcome",$J$3,"outcome","successful","Years",2019)*(1-GETPIVOTDATA("outcome",$J$3,"outcome","successful","Years",2019))/GETPIVOTDATA("outcome",$A$3,"Years",2019) -> 0.62188037 | P14: =GETPIVOTDATA("outcome",$J$3,"outcome","successful","Years",2019)+1.96*GETPIVOTDATA("outcome",$J$3,"outcome","successful","Years",2019)*(1-GETPIVOTDATA("outcome",$J$3,"outcome","successful","Years",2019))/GETPIVOTDATA("outcome",$A$3,"Years",2019) -> 0.63045607
A15: Grand Total | B15: 57 | C15: 362 | D15: 565 | E15: 984 | J15: Grand Total | K15: 0.057926829 | L15: 0.36788618 | M15: 0.57418699 | N15: 1 | O15: =GETPIVOTDATA("outcome",$J$3,"outcome","successful")-1.96*GETPIVOTDATA("outcome",$J$3,"outcome","successful")*(1-GETPIVOTDATA("outcome",$J$3,"outcome","successful"))/GETPIVOTDATA("outcome",$A$3) -> 0.57369999 | P15: =GETPIVOTDATA("outcome",$J$3,"outcome","successful")+1.96*GETPIVOTDATA("outcome",$J$3,"outcome","successful")*(1-GETPIVOTDATA("outcome",$J$3,"outcome","successful"))/GETPIVOTDATA("outcome",$A$3) -> 0.574674

Sheet Backer Distributions
A1: Backer Distributions
A3: Outcome | B3: Median Backers | C3: Mean Backers | D3: Std. Dev.
A4: Successful | B4: {=ROUND(MEDIAN(_xlfn._xlws.FILTER(CrowdfundingTable[backers_count],CrowdfundingTable[outcome]="successful")),2)} -> 201 | C4: {=ROUND(AVERAGE(_xlfn._xlws.FILTER(CrowdfundingTable[backers_count],CrowdfundingTable[outcome]="successful")),2)} -> 851.15 | D4: {=ROUND(STDEV(_xlfn._xlws.FILTER(CrowdfundingTable[backers_count],CrowdfundingTable[outcome]="successful")),2)} -> 1267.37
A5: Failed | B5: {=ROUND(MEDIAN(_xlfn._xlws.FILTER(CrowdfundingTable[backers_count],CrowdfundingTable[outcome]="failed")),2)} -> 114.5 | C5: {=ROUND(AVERAGE(_xlfn._xlws.FILTER(CrowdfundingTable[backers_count],CrowdfundingTable[outcome]="failed")),2)} -> 585.62 | D5: {=ROUND(STDEV(_xlfn._xlws.FILTER(CrowdfundingTable[backers_count],CrowdfundingTable[outcome]="failed")),2)} -> 961.31
A6: Canceled | B6: {=ROUND(MEDIAN(_xlfn._xlws.FILTER(CrowdfundingTable[backers_count],CrowdfundingTable[outcome]="canceled")),2)} -> 139 | C6: {=ROUND(AVERAGE(_xlfn._xlws.FILTER(CrowdfundingTable[backers_count],CrowdfundingTable[outcome]="canceled")),2)} -> 434.53 | D6: {=ROUND(STDEV(_xlfn._xlws.FILTER(CrowdfundingTable[backers_count],CrowdfundingTable[outcome]="canceled")),2)} -> 573.55
A7: Live | B7: {=ROUND(MEDIAN(_xlfn._xlws.FILTER(CrowdfundingTable[backers_count],CrowdfundingTable[outcome]="live")),2)} -> 148.5 | C7: {=ROUND(AVERAGE(_xlfn._xlws.FILTER(CrowdfundingTable[backers_count],CrowdfundingTable[outcome]="live")),2)} -> 583.93 | D7: {=ROUND(STDEV(_xlfn._xlws.FILTER(CrowdfundingTable[backers_count],CrowdfundingTable[outcome]="live")),2)} -> 968.41

Sheet Campaign Summary
A1: Goal | B1: Successful | C1: Failed | D1: Canceled | E1: Live | F1: Count | G1: Success Rate (%) | H1: Failure Rate (%) | I1: Canceled Rate (%) | J1: Live Rate (%)
A2: < $5,000 | B2: =COUNTIFS(Crowdfunding!$D$2:$D$1001,"<5000",Crowdfunding!$G$2:$G$1001,"=successful") -> 221 | C2: =COUNTIFS(Crowdfunding!$D$2:$D$1001,"<5000",Crowdfunding!$G$2:$G$1001,"=failed") -> 58 | D2: =COUNTIFS(Crowdfunding!$D$2:$D$1001,"<5000",Crowdfunding!$G$2:$G$1001,"=canceled") -> 3 | E2: =COUNTIFS(Crowdfunding!$D$2:$D$1001,"<5000",Crowdfunding!$G$2:$G$1001,"=live") -> 3 | F2: =SUM(B2:E2) -> 285 | G2: =B2/$F2 -> 0.7754386 | H2: =C2/$F2 -> 0.20350877 | I2: =D2/$F2 -> 0.010526316 | J2: =E2/$F2 -> 0.010526316
A3: $5,000 - $10,000 | B3: =COUNTIFS(Crowdfunding!$D$2:$D$1001,">=5000",Crowdfunding!$D$2:$D$1001,"<10000",Crowdfunding!$G$2:$G$1001,"=successful") -> 164 | C3: =COUNTIFS(Crowdfunding!$D$2:$D$1001,">=5000",Crowdfunding!$D$2:$D$1001,"<10000",Crowdfunding!$G$2:$G$1001,"=failed") -> 126 | D3: =COUNTIFS(Crowdfunding!$D$2:$D$1001,">=5000",Crowdfunding!$D$2:$D$1001,"<10000",Crowdfunding!$G$2:$G$1001,"=canceled") -> 25 | E3: =COUNTIFS(Crowdfunding!$D$2:$D$1001,">=5000",Crowdfunding!$D$2:$D$1001,"<10000",Crowdfunding!$G$2:$G$1001,"=live") -> 2 | F3: =SUM(B3:E3) -> 317 | G3: =B3/$F3 -> 0.51735016 | H3: =C3/$F3 -> 0.39747634 | I3: =D3/$F3 -> 0.078864353 | J3: =E3/$F3 -> 0.0063091483
A4: $10,000 - $15,000 | B4: =COUNTIFS(Crowdfunding!$D$2:$D$1001,">=10000",Crowdfunding!$D$2:$D$1001,"<15000",Crowdfunding!$G$2:$G$1001,"=successful") -> 4 | C4: =COUNTIFS(Crowdfunding!$D$2:$D$1001,">=10000",Crowdfunding!$D$2:$D$1001,"<15000",Crowdfunding!$G$2:$G$1001,"=failed") -> 5 | D4: =COUNTIFS(Crowdfunding!$D$2:$D$1001,">=10000",Crowdfunding!$D$2:$D$1001,"<15000",Crowdfunding!$G$2:$G$1001,"=canceled") -> 0 | E4: =COUNTIFS(Crowdfunding!$D$2:$D$1001,">=10000",Crowdfunding!$D$2:$D$1001,"<15000",Crowdfunding!$G$2:$G$1001,"=live") -> 0 | F4: =SUM(B4:E4) -> 9 | G4: =B4/$F4 -> 0.44444444 | H4: =C4/$F4 -> 0.55555556 | I4: =D4/$F4 -> 0 | J4: =E4/$F4 -> 0
A5: $15,000 - $35,000 | B5: =COUNTIFS(Crowdfunding!$D$2:$D$1001,">=15000",Crowdfunding!$D$2:$D$1001,"<35000",Crowdfunding!$G$2:$G$1001,"=successful") -> 35 | C5: =COUNTIFS(Crowdfunding!$D$2:$D$1001,">=15000",Crowdfunding!$D$2:$D$1001,"<35000",Crowdfunding!$G$2:$G$1001,"=failed") -> 3 | D5: =COUNTIFS(Crowdfunding!$D$2:$D$1001,">=15000",Crowdfunding!$D$2:$D$1001,"<35000",Crowdfunding!$G$2:$G$1001,"=canceled") -> 0 | E5: =COUNTIFS(Crowdfunding!$D$2:$D$1001,">=15000",Crowdfunding!$D$2:$D$1001,"<35000",Crowdfunding!$G$2:$G$1001,"=live") -> 0 | F5: =SUM(B5:E5) -> 38 | G5: =B5/$F5 -> 0.92105263 | H5: =C5/$F5 -> 0.078947368 | I5: =D5/$F5 -> 0 | J5: =E5/$F5 -> 0
A6: $35,000 - $100,000 | B6: =COUNTIFS(Crowdfunding!$D$2:$D$1001,">=35000",Crowdfunding!$D$2:$D$1001,"<100000",Crowdfunding!$G$2:$G$1001,"=successful") -> 97 | C6: =COUNTIFS(Crowdfunding!$D$2:$D$1001,">=35000",Crowdfunding!$D$2:$D$1001,"<100000",Crowdfunding!$G$2:$G$1001,"=failed") -> 52 | D6: =COUNTIFS(Crowdfunding!$D$2:$D$1001,">=35000",Crowdfunding!$D$2:$D$1001,"<100000",Crowdfunding!$G$2:$G$1001,"=canceled") -> 7 | E6: =COUNTIFS(Crowdfunding!$D$2:$D$1001,">=35000",Crowdfunding!$D$2:$D$1001,"<=100000",Crowdfunding!$G$2:$G$1001,"=live") -> 3 | F6: =SUM(B6:E6) -> 159 | G6: =B6/$F6 -> 0.61006289 | H6: =C6/$F6 -> 0.32704403 | I6: =D6/$F6 -> 0.044025157 | J6: =E6/$F6 -> 0.018867925
A7: > $100,000 | B7: =COUNTIFS(Crowdfunding!$D$2:$D$1001,">=100000",Crowdfunding!$G$2:$G$1001,"=successful") -> 44 | C7: =COUNTIFS(Crowdfunding!$D$2:$D$1001,">=100000",Crowdfunding!$G$2:$G$1001,"=failed") -> 120 | D7: =COUNTIFS(Crowdfunding!$D$2:$D$1001,">=100000",Crowdfunding!$G$2:$G$1001,"=canceled") -> 22 | E7: =COUNTIFS(Crowdfunding!$D$2:$D$1001,">=100000",Crowdfunding!$G$2:$G$1001,"=live") -> 6 | F7: =SUM(B7:E7) -> 192 | G7: =B7/$F7 -> 0.22916667 | H7: =C7/$F7 -> 0.625 | I7: =D7/$F7 -> 0.11458333 | J7: =E7/$F7 -> 0.03125

Sheet Statistical Analysis (Goals)
A1: {=_xlfn._xlws.FILTER(CrowdfundingTable[outcome],CrowdfundingTable[outcome]="successful")} -> successful | B1: {=_xlfn._xlws.FILTER(CrowdfundingTable[goal],CrowdfundingTable[outcome]="successful")} -> 1400 | D1: {=_xlfn._xlws.FILTER(CrowdfundingTable[outcome],CrowdfundingTable[outcome]="failed")} -> failed | E1: {=_xlfn._xlws.FILTER(CrowdfundingTable[goal],CrowdfundingTable[outcome]="failed")} -> 100 | F1: {=_xlfn._xlws.FILTER(CrowdfundingTable[outcome],CrowdfundingTable[outcome]="canceled")} -> canceled | G1: {=_xlfn._xlws.FILTER(CrowdfundingTable[goal],CrowdfundingTable[outcome]="canceled")} -> 9100 | H1: {=_xlfn._xlws.FILTER(CrowdfundingTable[outcome],CrowdfundingTable[outcome]="live")} -> live | I1: {=_xlfn._xlws.FILTER(CrowdfundingTable[goal],CrowdfundingTable[outcome]="live")} -> 110100 | M1: Category | N1: Successful Campaigns | O1: Failed Campaigns | P1: Canceled Campaigns | Q1: Live Campaigns
A2: successful | B2: 108400 | D2: failed | E2: 4200 | F2: canceled | G2: 107500 | H2: live | I2: 194500 | M2: Total Goals | N2: =SUM($B$1:$B$565) -> 14919000 | O2: =SUM($E$1:$E$565) -> 23806900 | P2: =SUM(_xlfn.ANCHORARRAY(G1)) -> 4032600 | Q2: =SUM(_xlfn.ANCHORARRAY(I1)) -> 1224600
A3: successful | B3: 7600 | D3: failed | E3: 7600 | F3: canceled | G3: 7900 | H3: live | I3: 153700 | M3: Mean | N3: =AVERAGE($B$1:$B$565) -> 26405.31 | O3: =AVERAGE($E$1:$E$565) -> 65403.571 | P3: =AVERAGE(_xlfn.ANCHORARRAY(G1)) -> 70747.368 | Q3: =AVERAGE(_xlfn.ANCHORARRAY(I1)) -> 87471.429
A4: successful | B4: 4500 | D4: failed | E4: 5200 | F4: canceled | G4: 108800 | H4: live | I4: 93800 | M4: Mode | N4: =MODE($B$1:$B$565) -> 1400 | O4: =MODE($E$1:$E$565) -> 100 | P4: =MODE(_xlfn.ANCHORARRAY(G1)) -> 8800 | Q4: =MODE(_xlfn.ANCHORARRAY(I1)) -> 153700
A5: successful | B5: 5200 | D5: failed | E5: 6200 | F5: canceled | G5: 70600 | H5: live | I5: 3800 | M5: Minimum | N5: =MIN($B$1:$B$565) -> 600 | O5: =MIN($E$1:$E$565) -> 100 | P5: =MIN(_xlfn.ANCHORARRAY(G1)) -> 100 | Q5: =MIN(_xlfn.ANCHORARRAY(I1)) -> 3600
A6: successful | B6: 4200 | D6: failed | E6: 6300 | F6: canceled | G6: 148500 | H6: live | I6: 153700 | M6: First Quartile (25%) | N6: =_xlfn.QUARTILE.EXC($B$1:$B$565,1) -> 3000 | O6: =_xlfn.QUARTILE.EXC($E$1:$E$565,1) -> 6600 | P6: =_xlfn.QUARTILE.EXC(_xlfn.ANCHORARRAY(G1),1) -> 8250 | Q6: =_xlfn.QUARTILE.EXC(_xlfn.ANCHORARRAY(I1),1) -> 7400
A7: successful | B7: 1700 | D7: failed | E7: 6300 | F7: canceled | G7: 82800 | H7: live | I7: 189500 | M7: Median (50%) | N7: =_xlfn.QUARTILE.EXC($B$1:$B$565,2) -> 6200 | O7: =_xlfn.QUARTILE.EXC($E$1:$E$565,2) -> 9900 | P7: =_xlfn.QUARTILE.EXC(_xlfn.ANCHORARRAY(G1),2) -> 36400 | Q7: =_xlfn.QUARTILE.EXC(_xlfn.ANCHORARRAY(I1),2) -> 82950
A8: successful | B8: 84600 | D8: failed | E8: 28200 | F8: canceled | G8: 8800 | H8: live | I8: 186700 | M8: Third Quartile (75%) | N8: =_xlfn.QUARTILE.EXC($B$1:$B$565,3) -> 34400 | O8: =_xlfn.QUARTILE.EXC($E$1:$E$565,3) -> 124775 | P8: =_xlfn.QUARTILE.EXC(_xlfn.ANCHORARRAY(G1),3) -> 137500 | Q8: =_xlfn.QUARTILE.EXC(_xlfn.ANCHORARRAY(I1),3) -> 161950
A9: successful | B9: 131800 | D9: failed | E9: 81200 | F9: canceled | G9: 36400 | H9: live | I9: 72100 | M9: Maximum | N9: =MAX($B$1:$B$565) -> 196900 | O9: =MAX($E$1:$E$565) -> 199200 | P9: =MAX(_xlfn.ANCHORARRAY(G1)) -> 194900 | Q9: =MAX(_xlfn.ANCHORARRAY(I1)) -> 194500
A10: successful | B10: 59100 | D10: failed | E10: 62500 | F10: canceled | G10: 191300 | H10: live | I10: 8600 | M10: Interquartile Range (IRQ) | N10: =$N$8-$N$6 -> 31400 | O10: =$O$8-$O$6 -> 118175 | P10: =$P$8-$P$6 -> 129250 | Q10: =$Q$8-$Q$6 -> 154550
A11: successful | B11: 4500 | D11: failed | E11: 94000 | F11: canceled | G11: 8300 | H11: live | I11: 3600 | M11: Upper Threshold | N11: =$N$8+(1.5*$N$10) -> 81500 | O11: =$O$8+(1.5*$O$10) -> 302037.5 | P11: =$P$8+(1.5*$P$10) -> 331375 | Q11: =$Q$8+(1.5*$Q$10) -> 393775
A12: successful | B12: 92400 | D12: failed | E12: 2000 | F12: canceled | G12: 9000 | H12: live | I12: 41000 | M12: Lower Threshold | N12: =$N$6-(1.5*$N$10) -> -44100 | O12: =$O$6-(1.5*$O$10) -> -170662.5 | P12: =$P$6-(1.5*$P$10) -> -185625 | Q12: =$Q$6-(1.5*$Q$10) -> -224425
A13: successful | B13: 5500 | D13: failed | E13: 101000 | F13: canceled | G13: 7200 | H13: live | I13: 3600 | M13: Count of Outliers | N13: =COUNTIF($B$1:$B$565, ">"&$N$11) -> 68 | O13: =COUNTIF($E$1:$E$565, ">"&$O$11) -> 0 | P13: =COUNTIF(_xlfn.ANCHORARRAY(G1), ">"&$P$11) -> 0 | Q13: =COUNTIF(_xlfn.ANCHORARRAY(I1), ">"&$Q$11) -> 0
A14: successful | B14: 130800 | D14: failed | E14: 9900 | F14: canceled | G14: 173900 | H14: live | I14: 9900 | M14: Standard Deviation | N14: =_xlfn.STDEV.P($B$1:$B$565) -> 40698.275 | O14: =_xlfn.STDEV.P($E$1:$E$565) -> 69788.377 | P14: =_xlfn.STDEV.P(_xlfn.ANCHORARRAY(G1)) -> 69935.399 | Q14: =_xlfn.STDEV.P(_xlfn.ANCHORARRAY(I1)) -> 74036.404
A15: successful | B15: 45900 | D15: failed | E15: 9500 | F15: canceled | G15: 112100 | M15: Skewness | N15: =_xlfn.SKEW.P($B$1:$B$565) -> 1.9625492 | O15: =_xlfn.SKEW.P($E$1:$E$565) -> 0.61404555 | P15: =_xlfn.SKEW.P(_xlfn.ANCHORARRAY(G1)) -> 0.4784409 | Q15: =_xlfn.SKEW.P(_xlfn.ANCHORARRAY(I1)) -> 0.18143727
A16: successful | B16: 9000 | D16: failed | E16: 100 | F16: canceled | G16: 6500
A17: successful | B17: 3500 | D17: failed | E17: 158100 | F17: canceled | G17: 4100
A18: successful | B18: 50200 | D18: failed | E18: 7200 | F18: canceled | G18: 8400
A19: successful | B19: 9300 | D19: failed | E19: 6000 | F19: canceled | G19: 136300
A20: successful | B20: 125500 | D20: failed | E20: 199200 | F20: canceled | G20: 114800
A21: successful | B21: 700 | D21: failed | E21: 4700 | F21: canceled | G21: 191000
A22: successful | B22: 8100 | D22: failed | E22: 2800 | F22: canceled | G22: 5400
A23: successful | B23: 3100 | D23: failed | E23: 2900 | F23: canceled | G23: 9300
A24: successful | B24: 8800 | D24: failed | E24: 122900 | F24: canceled | G24: 155200
A25: successful | B25: 5600 | D25: failed | E25: 9500 | F25: canceled | G25: 191000
A26: successful | B26: 1800 | D26: failed | E26: 57800 | F26: canceled | G26: 8300
A27: successful | B27: 90200 | D27: failed | E27: 106400 | F27: canceled | G27: 138700
... A57: successful | B57: 4800 | D57: failed | E57: 181200 | F57: canceled | G57: 111100
A58: successful | B58: 3400 | D58: failed | E58: 115000
A59: successful | B59: 20000 | D59: failed | E59: 7200
A60: successful | B60: 2900 | D60: failed | E60: 8600
A61: successful | B61: 900 | D61: failed | E61: 5100
A62: successful | B62: 69700 | D62: failed | E62: 1000
A63: successful | B63: 1300 | D63: failed | E63: 88800
A64: successful | B64: 7600 | D64: failed | E64: 8200
A65: successful | B65: 900 | D65: failed | E65: 3700
A66: successful | B66: 3700 | D66: failed | E66: 8400
A67: successful | B67: 119200 | D67: failed | E67: 42600
A68: successful | B68: 6800 | D68: failed | E68: 6600
A69: successful | B69: 3900 | D69: failed | E69: 8200
... A364: successful | B364: 600 | D364: failed | E364: 66600
A365: successful | B365: 35000
A366: successful | B366: 6900
A367: successful | B367: 5100
A368: successful | B368: 6900
A369: successful | B369: 48800
A370: successful | B370: 16200
A371: successful | B371: 97600
A372: successful | B372: 9700
A373: successful | B373: 62300
A374: successful | B374: 1400
A375: successful | B375: 5400
A376: successful | B376: 2300
... A565: successful | B565: 97300

Sheet Statistical Analysis (Pledges)
A1: {=_xlfn._xlws.FILTER(CrowdfundingTable[outcome],CrowdfundingTable[outcome]="successful")} -> successful | B1: {=_xlfn._xlws.FILTER(CrowdfundingTable[pledged],CrowdfundingTable[outcome]="successful")} -> 14560 | D1: {=_xlfn._xlws.FILTER(CrowdfundingTable[outcome],CrowdfundingTable[outcome]="failed")} -> failed | E1: {=_xlfn._xlws.FILTER(CrowdfundingTable[pledged],CrowdfundingTable[outcome]="failed")} -> 0 | F1: {=_xlfn._xlws.FILTER(CrowdfundingTable[outcome],CrowdfundingTable[outcome]="canceled")} -> canceled | G1: {=_xlfn._xlws.FILTER(CrowdfundingTable[pledged],CrowdfundingTable[outcome]="canceled")} -> 6089 | H1: {=_xlfn._xlws.FILTER(CrowdfundingTable[outcome],CrowdfundingTable[outcome]="live")} -> live | I1: {=_xlfn._xlws.FILTER(CrowdfundingTable[pledged],CrowdfundingTable[outcome]="live")} -> 21946 | M1: Category | N1: Successful Campaigns | O1: Failed Campaigns | P1: Canceled Campaigns | Q1: Live Campaigns
A2: successful | B2: 142523 | D2: failed | E2: 2477 | F2: canceled | G2: 51814 | H2: live | I2: 41212 | M2: Total Pledges | N2: =SUM($B$1:$B$565) -> 28436339 | O2: =SUM($E$1:$E$565) -> 12200146 | P2: =SUM(_xlfn.ANCHORARRAY(G1)) -> 1623364 | Q2: =SUM(_xlfn.ANCHORARRAY(I1)) -> 488206
A3: successful | B3: 13195 | D3: failed | E3: 5265 | F3: canceled | G3: 1901 | H3: live | I3: 1953 | M3: Mean | N3: =AVERAGE($B$1:$B$565) -> 50329.804 | O3: =AVERAGE($E$1:$E$565) -> 33516.885 | P3: =AVERAGE(_xlfn.ANCHORARRAY(G1)) -> 28480.07 | Q3: =AVERAGE(_xlfn.ANCHORARRAY(I1)) -> 34871.857
A4: successful | B4: 14741 | D4: failed | E4: 1090 | F4: canceled | G4: 65877 | H4: live | I4: 21477 | M4: Mode | N4: =MODE($B$1:$B$565) -> 14606 | O4: =MODE($E$1:$E$565) -> 2 | P4: =MODE(_xlfn.ANCHORARRAY(G1)) -> #N/A | Q4: =MODE(_xlfn.ANCHORARRAY(I1)) -> #N/A
A5: successful | B5: 13838 | D5: failed | E5: 3208 | F5: canceled | G5: 42596 | H5: live | I5: 2241 | M5: Minimum | N5: =MIN($B$1:$B$565) -> 1017 | O5: =MIN($E$1:$E$565) -> 0 | P5: =MIN(_xlfn.ANCHORARRAY(G1)) -> 4 | Q5: =MIN(_xlfn.ANCHORARRAY(I1)) -> 709
A6: successful | B6: 10295 | D6: failed | E6: 3030 | F6: canceled | G6: 4756 | H6: live | I6: 55536 | M6: First Quartile (25%) | N6: =_xlfn.QUARTILE.EXC($B$1:$B$565,1) -> 8731 | O6: =_xlfn.QUARTILE.EXC($E$1:$E$565,1) -> 2511 | P6: =_xlfn.QUARTILE.EXC(_xlfn.ANCHORARRAY(G1),1) -> 3241.5 | Q6: =_xlfn.QUARTILE.EXC(_xlfn.ANCHORARRAY(I1),1) -> 2205
A7: successful | B7: 11041 | D7: failed | E7: 5629 | F7: canceled | G7: 2721 | H7: live | I7: 117628 | M7: Median (50%) | N7: =_xlfn.QUARTILE.EXC($B$1:$B$565,2) -> 12516 | O7: =_xlfn.QUARTILE.EXC($E$1:$E$565,2) -> 6225 | P7: =_xlfn.QUARTILE.EXC(_xlfn.ANCHORARRAY(G1),2) -> 7220 | Q7: =_xlfn.QUARTILE.EXC(_xlfn.ANCHORARRAY(I1),2) -> 13819
A8: successful | B8: 134845 | D8: failed | E8: 18829 | F8: canceled | G8: 1518 | H8: live | I8: 178338 | M8: Third Quartile (75%) | N8: =_xlfn.QUARTILE.EXC($B$1:$B$565,3) -> 99148 | O8: =_xlfn.QUARTILE.EXC($E$1:$E$565,3) -> 57100 | P8: =_xlfn.QUARTILE.EXC(_xlfn.ANCHORARRAY(G1),3) -> 47743.5 | Q8: =_xlfn.QUARTILE.EXC(_xlfn.ANCHORARRAY(I1),3) -> 44793
A9: successful | B9: 147936 | D9: failed | E9: 38414 | F9: canceled | G9: 26914 | H9: live | I9: 30902 | M9: Maximum | N9: =MAX($B$1:$B$565) -> 199110 | O9: =MAX($E$1:$E$565) -> 188480 | P9: =MAX(_xlfn.ANCHORARRAY(G1)) -> 173191 | Q9: =MAX(_xlfn.ANCHORARRAY(I1)) -> 178338
A10: successful | B10: 75690 | D10: failed | E10: 30331 | F10: canceled | G10: 45004 | H10: live | I10: 4832 | M10: Interquartile Range (IRQ) | N10: =$N$8-$N$6 -> 90417 | O10: =$O$8-$O$6 -> 54589 | P10: =$P$8-$P$6 -> 44502 | Q10: =$Q$8-$Q$6 -> 42588
A11: successful | B11: 14942 | D11: failed | E11: 38533 | F11: canceled | G11: 6543 | H11: live | I11: 3174 | M11: Upper Threshold | N11: =$N$8+(1.5*$N$10) -> 234773.5 | O11: =$O$8+(1.5*$O$10) -> 138983.5 | P11: =$P$8+(1.5*$P$10) -> 114496.5 | Q11: =$Q$8+(1.5*$Q$10) -> 108675
A12: successful | B12: 104257 | D12: failed | E12: 1599 | F12: canceled | G12: 3496 | H12: live | I12: 709 | M12: Lower Threshold | N12: =$N$6-(1.5*$N$10) -> -126894.5 | O12: =$O$6-(1.5*$O$10) -> -79372.5 | P12: =$P$6-(1.5*$P$10) -> -63511.5 | Q12: =$Q$6-(1.5*$Q$10) -> -61677
A13: successful | B13: 11904 | D13: failed | E13: 87676 | F13: canceled | G13: 5523 | H13: live | I13: 2097 | M13: Count of Outliers | N13: =COUNTIF($B$1:$B$565, ">"&$N$11) -> 0 | O13: =COUNTIF($E$1:$E$565, ">"&$O$11) -> 18 | P13: =COUNTIF(_xlfn.ANCHORARRAY(G1), ">"&$P$11) -> 1 | Q13: =COUNTIF(_xlfn.ANCHORARRAY(I1), ">"&$Q$11) -> 2
A14: successful | B14: 137635 | D14: failed | E14: 5027 | F14: canceled | G14: 47260 | H14: live | I14: 6161 | M14: Standard Deviation | N14: =_xlfn.STDEV.P($B$1:$B$565) -> 64495.219 | O14: =_xlfn.STDEV.P($E$1:$E$565) -> 45711.612 | P14: =_xlfn.STDEV.P(_xlfn.ANCHORARRAY(G1)) -> 35318.473 | Q14: =_xlfn.STDEV.P(_xlfn.ANCHORARRAY(I1)) -> 50271.942
A15: successful | B15: 150965 | D15: failed | E15: 4530 | F15: canceled | G15: 19557 | M15: Skewness | N15: =_xlfn.SKEW.P($B$1:$B$565) -> 1.1665551 | O15: =_xlfn.SKEW.P($E$1:$E$565) -> 1.4738937 | P15: =_xlfn.SKEW.P(_xlfn.ANCHORARRAY(G1)) -> 1.7233807 | Q15: =_xlfn.SKEW.P(_xlfn.ANCHORARRAY(I1)) -> 1.8530254
A16: successful | B16: 14455 | D16: failed | E16: 2 | F16: canceled | G16: 1065
A17: successful | B17: 10850 | D17: failed | E17: 145243 | F17: canceled | G17: 3087
A18: successful | B18: 189666 | D18: failed | E18: 2459 | F18: canceled | G18: 3251
A19: successful | B19: 14025 | D19: failed | E19: 5392 | F19: canceled | G19: 108974
A20: successful | B20: 188628 | D20: failed | E20: 184750 | F20: canceled | G20: 12938
A21: successful | B21: 1101 | D21: failed | E21: 557 | F21: canceled | G21: 173191
A22: successful | B22: 11339 | D22: failed | E22: 2734 | F22: canceled | G22: 903
A23: successful | B23: 10085 | D23: failed | E23: 1307 | F23: canceled | G23: 3232
A24: successful | B24: 14878 | D24: failed | E24: 95993 | F24: canceled | G24: 37754
A25: successful | B25: 11924 | D25: failed | E25: 4460 | F25: canceled | G25: 45831
A26: successful | B26: 7991 | D26: failed | E26: 40228 | F26: canceled | G26: 3260
A27: successful | B27: 167717 | D27: failed | E27: 39996 | F27: canceled | G27: 31123
... A57: successful | B57: 12516 | D57: failed | E57: 47459 | F57: canceled | G57: 62819
A58: successful | B58: 8588 | D58: failed | E58: 86060
A59: successful | B59: 51775 | D59: failed | E59: 6927
A60: successful | B60: 8807 | D60: failed | E60: 5315
A61: successful | B61: 1017 | D61: failed | E61: 3525
A62: successful | B62: 151513 | D62: failed | E62: 718
A63: successful | B63: 12047 | D63: failed | E63: 28358
A64: successful | B64: 14951 | D64: failed | E64: 2625
A65: successful | B65: 9193 | D65: failed | E65: 2538
A66: successful | B66: 10422 | D66: failed | E66: 3188
A67: successful | B67: 170623 | D67: failed | E67: 8517
A68: successful | B68: 9829 | D68: failed | E68: 3012
A69: successful | B69: 14006 | D69: failed | E69: 5178
... A364: successful | B364: 14033 | D364: failed | E364: 37823
A365: successful | B365: 177936
A366: successful | B366: 13212
A367: successful | B367: 12219
A368: successful | B368: 12155
A369: successful | B369: 175020
A370: successful | B370: 75955
A371: successful | B371: 119127
A372: successful | B372: 11929
A373: successful | B373: 118214
A374: successful | B374: 14511
A375: successful | B375: 8109
A376: successful | B376: 8244
... A565: successful | B565: 153216

Sheet Category-Goal Statistics
A3: Row Labels | B3: Count of goal | C3: Sum of goal | D3: Mean of goal | E3: Varp of goal | F3: StdDevp of goal | G3: Min of goal | H3: 25% | I3: Median of goal | J3: 75% | K3: Max of goal | L3: IRQ | M3: Upper T | N3: Lower T | O3: Outlier Count | P3: Skewness
A4: film & video | B4: 178 | C4: 8744700 | D4: 49127.528 | E4: 4.1718617e+09 | F4: 64589.95 | G4: {=MIN(_xlfn._xlws.FILTER(CrowdfundingTable[goal],CrowdfundingTable[primary_category]=A4))} -> 100 | H4: {=_xlfn.QUARTILE.EXC(_xlfn._xlws.FILTER(CrowdfundingTable[goal],CrowdfundingTable[primary_category]=A4),1)} -> 4775 | I4: {=MEDIAN(_xlfn._xlws.FILTER(CrowdfundingTable[goal],CrowdfundingTable[primary_category]=A4))} -> 8450 | J4: {=_xlfn.QUARTILE.EXC(_xlfn._xlws.FILTER(CrowdfundingTable[goal],CrowdfundingTable[primary_category]=A4),3)} -> 99875 | K4: {=MAX(_xlfn._xlws.FILTER(CrowdfundingTable[goal],CrowdfundingTable[primary_category]=A4))} -> 197700 | L4: =J4-H4 -> 95100 | M4: =J4+(1.5*L4) -> 242525 | N4: =H4-(1.5*L4) -> -137875 | O4: {=COUNT(IF(_xlfn._xlws.FILTER(CrowdfundingTable[goal],CrowdfundingTable[primary_category]=A4) > M4,1,Null()))} -> 0 | P4: {=_xlfn.SKEW.P(_xlfn._xlws.FILTER(CrowdfundingTable[goal],CrowdfundingTable[primary_category]=A4))} -> 1.0946421
A5: animation | B5: 34 | C5: 1728400 | D5: 50835.294 | E5: 4.921187e+09 | F5: 70151.172 | G5: {=MIN(_xlfn._xlws.FILTER(CrowdfundingTable[goal],CrowdfundingTable[subcategory]=A5))} -> 100 | H5: {=_xlfn.QUARTILE.EXC(_xlfn._xlws.FILTER(CrowdfundingTable[goal],CrowdfundingTable[subcategory]=A5),1)} -> 3950 | I5: {=MEDIAN(_xlfn._xlws.FILTER(CrowdfundingTable[goal],CrowdfundingTable[subcategory]=A5))} -> 8750 | J5: {=_xlfn.QUARTILE.EXC(_xlfn._xlws.FILTER(CrowdfundingTable[goal],CrowdfundingTable[subcategory]=A5),3)} -> 106450 | K5: {=MAX(_xlfn._xlws.FILTER(CrowdfundingTable[goal],CrowdfundingTable[subcategory]=A5))} -> 197700 | L5: =J5-H5 -> 102500 | M5: =J5+(1.5*L5) -> 260200 | N5: =H5-(1.5*L5) -> -149800 | O5: {=COUNT(IF(_xlfn._xlws.FILTER(CrowdfundingTable[goal],CrowdfundingTable[subcategory]=A5) > M5,1,Null()))} -> 0 | P5: {=_xlfn.SKEW.P(_xlfn._xlws.FILTER(CrowdfundingTable[goal],CrowdfundingTable[subcategory]=A5))} -> 1.1517927
A6: documentary | B6: 60 | C6: 3386600 | D6: 56443.333 | E6: 4.7308141e+09 | F6: 68780.914 | G6: {=MIN(_xlfn._xlws.FILTER(CrowdfundingTable[goal],CrowdfundingTable[subcategory]=A6))} -> 800 | H6: {=_xlfn.QUARTILE.EXC(_xlfn._xlws.FILTER(CrowdfundingTable[goal],CrowdfundingTable[subcategory]=A6),1)} -> 5000 | I6: {=MEDIAN(_xlfn._xlws.FILTER(CrowdfundingTable[goal],CrowdfundingTable[subcategory]=A6))} -> 8850 | J6: {=_xlfn.QUARTILE.EXC(_xlfn._xlws.FILTER(CrowdfundingTable[goal],CrowdfundingTable[subcategory]=A6),3)} -> 127175 | K6: {=MAX(_xlfn._xlws.FILTER(CrowdfundingTable[goal],CrowdfundingTable[subcategory]=A6))} -> 196900 | L6: =J6-H6 -> 122175 | M6: =J6+(1.5*L6) -> 310437.5 | N6: =H6-(1.5*L6) -> -178262.5 | O6: {=COUNT(IF(_xlfn._xlws.FILTER(CrowdfundingTable[goal],CrowdfundingTable[subcategory]=A6) > M6,1,Null()))} -> 0 | P6: {=_xlfn.SKEW.P(_xlfn._xlws.FILTER(CrowdfundingTable[goal],CrowdfundingTable[subcategory]=A6))} -> 0.79622664
A7: drama | B7: 37 | C7: 1395300 | D7: 37710.811 | E7: 2.4956226e+09 | F7: 49956.207 | G7: {=MIN(_xlfn._xlws.FILTER(CrowdfundingTable[goal],CrowdfundingTable[subcategory]=A7))} -> 700 | H7: {=_xlfn.QUARTILE.EXC(_xlfn._xlws.FILTER(CrowdfundingTable[goal],CrowdfundingTable[subcategory]=A7),1)} -> 4950 | I7: {=MEDIAN(_xlfn._xlws.FILTER(CrowdfundingTable[goal],CrowdfundingTable[subcategory]=A7))} -> 7800 | J7: {=_xlfn.QUARTILE.EXC(_xlfn._xlws.FILTER(CrowdfundingTable[goal],CrowdfundingTable[subcategory]=A7),3)} -> 76500 | K7: {=MAX(_xlfn._xlws.FILTER(CrowdfundingTable[goal],CrowdfundingTable[subcategory]=A7))} -> 161900 | L7: =J7-H7 -> 71550 | M7: =J7+(1.5*L7) -> 183825 | N7: =H7-(1.5*L7) -> -102375 | O7: {=COUNT(IF(_xlfn._xlws.FILTER(CrowdfundingTable[goal],CrowdfundingTable[subcategory]=A7) > M7,1,Null()))} -> 0 | P7: {=_xlfn.SKEW.P(_xlfn._xlws.FILTER(CrowdfundingTable[goal],CrowdfundingTable[subcategory]=A7))} -> 1.2231585
A8: science fiction | B8: 14 | C8: 766300 | D8: 54735.714 | E8: 4.133888e+09 | F8: 64295.319 | G8: {=MIN(_xlfn._xlws.FILTER(CrowdfundingTable[goal],CrowdfundingTable[subcategory]=A8))} -> 3300 | H8: {=_xlfn.QUARTILE.EXC(_xlfn._xlws.FILTER(CrowdfundingTable[goal],CrowdfundingTable[subcategory]=A8),1)} -> 7875 | I8: {=MEDIAN(_xlfn._xlws.FILTER(CrowdfundingTable[goal],CrowdfundingTable[subcategory]=A8))} -> 19200 | J8: {=_xlfn.QUARTILE.EXC(_xlfn._xlws.FILTER(CrowdfundingTable[goal],CrowdfundingTable[subcategory]=A8),3)} -> 104725 | K8: {=MAX(_xlfn._xlws.FILTER(CrowdfundingTable[goal],CrowdfundingTable[subcategory]=A8))} -> 187600 | L8: =J8-H8 -> 96850 | M8: =J8+(1.5*L8) -> 250000 | N8: =H8-(1.5*L8) -> -137400 | O8: {=COUNT(IF(_xlfn._xlws.FILTER(CrowdfundingTable[goal],CrowdfundingTable[subcategory]=A8) > M8,1,Null()))} -> 0 | P8: {=_xlfn.SKEW.P(_xlfn._xlws.FILTER(CrowdfundingTable[goal],CrowdfundingTable[subcategory]=A8))} -> 1.1144324
A9: shorts | B9: 16 | C9: 775500 | D9: 48468.75 | E9: 4.7266609e+09 | F9: 68750.716 | G9: {=MIN(_xlfn._xlws.FILTER(CrowdfundingTable[goal],CrowdfundingTable[subcategory]=A9))} -> 900 | H9: {=_xlfn.QUARTILE.EXC(_xlfn._xlws.FILTER(CrowdfundingTable[goal],CrowdfundingTable[subcategory]=A9),1)} -> 3600 | I9: {=MEDIAN(_xlfn._xlws.FILTER(CrowdfundingTable[goal],CrowdfundingTable[subcategory]=A9))} -> 6500 | J9: {=_xlfn.QUARTILE.EXC(_xlfn._xlws.FILTER(CrowdfundingTable[goal],CrowdfundingTable[subcategory]=A9),3)} -> 57775 | K9: {=MAX(_xlfn._xlws.FILTER(CrowdfundingTable[goal],CrowdfundingTable[subcategory]=A9))} -> 196700 | L9: =J9-H9 -> 54175 | M9: =J9+(1.5*L9) -> 139037.5 | N9: =H9-(1.5*L9) -> -77662.5 | O9: {=COUNT(IF(_xlfn._xlws.FILTER(CrowdfundingTable[goal],CrowdfundingTable[subcategory]=A9) > M9,1,Null()))} -> 3 | P9: {=_xlfn.SKEW.P(_xlfn._xlws.FILTER(CrowdfundingTable[goal],CrowdfundingTable[subcategory]=A9))} -> 1.3780514
A10: television | B10: 17 | C10: 692600 | D10: 40741.176 | E10: 3.2827754e+09 | F10: 57295.509 | G10: {=MIN(_xlfn._xlws.FILTER(CrowdfundingTable[goal],CrowdfundingTable[subcategory]=A10))} -> 1000 | H10: {=_xlfn.QUARTILE.EXC(_xlfn._xlws.FILTER(CrowdfundingTable[goal],CrowdfundingTable[subcategory]=A10),1)} -> 3200 | I10: {=MEDIAN(_xlfn._xlws.FILTER(CrowdfundingTable[goal],CrowdfundingTable[subcategory]=A10))} -> 5200 | J10: {=_xlfn.QUARTILE.EXC(_xlfn._xlws.FILTER(CrowdfundingTable[goal],CrowdfundingTable[subcategory]=A10),3)} -> 110350 | K10: {=MAX(_xlfn._xlws.FILTER(CrowdfundingTable[goal],CrowdfundingTable[subcategory]=A10))} -> 155200 | L10: =J10-H10 -> 107150 | M10: =J10+(1.5*L10) -> 271075 | N10: =H10-(1.5*L10) -> -157525 | O10: {=COUNT(IF(_xlfn._xlws.FILTER(CrowdfundingTable[goal],CrowdfundingTable[subcategory]=A10) > M10,1,Null()))} -> 0 | P10: {=_xlfn.SKEW.P(_xlfn._xlws.FILTER(CrowdfundingTable[goal],CrowdfundingTable[subcategory]=A10))} -> 0.99425472
A11: food | B11: 46 | C11: 1921300 | D11: 41767.391 | E11: 3.7031578e+09 | F11: 60853.577 | G11: {=MIN(_xlfn._xlws.FILTER(CrowdfundingTable[goal],CrowdfundingTable[primary_category]=A11))} -> 100 | H11: {=_xlfn.QUARTILE.EXC(_xlfn._xlws.FILTER(CrowdfundingTable[goal],CrowdfundingTable[primary_category]=A11),1)} -> 3000 | I11: {=MEDIAN(_xlfn._xlws.FILTER(CrowdfundingTable[goal],CrowdfundingTable[primary_category]=A11))} -> 7100 | J11: {=_xlfn.QUARTILE.EXC(_xlfn._xlws.FILTER(CrowdfundingTable[goal],CrowdfundingTable[primary_category]=A11),3)} -> 97625 | K11: {=MAX(_xlfn._xlws.FILTER(CrowdfundingTable[goal],CrowdfundingTable[primary_category]=A11))} -> 199000 | L11: =J11-H11 -> 94625 | M11: =J11+(1.5*L11) -> 239562.5 | N11: =H11-(1.5*L11) -> -138937.5 | O11: {=COUNT(IF(_xlfn._xlws.FILTER(CrowdfundingTable[goal],CrowdfundingTable[primary_category]=A11) > M11,1,Null()))} -> 0 | P11: {=_xlfn.SKEW.P(_xlfn._xlws.FILTER(CrowdfundingTable[goal],CrowdfundingTable[primary_category]=A11))} -> 1.2688609
A12: food trucks | B12: 46 | C12: 1921300 | D12: 41767.391 | E12: 3.7031578e+09 | F12: 60853.577 | G12: {=MIN(_xlfn._xlws.FILTER(CrowdfundingTable[goal],CrowdfundingTable[subcategory]=A12))} -> 100 | H12: {=_xlfn.QUARTILE.EXC(_xlfn._xlws.FILTER(CrowdfundingTable[goal],CrowdfundingTable[subcategory]=A12),1)} -> 3000 | I12: {=MEDIAN(_xlfn._xlws.FILTER(CrowdfundingTable[goal],CrowdfundingTable[subcategory]=A12))} -> 7100 | J12: {=_xlfn.QUARTILE.EXC(_xlfn._xlws.FILTER(CrowdfundingTable[goal],CrowdfundingTable[subcategory]=A12),3)} -> 97625 | K12: {=MAX(_xlfn._xlws.FILTER(CrowdfundingTable[goal],CrowdfundingTable[subcategory]=A12))} -> 199000 | L12: =J12-H12 -> 94625 | M12: =J12+(1.5*L12) -> 239562.5 | N12: =H12-(1.5*L12) -> -138937.5 | O12: {=COUNT(IF(_xlfn._xlws.FILTER(CrowdfundingTable[goal],CrowdfundingTable[subcategory]=A12) > M12,1,Null()))} -> 0 | P12: {=_xlfn.SKEW.P(_xlfn._xlws.FILTER(CrowdfundingTable[goal],CrowdfundingTable[subcategory]=A12))} -> 1.2688609
A13: games | B13: 48 | C13: 2858000 | D13: 59541.667 | E13: 4.410017e+09 | F13: 66407.959 | G13: {=MIN(_xlfn._xlws.FILTER(CrowdfundingTable[goal],CrowdfundingTable[primary_category]=A13))} -> 600 | H13: {=_xlfn.QUARTILE.EXC(_xlfn._xlws.FILTER(CrowdfundingTable[goal],CrowdfundingTable[primary_category]=A13),1)} -> 4950 | I13: {=MEDIAN(_xlfn._xlws.FILTER(CrowdfundingTable[goal],CrowdfundingTable[primary_category]=A13))} -> 14800 | J13: {=_xlfn.QUARTILE.EXC(_xlfn._xlws.FILTER(CrowdfundingTable[goal],CrowdfundingTable[primary_category]=A13),3)} -> 98475 | K13: {=MAX(_xlfn._xlws.FILTER(CrowdfundingTable[goal],CrowdfundingTable[primary_category]=A13))} -> 197600 | L13: =J13-H13 -> 93525 | M13: =J13+(1.5*L13) -> 238762.5 | N13: =H13-(1.5*L13) -> -135337.5 | O13: {=COUNT(IF(_xlfn._xlws.FILTER(CrowdfundingTable[goal],CrowdfundingTable[primary_category]=A13) > M13,1,Null()))} -> 0 | P13: {=_xlfn.SKEW.P(_xlfn._xlws.FILTER(CrowdfundingTable[goal],CrowdfundingTable[primary_category]=A13))} -> 0.80592297
A14: mobile games | B14: 13 | C14: 1373800 | D14: 105676.92 | E14: 4.4602372e+09 | F14: 66785.007 | G14: {=MIN(_xlfn._xlws.FILTER(CrowdfundingTable[goal],CrowdfundingTable[subcategory]=A14))} -> 6200 | H14: {=_xlfn.QUARTILE.EXC(_xlfn._xlws.FILTER(CrowdfundingTable[goal],CrowdfundingTable[subcategory]=A14),1)} -> 35250 | I14: {=MEDIAN(_xlfn._xlws.FILTER(CrowdfundingTable[goal],CrowdfundingTable[subcategory]=A14))} -> 118000 | J14: {=_xlfn.QUARTILE.EXC(_xlfn._xlws.FILTER(CrowdfundingTable[goal],CrowdfundingTable[subcategory]=A14),3)} -> 165850 | K14: {=MAX(_xlfn._xlws.FILTER(CrowdfundingTable[goal],CrowdfundingTable[subcategory]=A14))} -> 193200 | L14: =J14-H14 -> 130600 | M14: =J14+(1.5*L14) -> 361750 | N14: =H14-(1.5*L14) -> -160650 | O14: {=COUNT(IF(_xlfn._xlws.FILTER(CrowdfundingTable[goal],CrowdfundingTable[subcategory]=A14) > M14,1,Null()))} -> 0 | P14: {=_xlfn.SKEW.P(_xlfn._xlws.FILTER(CrowdfundingTable[goal],CrowdfundingTable[subcategory]=A14))} -> -0.26884168
A15: video games | B15: 35 | C15: 1484200 | D15: 42405.714 | E15: 3.3071514e+09 | F15: 57507.838 | G15: {=MIN(_xlfn._xlws.FILTER(CrowdfundingTable[goal],CrowdfundingTable[subcategory]=A15))} -> 600 | H15: {=_xlfn.QUARTILE.EXC(_xlfn._xlws.FILTER(CrowdfundingTable[goal],CrowdfundingTable[subcategory]=A15),1)} -> 2900 | I15: {=MEDIAN(_xlfn._xlws.FILTER(CrowdfundingTable[goal],CrowdfundingTable[subcategory]=A15))} -> 7800 | J15: {=_xlfn.QUARTILE.EXC(_xlfn._xlws.FILTER(CrowdfundingTable[goal],CrowdfundingTable[subcategory]=A15),3)} -> 89900 | K15: {=MAX(_xlfn._xlws.FILTER(CrowdfundingTable[goal],CrowdfundingTable[subcategory]=A15))} -> 197600 | L15: =J15-H15 -> 87000 | M15: =J15+(1.5*L15) -> 220400 | N15: =H15-(1.5*L15) -> -127600 | O15: {=COUNT(IF(_xlfn._xlws.FILTER(CrowdfundingTable[goal],CrowdfundingTable[subcategory]=A15) > M15,1,Null()))} -> 0 | P15: {=_xlfn.SKEW.P(_xlfn._xlws.FILTER(CrowdfundingTable[goal],CrowdfundingTable[subcategory]=A15))} -> 1.3813446
A16: journalism | B16: 4 | C16: 25700 | D16: 6425 | E16: 6806875 | F16: 2608.9989 | G16: {=MIN(_xlfn._xlws.FILTER(CrowdfundingTable[goal],CrowdfundingTable[primary_category]=A16))} -> 2400 | H16: {=_xlfn.QUARTILE.EXC(_xlfn._xlws.FILTER(CrowdfundingTable[goal],CrowdfundingTable[primary_category]=A16),1)} -> 3475 | I16: {=MEDIAN(_xlfn._xlws.FILTER(CrowdfundingTable[goal],CrowdfundingTable[primary_category]=A16))} -> 6800 | J16: {=_xlfn.QUARTILE.EXC(_xlfn._xlws.FILTER(CrowdfundingTable[goal],CrowdfundingTable[primary_category]=A16),3)} -> 9000 | K16: {=MAX(_xlfn._xlws.FILTER(CrowdfundingTable[goal],CrowdfundingTable[primary_category]=A16))} -> 9700 | L16: =J16-H16 -> 5525 | M16: =J16+(1.5*L16) -> 17287.5 | N16: =H16-(1.5*L16) -> -4812.5 | O16: {=COUNT(IF(_xlfn._xlws.FILTER(CrowdfundingTable[goal],CrowdfundingTable[primary_category]=A16) > M16,1,Null()))} -> 0 | P16: {=_xlfn.SKEW.P(_xlfn._xlws.FILTER(CrowdfundingTable[goal],CrowdfundingTable[primary_category]=A16))} -> -0.42165814
A17: audio | B17: 4 | C17: 25700 | D17: 6425 | E17: 6806875 | F17: 2608.9989 | G17: {=MIN(_xlfn._xlws.FILTER(CrowdfundingTable[goal],CrowdfundingTable[subcategory]=A17))} -> 2400 | H17: {=_xlfn.QUARTILE.EXC(_xlfn._xlws.FILTER(CrowdfundingTable[goal],CrowdfundingTable[subcategory]=A17),1)} -> 3475 | I17: {=MEDIAN(_xlfn._xlws.FILTER(CrowdfundingTable[goal],CrowdfundingTable[subcategory]=A17))} -> 6800 | J17: {=_xlfn.QUARTILE.EXC(_xlfn._xlws.FILTER(CrowdfundingTable[goal],CrowdfundingTable[subcategory]=A17),3)} -> 9000 | K17: {=MAX(_xlfn._xlws.FILTER(CrowdfundingTable[goal],CrowdfundingTable[subcategory]=A17))} -> 9700 | L17: =J17-H17 -> 5525 | M17: =J17+(1.5*L17) -> 17287.5 | N17: =H17-(1.5*L17) -> -4812.5 | O17: {=COUNT(IF(_xlfn._xlws.FILTER(CrowdfundingTable[goal],CrowdfundingTable[subcategory]=A17) > M17,1,Null()))} -> 0 | P17: {=_xlfn.SKEW.P(_xlfn._xlws.FILTER(CrowdfundingTable[goal],CrowdfundingTable[subcategory]=A17))} -> -0.42165814
A18: music | B18: 175 | C18: 7026300 | D18: 40150.286 | E18: 3.035298e+09 | F18: 55093.539 | G18: {=MIN(_xlfn._xlws.FILTER(CrowdfundingTable[goal],CrowdfundingTable[primary_category]=A18))} -> 100 | H18: {=_xlfn.QUARTILE.EXC(_xlfn._xlws.FILTER(CrowdfundingTable[goal],CrowdfundingTable[primary_category]=A18),1)} -> 3700 | I18: {=MEDIAN(_xlfn._xlws.FILTER(CrowdfundingTable[goal],CrowdfundingTable[primary_category]=A18))} -> 7800 | J18: {=_xlfn.QUARTILE.EXC(_xlfn._xlws.FILTER(CrowdfundingTable[goal],CrowdfundingTable[primary_category]=A18),3)} -> 70600 | K18: {=MAX(_xlfn._xlws.FILTER(CrowdfundingTable[goal],CrowdfundingTable[primary_category]=A18))} -> 198500 | L18: =J18-H18 -> 66900 | M18: =J18+(1.5*L18) -> 170950 | N18: =H18-(1.5*L18) -> -96650 | O18: {=COUNT(IF(_xlfn._xlws.FILTER(CrowdfundingTable[goal],CrowdfundingTable[primary_category]=A18) > M18,1,Null()))} -> 7 | P18: {=_xlfn.SKEW.P(_xlfn._xlws.FILTER(CrowdfundingTable[goal],CrowdfundingTable[primary_category]=A18))} -> 1.3535088
A19: electric music | B19: 18 | C19: 760300 | D19: 42238.889 | E19: 3.0268802e+09 | F19: 55017.09 | G19: {=MIN(_xlfn._xlws.FILTER(CrowdfundingTable[goal],CrowdfundingTable[subcategory]=A19))} -> 100 | H19: {=_xlfn.QUARTILE.EXC(_xlfn._xlws.FILTER(CrowdfundingTable[goal],CrowdfundingTable[subcategory]=A19),1)} -> 5450 | I19: {=MEDIAN(_xlfn._xlws.FILTER(CrowdfundingTable[goal],CrowdfundingTable[subcategory]=A19))} -> 7800 | J19: {=_xlfn.QUARTILE.EXC(_xlfn._xlws.FILTER(CrowdfundingTable[goal],CrowdfundingTable[subcategory]=A19),3)} -> 89975 | K19: {=MAX(_xlfn._xlws.FILTER(CrowdfundingTable[goal],CrowdfundingTable[subcategory]=A19))} -> 167500 | L19: =J19-H19 -> 84525 | M19: =J19+(1.5*L19) -> 216762.5 | N19: =H19-(1.5*L19) -> -121337.5 | O19: {=COUNT(IF(_xlfn._xlws.FILTER(CrowdfundingTable[goal],CrowdfundingTable[subcategory]=A19) > M19,1,Null()))} -> 0 | P19: {=_xlfn.SKEW.P(_xlfn._xlws.FILTER(CrowdfundingTable[goal],CrowdfundingTable[subcategory]=A19))} -> 1.0777511
A20: indie rock | B20: 45 | C20: 2278300 | D20: 50628.889 | E20: 3.8070874e+09 | F20: 61701.6 | G20: {=MIN(_xlfn._xlws.FILTER(CrowdfundingTable[goal],CrowdfundingTable[subcategory]=A20))} -> 100 | H20: {=_xlfn.QUARTILE.EXC(_xlfn._xlws.FILTER(CrowdfundingTable[goal],CrowdfundingTable[subcategory]=A20),1)} -> 4550 | I20: {=MEDIAN(_xlfn._xlws.FILTER(CrowdfundingTable[goal],CrowdfundingTable[subcategory]=A20))} -> 9000 | J20: {=_xlfn.QUARTILE.EXC(_xlfn._xlws.FILTER(CrowdfundingTable[goal],CrowdfundingTable[subcategory]=A20),3)} -> 114550 | K20: {=MAX(_xlfn._xlws.FILTER(CrowdfundingTable[goal],CrowdfundingTable[subcategory]=A20))} -> 189000 | L20: =J20-H20 -> 110000 | M20: =J20+(1.5*L20) -> 279550 | N20: =H20-(1.5*L20) -> -160450 | O20: {=COUNT(IF(_xlfn._xlws.FILTER(CrowdfundingTable[goal],CrowdfundingTable[subcategory]=A20) > M20,1,Null()))} -> 0 | P20: {=_xlfn.SKEW.P(_xlfn._xlws.FILTER(CrowdfundingTable[goal],CrowdfundingTable[subcategory]=A20))} -> 0.91852546
A21: jazz | B21: 17 | C21: 489500 | D21: 28794.118 | E21: 1.5418735e+09 | F21: 39266.697 | G21: {=MIN(_xlfn._xlws.FILTER(CrowdfundingTable[goal],CrowdfundingTable[subcategory]=A21))} -> 100 | H21: {=_xlfn.QUARTILE.EXC(_xlfn._xlws.FILTER(CrowdfundingTable[goal],CrowdfundingTable[subcategory]=A21),1)} -> 1450 | I21: {=MEDIAN(_xlfn._xlws.FILTER(CrowdfundingTable[goal],CrowdfundingTable[subcategory]=A21))} -> 6200 | J21: {=_xlfn.QUARTILE.EXC(_xlfn._xlws.FILTER(CrowdfundingTable[goal],CrowdfundingTable[subcategory]=A21),3)} -> 68900 | K21: {=MAX(_xlfn._xlws.FILTER(CrowdfundingTable[goal],CrowdfundingTable[subcategory]=A21))} -> 111900 | L21: =J21-H21 -> 67450 | M21: =J21+(1.5*L21) -> 170075 | N21: =H21-(1.5*L21) -> -99725 | O21: {=COUNT(IF(_xlfn._xlws.FILTER(CrowdfundingTable[goal],CrowdfundingTable[subcategory]=A21) > M21,1,Null()))} -> 0 | P21: {=_xlfn.SKEW.P(_xlfn._xlws.FILTER(CrowdfundingTable[goal],CrowdfundingTable[subcategory]=A21))} -> 1.0941388
A22: metal | B22: 7 | C22: 70200 | D22: 10028.571 | E22: 1.2498776e+08 | F22: 11179.792 | G22: {=MIN(_xlfn._xlws.FILTER(CrowdfundingTable[goal],CrowdfundingTable[subcategory]=A22))} -> 100 | H22: {=_xlfn.QUARTILE.EXC(_xlfn._xlws.FILTER(CrowdfundingTable[goal],CrowdfundingTable[subcategory]=A22),1)} -> 2700 | I22: {=MEDIAN(_xlfn._xlws.FILTER(CrowdfundingTable[goal],CrowdfundingTable[subcategory]=A22))} -> 5600 | J22: {=_xlfn.QUARTILE.EXC(_xlfn._xlws.FILTER(CrowdfundingTable[goal],CrowdfundingTable[subcategory]=A22),3)} -> 15800 | K22: {=MAX(_xlfn._xlws.FILTER(CrowdfundingTable[goal],CrowdfundingTable[subcategory]=A22))} -> 35000 | L22: =J22-H22 -> 13100 | M22: =J22+(1.5*L22) -> 35450 | N22: =H22-(1.5*L22) -> -16950 | O22: {=COUNT(IF(_xlfn._xlws.FILTER(CrowdfundingTable[goal],CrowdfundingTable[subcategory]=A22) > M22,1,Null()))} -> 0 | P22: {=_xlfn.SKEW.P(_xlfn._xlws.FILTER(CrowdfundingTable[goal],CrowdfundingTable[subcategory]=A22))} -> 1.4363288
A23: rock | B23: 85 | C23: 3283700 | D23: 38631.765 | E23: 3.0682697e+09 | F23: 55391.964 | G23: {=MIN(_xlfn._xlws.FILTER(CrowdfundingTable[goal],CrowdfundingTable[subcategory]=A23))} -> 100 | H23: {=_xlfn.QUARTILE.EXC(_xlfn._xlws.FILTER(CrowdfundingTable[goal],CrowdfundingTable[subcategory]=A23),1)} -> 3400 | I23: {=MEDIAN(_xlfn._xlws.FILTER(CrowdfundingTable[goal],CrowdfundingTable[subcategory]=A23))} -> 7800 | J23: {=_xlfn.QUARTILE.EXC(_xlfn._xlws.FILTER(CrowdfundingTable[goal],CrowdfundingTable[subcategory]=A23),3)} -> 63700 | K23: {=MAX(_xlfn._xlws.FILTER(CrowdfundingTable[goal],CrowdfundingTable[subcategory]=A23))} -> 198500 | L23: =J23-H23 -> 60300 | M23: =J23+(1.5*L23) -> 154150 | N23: =H23-(1.5*L23) -> -87050 | O23: {=COUNT(IF(_xlfn._xlws.FILTER(CrowdfundingTable[goal],CrowdfundingTable[subcategory]=A23) > M23,1,Null()))} -> 6 | P23: {=_xlfn.SKEW.P(_xlfn._xlws.FILTER(CrowdfundingTable[goal],CrowdfundingTable[subcategory]=A23))} -> 1.5269426
A24: world music | B24: 3 | C24: 144300 | D24: 48100 | E24: 1.1786467e+09 | F24: 34331.424 | G24: {=MIN(_xlfn._xlws.FILTER(CrowdfundingTable[goal],CrowdfundingTable[subcategory]=A24))} -> 4500 | H24: {=_xlfn.QUARTILE.EXC(_xlfn._xlws.FILTER(CrowdfundingTable[goal],CrowdfundingTable[subcategory]=A24),1)} -> 4500 | I24: {=MEDIAN(_xlfn._xlws.FILTER(CrowdfundingTable[goal],CrowdfundingTable[subcategory]=A24))} -> 51400 | J24: {=_xlfn.QUARTILE.EXC(_xlfn._xlws.FILTER(CrowdfundingTable[goal],CrowdfundingTable[subcategory]=A24),3)} -> 88400 | K24: {=MAX(_xlfn._xlws.FILTER(CrowdfundingTable[goal],CrowdfundingTable[subcategory]=A24))} -> 88400 | L24: =J24-H24 -> 83900 | M24: =J24+(1.5*L24) -> 214250 | N24: =H24-(1.5*L24) -> -121350 | O24: {=COUNT(IF(_xlfn._xlws.FILTER(CrowdfundingTable[goal],CrowdfundingTable[subcategory]=A24) > M24,1,Null()))} -> 0 | P24: {=_xlfn.SKEW.P(_xlfn._xlws.FILTER(CrowdfundingTable[goal],CrowdfundingTable[subcategory]=A24))} -> -0.14329467
A25: photography | B25: 42 | C25: 1351700 | D25: 32183.333 | E25: 3.0795866e+09 | F25: 55494.023 | G25: {=MIN(_xlfn._xlws.FILTER(CrowdfundingTable[goal],CrowdfundingTable[primary_category]=A25))} -> 100 | H25: {=_xlfn.QUARTILE.EXC(_xlfn._xlws.FILTER(CrowdfundingTable[goal],CrowdfundingTable[primary_category]=A25),1)} -> 3400 | I25: {=MEDIAN(_xlfn._xlws.FILTER(CrowdfundingTable[goal],CrowdfundingTable[primary_category]=A25))} -> 6550 | J25: {=_xlfn.QUARTILE.EXC(_xlfn._xlws.FILTER(CrowdfundingTable[goal],CrowdfundingTable[primary_category]=A25),3)} -> 37100 | K25: {=MAX(_xlfn._xlws.FILTER(CrowdfundingTable[goal],CrowdfundingTable[primary_category]=A25))} -> 191000 | L25: =J25-H25 -> 33700 | M25: =J25+(1.5*L25) -> 87650 | N25: =H25-(1.5*L25) -> -47150 | O25: {=COUNT(IF(_xlfn._xlws.FILTER(CrowdfundingTable[goal],CrowdfundingTable[primary_category]=A25) > M25,1,Null()))} -> 6 | P25: {=_xlfn.SKEW.P(_xlfn._xlws.FILTER(CrowdfundingTable[goal],CrowdfundingTable[primary_category]=A25))} -> 1.9908413
A26: photography books | B26: 42 | C26: 1351700 | D26: 32183.333 | E26: 3.0795866e+09 | F26: 55494.023 | G26: {=MIN(_xlfn._xlws.FILTER(CrowdfundingTable[goal],CrowdfundingTable[subcategory]=A26))} -> 100 | H26: {=_xlfn.QUARTILE.EXC(_xlfn._xlws.FILTER(CrowdfundingTable[goal],CrowdfundingTable[subcategory]=A26),1)} -> 3400 | I26: {=MEDIAN(_xlfn._xlws.FILTER(CrowdfundingTable[goal],CrowdfundingTable[subcategory]=A26))} -> 6550 | J26: {=_xlfn.QUARTILE.EXC(_xlfn._xlws.FILTER(CrowdfundingTable[goal],CrowdfundingTable[subcategory]=A26),3)} -> 37100 | K26: {=MAX(_xlfn._xlws.FILTER(CrowdfundingTable[goal],CrowdfundingTable[subcategory]=A26))} -> 191000 | L26: =J26-H26 -> 33700 | M26: =J26+(1.5*L26) -> 87650 | N26: =H26-(1.5*L26) -> -47150 | O26: {=COUNT(IF(_xlfn._xlws.FILTER(CrowdfundingTable[goal],CrowdfundingTable[subcategory]=A26) > M26,1,Null()))} -> 6 | P26: {=_xlfn.SKEW.P(_xlfn._xlws.FILTER(CrowdfundingTable[goal],CrowdfundingTable[subcategory]=A26))} -> 1.9908413
A27: publishing | B27: 67 | C27: 3240100 | D27: 48359.701 | E27: 3.748326e+09 | F27: 61223.574 | G27: {=MIN(_xlfn._xlws.FILTER(CrowdfundingTable[goal],CrowdfundingTable[primary_category]=A27))} -> 100 | H27: {=_xlfn.QUARTILE.EXC(_xlfn._xlws.FILTER(CrowdfundingTable[goal],CrowdfundingTable[primary_category]=A27),1)} -> 4600 | I27: {=MEDIAN(_xlfn._xlws.FILTER(CrowdfundingTable[goal],CrowdfundingTable[primary_category]=A27))} -> 8900 | J27: {=_xlfn.QUARTILE.EXC(_xlfn._xlws.FILTER(CrowdfundingTable[goal],CrowdfundingTable[primary_category]=A27),3)} -> 85000 | K27: {=MAX(_xlfn._xlws.FILTER(CrowdfundingTable[goal],CrowdfundingTable[primary_category]=A27))} -> 198600 | L27: =J27-H27 -> 80400 | M27: =J27+(1.5*L27) -> 205600 | N27: =H27-(1.5*L27) -> -116000 | O27: {=COUNT(IF(_xlfn._xlws.FILTER(CrowdfundingTable[goal],CrowdfundingTable[primary_category]=A27) > M27,1,Null()))} -> 0 | P27: {=_xlfn.SKEW.P(_xlfn._xlws.FILTER(CrowdfundingTable[goal],CrowdfundingTable[primary_category]=A27))} -> 1.167297
A28: fiction | B28: 17 | C28: 964300 | D28: 56723.529 | E28: 4.5746053e+09 | F28: 67635.829 | G28: {=MIN(_xlfn._xlws.FILTER(CrowdfundingTable[goal],CrowdfundingTable[subcategory]=A28))} -> 1600 | H28: {=_xlfn.QUARTILE.EXC(_xlfn._xlws.FILTER(CrowdfundingTable[goal],CrowdfundingTable[subcategory]=A28),1)} -> 6100 | I28: {=MEDIAN(_xlfn._xlws.FILTER(CrowdfundingTable[goal],CrowdfundingTable[subcategory]=A28))} -> 9800 | J28: {=_xlfn.QUARTILE.EXC(_xlfn._xlws.FILTER(CrowdfundingTable[goal],CrowdfundingTable[subcategory]=A28),3)} -> 120900 | K28: {=MAX(_xlfn._xlws.FILTER(CrowdfundingTable[goal],CrowdfundingTable[subcategory]=A28))} -> 191500 | L28: =J28-H28 -> 114800 | M28: =J28+(1.5*L28) -> 293100 | N28: =H28-(1.5*L28) -> -166100 | O28: {=COUNT(IF(_xlfn._xlws.FILTER(CrowdfundingTable[goal],CrowdfundingTable[subcategory]=A28) > M28,1,Null()))} -> 0 | P28: {=_xlfn.SKEW.P(_xlfn._xlws.FILTER(CrowdfundingTable[goal],CrowdfundingTable[subcategory]=A28))} -> 0.89063106
A29: nonfiction | B29: 21 | C29: 1220000 | D29: 58095.238 | E29: 4.7600985e+09 | F29: 68993.467 | G29: {=MIN(_xlfn._xlws.FILTER(CrowdfundingTable[goal],CrowdfundingTable[subcategory]=A29))} -> 100 | H29: {=_xlfn.QUARTILE.EXC(_xlfn._xlws.FILTER(CrowdfundingTable[goal],CrowdfundingTable[subcategory]=A29),1)} -> 1750 | I29: {=MEDIAN(_xlfn._xlws.FILTER(CrowdfundingTable[goal],CrowdfundingTable[subcategory]=A29))} -> 38900 | J29: {=_xlfn.QUARTILE.EXC(_xlfn._xlws.FILTER(CrowdfundingTable[goal],CrowdfundingTable[subcategory]=A29),3)} -> 105200 | K29: {=MAX(_xlfn._xlws.FILTER(CrowdfundingTable[goal],CrowdfundingTable[subcategory]=A29))} -> 198600 | L29: =J29-H29 -> 103450 | M29: =J29+(1.5*L29) -> 260375 | N29: =H29-(1.5*L29) -> -153425 | O29: {=COUNT(IF(_xlfn._xlws.FILTER(CrowdfundingTable[goal],CrowdfundingTable[subcategory]=A29) > M29,1,Null()))} -> 0 | P29: {=_xlfn.SKEW.P(_xlfn._xlws.FILTER(CrowdfundingTable[goal],CrowdfundingTable[subcategory]=A29))} -> 0.96931661
A30: radio & podcasts | B30: 8 | C30: 275200 | D30: 34400 | E30: 1345525000 | F30: 36681.399 | G30: {=MIN(_xlfn._xlws.FILTER(CrowdfundingTable[goal],CrowdfundingTable[subcategory]=A30))} -> 3800 | H30: {=_xlfn.QUARTILE.EXC(_xlfn._xlws.FILTER(CrowdfundingTable[goal],CrowdfundingTable[subcategory]=A30),1)} -> 6600 | I30: {=MEDIAN(_xlfn._xlws.FILTER(CrowdfundingTable[goal],CrowdfundingTable[subcategory]=A30))} -> 8250 | J30: {=_xlfn.QUARTILE.EXC(_xlfn._xlws.FILTER(CrowdfundingTable[goal],CrowdfundingTable[subcategory]=A30),3)} -> 82775 | K30: {=MAX(_xlfn._xlws.FILTER(CrowdfundingTable[goal],CrowdfundingTable[subcategory]=A30))} -> 90200 | L30: =J30-H30 -> 76175 | M30: =J30+(1.5*L30) -> 197037.5 | N30: =H30-(1.5*L30) -> -107662.5 | O30: {=COUNT(IF(_xlfn._xlws.FILTER(CrowdfundingTable[goal],CrowdfundingTable[subcategory]=A30) > M30,1,Null()))} -> 0 | P30: {=_xlfn.SKEW.P(_xlfn._xlws.FILTER(CrowdfundingTable[goal],CrowdfundingTable[subcategory]=A30))} -> 0.65149324
A31: translations | B31: 21 | C31: 780600 | D31: 37171.429 | E31: 2.6321887e+09 | F31: 51304.86 | G31: {=MIN(_xlfn._xlws.FILTER(CrowdfundingTable[goal],CrowdfundingTable[subcategory]=A31))} -> 2400 | H31: {=_xlfn.QUARTILE.EXC(_xlfn._xlws.FILTER(CrowdfundingTable[goal],CrowdfundingTable[subcategory]=A31),1)} -> 4750 | I31: {=MEDIAN(_xlfn._xlws.FILTER(CrowdfundingTable[goal],CrowdfundingTable[subcategory]=A31))} -> 6000 | J31: {=_xlfn.QUARTILE.EXC(_xlfn._xlws.FILTER(CrowdfundingTable[goal],CrowdfundingTable[subcategory]=A31),3)} -> 62450 | K31: {=MAX(_xlfn._xlws.FILTER(CrowdfundingTable[goal],CrowdfundingTable[subcategory]=A31))} -> 154300 | L31: =J31-H31 -> 57700 | M31: =J31+(1.5*L31) -> 149000 | N31: =H31-(1.5*L31) -> -81800 | O31: {=COUNT(IF(_xlfn._xlws.FILTER(CrowdfundingTable[goal],CrowdfundingTable[subcategory]=A31) > M31,1,Null()))} -> 1 | P31: {=_xlfn.SKEW.P(_xlfn._xlws.FILTER(CrowdfundingTable[goal],CrowdfundingTable[subcategory]=A31))} -> 1.3321692
A32: technology | B32: 96 | C32: 3177400 | D32: 33097.917 | E32: 2.30131e+09 | F32: 47971.971 | G32: {=MIN(_xlfn._xlws.FILTER(CrowdfundingTable[goal],CrowdfundingTable[primary_category]=A32))} -> 100 | H32: {=_xlfn.QUARTILE.EXC(_xlfn._xlws.FILTER(CrowdfundingTable[goal],CrowdfundingTable[primary_category]=A32),1)} -> 3725 | I32: {=MEDIAN(_xlfn._xlws.FILTER(CrowdfundingTable[goal],CrowdfundingTable[primary_category]=A32))} -> 8250 | J32: {=_xlfn.QUARTILE.EXC(_xlfn._xlws.FILTER(CrowdfundingTable[goal],CrowdfundingTable[primary_category]=A32),3)} -> 52525 | K32: {=MAX(_xlfn._xlws.FILTER(CrowdfundingTable[goal],CrowdfundingTable[primary_category]=A32))} -> 193400 | L32: =J32-H32 -> 48800 | M32: =J32+(1.5*L32) -> 125725 | N32: =H32-(1.5*L32) -> -69475 | O32: {=COUNT(IF(_xlfn._xlws.FILTER(CrowdfundingTable[goal],CrowdfundingTable[primary_category]=A32) > M32,1,Null()))} -> 6 | P32: {=_xlfn.SKEW.P(_xlfn._xlws.FILTER(CrowdfundingTable[goal],CrowdfundingTable[primary_category]=A32))} -> 1.7128326
A33: wearables | B33: 45 | C33: 1182800 | D33: 26284.444 | E33: 1.3315773e+09 | F33: 36490.784 | G33: {=MIN(_xlfn._xlws.FILTER(CrowdfundingTable[goal],CrowdfundingTable[subcategory]=A33))} -> 100 | H33: {=_xlfn.QUARTILE.EXC(_xlfn._xlws.FILTER(CrowdfundingTable[goal],CrowdfundingTable[subcategory]=A33),1)} -> 3750 | I33: {=MEDIAN(_xlfn._xlws.FILTER(CrowdfundingTable[goal],CrowdfundingTable[subcategory]=A33))} -> 8600 | J33: {=_xlfn.QUARTILE.EXC(_xlfn._xlws.FILTER(CrowdfundingTable[goal],CrowdfundingTable[subcategory]=A33),3)} -> 30450 | K33: {=MAX(_xlfn._xlws.FILTER(CrowdfundingTable[goal],CrowdfundingTable[subcategory]=A33))} -> 158100 | L33: =J33-H33 -> 26700 | M33: =J33+(1.5*L33) -> 70500 | N33: =H33-(1.5*L33) -> -36300 | O33: {=COUNT(IF(_xlfn._xlws.FILTER(CrowdfundingTable[goal],CrowdfundingTable[subcategory]=A33) > M33,1,Null()))} -> 7 | P33: {=_xlfn.SKEW.P(_xlfn._xlws.FILTER(CrowdfundingTable[goal],CrowdfundingTable[subcategory]=A33))} -> 1.817319
A34: web | B34: 51 | C34: 1994600 | D34: 39109.804 | E34: 3.0798519e+09 | F34: 55496.413 | G34: {=MIN(_xlfn._xlws.FILTER(CrowdfundingTable[goal],CrowdfundingTable[subcategory]=A34))} -> 100 | H34: {=_xlfn.QUARTILE.EXC(_xlfn._xlws.FILTER(CrowdfundingTable[goal],CrowdfundingTable[subcategory]=A34),1)} -> 2900 | I34: {=MEDIAN(_xlfn._xlws.FILTER(CrowdfundingTable[goal],CrowdfundingTable[subcategory]=A34))} -> 7600 | J34: {=_xlfn.QUARTILE.EXC(_xlfn._xlws.FILTER(CrowdfundingTable[goal],CrowdfundingTable[subcategory]=A34),3)} -> 69900 | K34: {=MAX(_xlfn._xlws.FILTER(CrowdfundingTable[goal],CrowdfundingTable[subcategory]=A34))} -> 193400 | L34: =J34-H34 -> 67000 | M34: =J34+(1.5*L34) -> 170400 | N34: =H34-(1.5*L34) -> -97600 | O34: {=COUNT(IF(_xlfn._xlws.FILTER(CrowdfundingTable[goal],CrowdfundingTable[subcategory]=A34) > M34,1,Null()))} -> 2 | P34: {=_xlfn.SKEW.P(_xlfn._xlws.FILTER(CrowdfundingTable[goal],CrowdfundingTable[subcategory]=A34))} -> 1.4425207
A35: theater | B35: 344 | C35: 15637900 | D35: 45459.012 | E35: 3.4065071e+09 | F35: 58365.29 | G35: {=MIN(_xlfn._xlws.FILTER(CrowdfundingTable[goal],CrowdfundingTable[primary_category]=A35))} -> 100 | H35: {=_xlfn.QUARTILE.EXC(_xlfn._xlws.FILTER(CrowdfundingTable[goal],CrowdfundingTable[primary_category]=A35),1)} -> 4900 | I35: {=MEDIAN(_xlfn._xlws.FILTER(CrowdfundingTable[goal],CrowdfundingTable[primary_category]=A35))} -> 8550 | J35: {=_xlfn.QUARTILE.EXC(_xlfn._xlws.FILTER(CrowdfundingTable[goal],CrowdfundingTable[primary_category]=A35),3)} -> 82650 | K35: {=MAX(_xlfn._xlws.FILTER(CrowdfundingTable[goal],CrowdfundingTable[primary_category]=A35))} -> 199200 | L35: =J35-H35 -> 77750 | M35: =J35+(1.5*L35) -> 199275 | N35: =H35-(1.5*L35) -> -111725 | O35: {=COUNT(IF(_xlfn._xlws.FILTER(CrowdfundingTable[goal],CrowdfundingTable[primary_category]=A35) > M35,1,Null()))} -> 0 | P35: {=_xlfn.SKEW.P(_xlfn._xlws.FILTER(CrowdfundingTable[goal],CrowdfundingTable[primary_category]=A35))} -> 1.2168945
A36: plays | B36: 344 | C36: 15637900 | D36: 45459.012 | E36: 3.4065071e+09 | F36: 58365.29 | G36: {=MIN(_xlfn._xlws.FILTER(CrowdfundingTable[goal],CrowdfundingTable[subcategory]=A36))} -> 100 | H36: {=_xlfn.QUARTILE.EXC(_xlfn._xlws.FILTER(CrowdfundingTable[goal],CrowdfundingTable[subcategory]=A36),1)} -> 4900 | I36: {=MEDIAN(_xlfn._xlws.FILTER(CrowdfundingTable[goal],CrowdfundingTable[subcategory]=A36))} -> 8550 | J36: {=_xlfn.QUARTILE.EXC(_xlfn._xlws.FILTER(CrowdfundingTable[goal],CrowdfundingTable[subcategory]=A36),3)} -> 82650 | K36: {=MAX(_xlfn._xlws.FILTER(CrowdfundingTable[goal],CrowdfundingTable[subcategory]=A36))} -> 199200 | L36: =J36-H36 -> 77750 | M36: =J36+(1.5*L36) -> 199275 | N36: =H36-(1.5*L36) -> -111725 | O36: {=COUNT(IF(_xlfn._xlws.FILTER(CrowdfundingTable[goal],CrowdfundingTable[subcategory]=A36) > M36,1,Null()))} -> 0 | P36: {=_xlfn.SKEW.P(_xlfn._xlws.FILTER(CrowdfundingTable[goal],CrowdfundingTable[subcategory]=A36))} -> 1.2168945
A37: Grand Total | B37: 1000 | C37: 43983100 | D37: 43983.1 | E37: 3.4730911e+09 | F37: 58932.937
A39: Adjusted Grand Total | B39: =SUM(B4,B11,B13,B18,B25,B27,B32,B35)-GETPIVOTDATA("Count of goal",$A$3,"Primary Category","music","Subcategory","world music") -> 993 | C39: =SUM(C4,C11,C13,C18,C25,C27,C32,C35)-GETPIVOTDATA("Sum of goal",$A$3,"Primary Category","music","Subcategory","world music") -> 43813100 | D39: =(SUM(D4,D11,D13,D18,D25,D27,D32,D35)-GETPIVOTDATA("Mean of goal",$A$3,"Primary Category","music","Subcategory","world music"))/8 -> 37698.354

Sheet Category-Pledge Statistics
A3: Row Labels | B3: Count of pledged | C3: Sum of pledged | D3: Mean of pledged | E3: Varp of pledged | F3: StdDev of pledged | G3: Min of pledged | H3: 25% | I3: Median of pledged | J3: 75% | K3: Max of pledged | L3: IRQ | M3: Upper T | N3: Lower T | O3: Outlier Count | P3: Skewness
A4: film & video | B4: 178 | C4: 7510076 | D4: 42191.438 | E4: 3.1107222e+09 | F4: 55931.18 | G4: {=MIN(_xlfn._xlws.FILTER(CrowdfundingTable[pledged],CrowdfundingTable[primary_category]=A4))} -> 4 | H4: {=_xlfn.QUARTILE.EXC(_xlfn._xlws.FILTER(CrowdfundingTable[pledged],CrowdfundingTable[primary_category]=A4),1)} -> 6129.25 | I4: {=MEDIAN(_xlfn._xlws.FILTER(CrowdfundingTable[pledged],CrowdfundingTable[primary_category]=A4))} -> 12402.5 | J4: {=_xlfn.QUARTILE.EXC(_xlfn._xlws.FILTER(CrowdfundingTable[pledged],CrowdfundingTable[primary_category]=A4),3)} -> 66350.5 | K4: {=MAX(_xlfn._xlws.FILTER(CrowdfundingTable[pledged],CrowdfundingTable[primary_category]=A4))} -> 199110 | L4: =J4-H4 -> 60221.25 | M4: =J4+(1.5*L4) -> 156682.38 | N4: =H4-(1.5*L4) -> -84202.625 | O4: {=COUNT(IF(_xlfn._xlws.FILTER(CrowdfundingTable[pledged],CrowdfundingTable[primary_category]=A4) > M4,1,Null()))} -> 15 | P4: {=_xlfn.SKEW.P(_xlfn._xlws.FILTER(CrowdfundingTable[pledged],CrowdfundingTable[primary_category]=A4))} -> 1.4704662
A5: animation | B5: 34 | C5: 1700624 | D5: 50018.353 | E5: 4.0598222e+09 | F5: 64674.934 | G5: {=MIN(_xlfn._xlws.FILTER(CrowdfundingTable[pledged],CrowdfundingTable[subcategory]=A5))} -> 4 | H5: {=_xlfn.QUARTILE.EXC(_xlfn._xlws.FILTER(CrowdfundingTable[pledged],CrowdfundingTable[subcategory]=A5),1)} -> 5291.75 | I5: {=MEDIAN(_xlfn._xlws.FILTER(CrowdfundingTable[pledged],CrowdfundingTable[subcategory]=A5))} -> 12075 | J5: {=_xlfn.QUARTILE.EXC(_xlfn._xlws.FILTER(CrowdfundingTable[pledged],CrowdfundingTable[subcategory]=A5),3)} -> 120118.75 | K5: {=MAX(_xlfn._xlws.FILTER(CrowdfundingTable[pledged],CrowdfundingTable[subcategory]=A5))} -> 188480 | L5: =J5-H5 -> 114827 | M5: =J5+(1.5*L5) -> 292359.25 | N5: =H5-(1.5*L5) -> -166948.75 | O5: {=COUNT(IF(_xlfn._xlws.FILTER(CrowdfundingTable[pledged],CrowdfundingTable[subcategory]=A5) > M5,1,Null()))} -> 0 | P5: {=_xlfn.SKEW.P(_xlfn._xlws.FILTER(CrowdfundingTable[pledged],CrowdfundingTable[subcategory]=A5))} -> 1.0643097
A6: documentary | B6: 60 | C6: 2448783 | D6: 40813.05 | E6: 2.4058029e+09 | F6: 49462.907 | G6: {=MIN(_xlfn._xlws.FILTER(CrowdfundingTable[pledged],CrowdfundingTable[subcategory]=A6))} -> 663 | H6: {=_xlfn.QUARTILE.EXC(_xlfn._xlws.FILTER(CrowdfundingTable[pledged],CrowdfundingTable[subcategory]=A6),1)} -> 7226.25 | I6: {=MEDIAN(_xlfn._xlws.FILTER(CrowdfundingTable[pledged],CrowdfundingTable[subcategory]=A6))} -> 13946.5 | J6: {=_xlfn.QUARTILE.EXC(_xlfn._xlws.FILTER(CrowdfundingTable[pledged],CrowdfundingTable[subcategory]=A6),3)} -> 74825.25 | K6: {=MAX(_xlfn._xlws.FILTER(CrowdfundingTable[pledged],CrowdfundingTable[subcategory]=A6))} -> 199110 | L6: =J6-H6 -> 67599 | M6: =J6+(1.5*L6) -> 176223.75 | N6: =H6-(1.5*L6) -> -94172.25 | O6: {=COUNT(IF(_xlfn._xlws.FILTER(CrowdfundingTable[pledged],CrowdfundingTable[subcategory]=A6) > M6,1,Null()))} -> 3 | P6: {=_xlfn.SKEW.P(_xlfn._xlws.FILTER(CrowdfundingTable[pledged],CrowdfundingTable[subcategory]=A6))} -> 1.6133619
A7: drama | B7: 37 | C7: 1208745 | D7: 32668.784 | E7: 2.4240679e+09 | F7: 49913.957 | G7: {=MIN(_xlfn._xlws.FILTER(CrowdfundingTable[pledged],CrowdfundingTable[subcategory]=A7))} -> 1022 | H7: {=_xlfn.QUARTILE.EXC(_xlfn._xlws.FILTER(CrowdfundingTable[pledged],CrowdfundingTable[subcategory]=A7),1)} -> 6189.5 | I7: {=MEDIAN(_xlfn._xlws.FILTER(CrowdfundingTable[pledged],CrowdfundingTable[subcategory]=A7))} -> 11579 | J7: {=_xlfn.QUARTILE.EXC(_xlfn._xlws.FILTER(CrowdfundingTable[pledged],CrowdfundingTable[subcategory]=A7),3)} -> 29347.5 | K7: {=MAX(_xlfn._xlws.FILTER(CrowdfundingTable[pledged],CrowdfundingTable[subcategory]=A7))} -> 188628 | L7: =J7-H7 -> 23158 | M7: =J7+(1.5*L7) -> 64084.5 | N7: =H7-(1.5*L7) -> -28547.5 | O7: {=COUNT(IF(_xlfn._xlws.FILTER(CrowdfundingTable[pledged],CrowdfundingTable[subcategory]=A7) > M7,1,Null()))} -> 6 | P7: {=_xlfn.SKEW.P(_xlfn._xlws.FILTER(CrowdfundingTable[pledged],CrowdfundingTable[subcategory]=A7))} -> 2.0111987
A8: science fiction | B8: 14 | C8: 559713 | D8: 39979.5 | E8: 2.7700669e+09 | F8: 54618.211 | G8: {=MIN(_xlfn._xlws.FILTER(CrowdfundingTable[pledged],CrowdfundingTable[subcategory]=A8))} -> 824 | H8: {=_xlfn.QUARTILE.EXC(_xlfn._xlws.FILTER(CrowdfundingTable[pledged],CrowdfundingTable[subcategory]=A8),1)} -> 5906.75 | I8: {=MEDIAN(_xlfn._xlws.FILTER(CrowdfundingTable[pledged],CrowdfundingTable[subcategory]=A8))} -> 12847.5 | J8: {=_xlfn.QUARTILE.EXC(_xlfn._xlws.FILTER(CrowdfundingTable[pledged],CrowdfundingTable[subcategory]=A8),3)} -> 68658.25 | K8: {=MAX(_xlfn._xlws.FILTER(CrowdfundingTable[pledged],CrowdfundingTable[subcategory]=A8))} -> 186885 | L8: =J8-H8 -> 62751.5 | M8: =J8+(1.5*L8) -> 162785.5 | N8: =H8-(1.5*L8) -> -88220.5 | O8: {=COUNT(IF(_xlfn._xlws.FILTER(CrowdfundingTable[pledged],CrowdfundingTable[subcategory]=A8) > M8,1,Null()))} -> 1 | P8: {=_xlfn.SKEW.P(_xlfn._xlws.FILTER(CrowdfundingTable[pledged],CrowdfundingTable[subcategory]=A8))} -> 1.6383374
A9: shorts | B9: 16 | C9: 855820 | D9: 53488.75 | E9: 4.0664972e+09 | F9: 65860.435 | G9: {=MIN(_xlfn._xlws.FILTER(CrowdfundingTable[pledged],CrowdfundingTable[subcategory]=A9))} -> 2097 | H9: {=_xlfn.QUARTILE.EXC(_xlfn._xlws.FILTER(CrowdfundingTable[pledged],CrowdfundingTable[subcategory]=A9),1)} -> 6580.5 | I9: {=MEDIAN(_xlfn._xlws.FILTER(CrowdfundingTable[pledged],CrowdfundingTable[subcategory]=A9))} -> 14263.5 | J9: {=_xlfn.QUARTILE.EXC(_xlfn._xlws.FILTER(CrowdfundingTable[pledged],CrowdfundingTable[subcategory]=A9),3)} -> 128490.75 | K9: {=MAX(_xlfn._xlws.FILTER(CrowdfundingTable[pledged],CrowdfundingTable[subcategory]=A9))} -> 174039 | L9: =J9-H9 -> 121910.25 | M9: =J9+(1.5*L9) -> 311356.12 | N9: =H9-(1.5*L9) -> -176284.88 | O9: {=COUNT(IF(_xlfn._xlws.FILTER(CrowdfundingTable[pledged],CrowdfundingTable[subcategory]=A9) > M9,1,Null()))} -> 0 | P9: {=_xlfn.SKEW.P(_xlfn._xlws.FILTER(CrowdfundingTable[pledged],CrowdfundingTable[subcategory]=A9))} -> 0.88596696
A10: television | B10: 17 | C10: 736391 | D10: 43317.118 | E10: 4.1239329e+09 | F10: 66194.25 | G10: {=MIN(_xlfn._xlws.FILTER(CrowdfundingTable[pledged],CrowdfundingTable[subcategory]=A10))} -> 718 | H10: {=_xlfn.QUARTILE.EXC(_xlfn._xlws.FILTER(CrowdfundingTable[pledged],CrowdfundingTable[subcategory]=A10),1)} -> 3234 | I10: {=MEDIAN(_xlfn._xlws.FILTER(CrowdfundingTable[pledged],CrowdfundingTable[subcategory]=A10))} -> 9076 | J10: {=_xlfn.QUARTILE.EXC(_xlfn._xlws.FILTER(CrowdfundingTable[pledged],CrowdfundingTable[subcategory]=A10),3)} -> 65289 | K10: {=MAX(_xlfn._xlws.FILTER(CrowdfundingTable[pledged],CrowdfundingTable[subcategory]=A10))} -> 195936 | L10: =J10-H10 -> 62055 | M10: =J10+(1.5*L10) -> 158371.5 | N10: =H10-(1.5*L10) -> -89848.5 | O10: {=COUNT(IF(_xlfn._xlws.FILTER(CrowdfundingTable[pledged],CrowdfundingTable[subcategory]=A10) > M10,1,Null()))} -> 3 | P10: {=_xlfn.SKEW.P(_xlfn._xlws.FILTER(CrowdfundingTable[pledged],CrowdfundingTable[subcategory]=A10))} -> 1.4333881
A11: food | B11: 46 | C11: 1735179 | D11: 37721.283 | E11: 3.0385793e+09 | F11: 55732.426 | G11: {=MIN(_xlfn._xlws.FILTER(CrowdfundingTable[pledged],CrowdfundingTable[primary_category]=A11))} -> 0 | H11: {=_xlfn.QUARTILE.EXC(_xlfn._xlws.FILTER(CrowdfundingTable[pledged],CrowdfundingTable[primary_category]=A11),1)} -> 6507.5 | I11: {=MEDIAN(_xlfn._xlws.FILTER(CrowdfundingTable[pledged],CrowdfundingTable[primary_category]=A11))} -> 10882.5 | J11: {=_xlfn.QUARTILE.EXC(_xlfn._xlws.FILTER(CrowdfundingTable[pledged],CrowdfundingTable[primary_category]=A11),3)} -> 52952.75 | K11: {=MAX(_xlfn._xlws.FILTER(CrowdfundingTable[pledged],CrowdfundingTable[primary_category]=A11))} -> 180667 | L11: =J11-H11 -> 46445.25 | M11: =J11+(1.5*L11) -> 122620.62 | N11: =H11-(1.5*L11) -> -63160.375 | O11: {=COUNT(IF(_xlfn._xlws.FILTER(CrowdfundingTable[pledged],CrowdfundingTable[primary_category]=A11) > M11,1,Null()))} -> 7 | P11: {=_xlfn.SKEW.P(_xlfn._xlws.FILTER(CrowdfundingTable[pledged],CrowdfundingTable[primary_category]=A11))} -> 1.5385263
A12: food trucks | B12: 46 | C12: 1735179 | D12: 37721.283 | E12: 3.0385793e+09 | F12: 55732.426 | G12: {=MIN(_xlfn._xlws.FILTER(CrowdfundingTable[pledged],CrowdfundingTable[subcategory]=A12))} -> 0 | H12: {=_xlfn.QUARTILE.EXC(_xlfn._xlws.FILTER(CrowdfundingTable[pledged],CrowdfundingTable[subcategory]=A12),1)} -> 6507.5 | I12: {=MEDIAN(_xlfn._xlws.FILTER(CrowdfundingTable[pledged],CrowdfundingTable[subcategory]=A12))} -> 10882.5 | J12: {=_xlfn.QUARTILE.EXC(_xlfn._xlws.FILTER(CrowdfundingTable[pledged],CrowdfundingTable[subcategory]=A12),3)} -> 52952.75 | K12: {=MAX(_xlfn._xlws.FILTER(CrowdfundingTable[pledged],CrowdfundingTable[subcategory]=A12))} -> 180667 | L12: =J12-H12 -> 46445.25 | M12: =J12+(1.5*L12) -> 122620.62 | N12: =H12-(1.5*L12) -> -63160.375 | O12: {=COUNT(IF(_xlfn._xlws.FILTER(CrowdfundingTable[pledged],CrowdfundingTable[subcategory]=A12) > M12,1,Null()))} -> 7 | P12: {=_xlfn.SKEW.P(_xlfn._xlws.FILTER(CrowdfundingTable[pledged],CrowdfundingTable[subcategory]=A12))} -> 1.5385263
A13: games | B13: 48 | C13: 2015817 | D13: 41996.188 | E13: 2.2206101e+09 | F13: 47622.023 | G13: {=MIN(_xlfn._xlws.FILTER(CrowdfundingTable[pledged],CrowdfundingTable[primary_category]=A13))} -> 574 | H13: {=_xlfn.QUARTILE.EXC(_xlfn._xlws.FILTER(CrowdfundingTable[pledged],CrowdfundingTable[primary_category]=A13),1)} -> 6919.75 | I13: {=MEDIAN(_xlfn._xlws.FILTER(CrowdfundingTable[pledged],CrowdfundingTable[primary_category]=A13))} -> 14418.5 | J13: {=_xlfn.QUARTILE.EXC(_xlfn._xlws.FILTER(CrowdfundingTable[pledged],CrowdfundingTable[primary_category]=A13),3)} -> 67923.5 | K13: {=MAX(_xlfn._xlws.FILTER(CrowdfundingTable[pledged],CrowdfundingTable[primary_category]=A13))} -> 178338 | L13: =J13-H13 -> 61003.75 | M13: =J13+(1.5*L13) -> 159429.12 | N13: =H13-(1.5*L13) -> -84585.875 | O13: {=COUNT(IF(_xlfn._xlws.FILTER(CrowdfundingTable[pledged],CrowdfundingTable[primary_category]=A13) > M13,1,Null()))} -> 2 | P13: {=_xlfn.SKEW.P(_xlfn._xlws.FILTER(CrowdfundingTable[pledged],CrowdfundingTable[primary_category]=A13))} -> 1.249739
A14: mobile games | B14: 13 | C14: 888866 | D14: 68374.308 | E14: 2.4696515e+09 | F14: 51724.808 | G14: {=MIN(_xlfn._xlws.FILTER(CrowdfundingTable[pledged],CrowdfundingTable[subcategory]=A14))} -> 4275 | H14: {=_xlfn.QUARTILE.EXC(_xlfn._xlws.FILTER(CrowdfundingTable[pledged],CrowdfundingTable[subcategory]=A14),1)} -> 20986.5 | I14: {=MEDIAN(_xlfn._xlws.FILTER(CrowdfundingTable[pledged],CrowdfundingTable[subcategory]=A14))} -> 57034 | J14: {=_xlfn.QUARTILE.EXC(_xlfn._xlws.FILTER(CrowdfundingTable[pledged],CrowdfundingTable[subcategory]=A14),3)} -> 107511.5 | K14: {=MAX(_xlfn._xlws.FILTER(CrowdfundingTable[pledged],CrowdfundingTable[subcategory]=A14))} -> 165798 | L14: =J14-H14 -> 86525 | M14: =J14+(1.5*L14) -> 237299 | N14: =H14-(1.5*L14) -> -108801 | O14: {=COUNT(IF(_xlfn._xlws.FILTER(CrowdfundingTable[pledged],CrowdfundingTable[subcategory]=A14) > M14,1,Null()))} -> 0 | P14: {=_xlfn.SKEW.P(_xlfn._xlws.FILTER(CrowdfundingTable[pledged],CrowdfundingTable[subcategory]=A14))} -> 0.4692207
A15: video games | B15: 35 | C15: 1126951 | D15: 32198.6 | E15: 1.7736743e+09 | F15: 42729.863 | G15: {=MIN(_xlfn._xlws.FILTER(CrowdfundingTable[pledged],CrowdfundingTable[subcategory]=A15))} -> 574 | H15: {=_xlfn.QUARTILE.EXC(_xlfn._xlws.FILTER(CrowdfundingTable[pledged],CrowdfundingTable[subcategory]=A15),1)} -> 6226 | I15: {=MEDIAN(_xlfn._xlws.FILTER(CrowdfundingTable[pledged],CrowdfundingTable[subcategory]=A15))} -> 10850 | J15: {=_xlfn.QUARTILE.EXC(_xlfn._xlws.FILTER(CrowdfundingTable[pledged],CrowdfundingTable[subcategory]=A15),3)} -> 47260 | K15: {=MAX(_xlfn._xlws.FILTER(CrowdfundingTable[pledged],CrowdfundingTable[subcategory]=A15))} -> 178338 | L15: =J15-H15 -> 41034 | M15: =J15+(1.5*L15) -> 108811 | N15: =H15-(1.5*L15) -> -55325 | O15: {=COUNT(IF(_xlfn._xlws.FILTER(CrowdfundingTable[pledged],CrowdfundingTable[subcategory]=A15) > M15,1,Null()))} -> 3 | P15: {=_xlfn.SKEW.P(_xlfn._xlws.FILTER(CrowdfundingTable[pledged],CrowdfundingTable[subcategory]=A15))} -> 1.7621102
A16: journalism | B16: 4 | C16: 36176 | D16: 9044 | E16: 10045638 | F16: 3659.8066 | G16: {=MIN(_xlfn._xlws.FILTER(CrowdfundingTable[pledged],CrowdfundingTable[primary_category]=A16))} -> 4596 | H16: {=_xlfn.QUARTILE.EXC(_xlfn._xlws.FILTER(CrowdfundingTable[pledged],CrowdfundingTable[primary_category]=A16),1)} -> 5321 | I16: {=MEDIAN(_xlfn._xlws.FILTER(CrowdfundingTable[pledged],CrowdfundingTable[primary_category]=A16))} -> 9712.5 | J16: {=_xlfn.QUARTILE.EXC(_xlfn._xlws.FILTER(CrowdfundingTable[pledged],CrowdfundingTable[primary_category]=A16),3)} -> 12098.5 | K16: {=MAX(_xlfn._xlws.FILTER(CrowdfundingTable[pledged],CrowdfundingTable[primary_category]=A16))} -> 12155 | L16: =J16-H16 -> 6777.5 | M16: =J16+(1.5*L16) -> 22264.75 | N16: =H16-(1.5*L16) -> -4845.25 | O16: {=COUNT(IF(_xlfn._xlws.FILTER(CrowdfundingTable[pledged],CrowdfundingTable[primary_category]=A16) > M16,1,Null()))} -> 0 | P16: {=_xlfn.SKEW.P(_xlfn._xlws.FILTER(CrowdfundingTable[pledged],CrowdfundingTable[primary_category]=A16))} -> -0.29515283
A17: audio | B17: 4 | C17: 36176 | D17: 9044 | E17: 10045638 | F17: 3659.8066 | G17: {=MIN(_xlfn._xlws.FILTER(CrowdfundingTable[pledged],CrowdfundingTable[subcategory]=A17))} -> 4596 | H17: {=_xlfn.QUARTILE.EXC(_xlfn._xlws.FILTER(CrowdfundingTable[pledged],CrowdfundingTable[subcategory]=A17),1)} -> 5321 | I17: {=MEDIAN(_xlfn._xlws.FILTER(CrowdfundingTable[pledged],CrowdfundingTable[subcategory]=A17))} -> 9712.5 | J17: {=_xlfn.QUARTILE.EXC(_xlfn._xlws.FILTER(CrowdfundingTable[pledged],CrowdfundingTable[subcategory]=A17),3)} -> 12098.5 | K17: {=MAX(_xlfn._xlws.FILTER(CrowdfundingTable[pledged],CrowdfundingTable[subcategory]=A17))} -> 12155 | L17: =J17-H17 -> 6777.5 | M17: =J17+(1.5*L17) -> 22264.75 | N17: =H17-(1.5*L17) -> -4845.25 | O17: {=COUNT(IF(_xlfn._xlws.FILTER(CrowdfundingTable[pledged],CrowdfundingTable[subcategory]=A17) > M17,1,Null()))} -> 0 | P17: {=_xlfn.SKEW.P(_xlfn._xlws.FILTER(CrowdfundingTable[pledged],CrowdfundingTable[subcategory]=A17))} -> -0.29515283
A18: music | B18: 175 | C18: 7480097 | D18: 42743.411 | E18: 3.5239498e+09 | F18: 59533.204 | G18: {=MIN(_xlfn._xlws.FILTER(CrowdfundingTable[pledged],CrowdfundingTable[primary_category]=A18))} -> 1 | H18: {=_xlfn.QUARTILE.EXC(_xlfn._xlws.FILTER(CrowdfundingTable[pledged],CrowdfundingTable[primary_category]=A18),1)} -> 5028 | I18: {=MEDIAN(_xlfn._xlws.FILTER(CrowdfundingTable[pledged],CrowdfundingTable[primary_category]=A18))} -> 11075 | J18: {=_xlfn.QUARTILE.EXC(_xlfn._xlws.FILTER(CrowdfundingTable[pledged],CrowdfundingTable[primary_category]=A18),3)} -> 62804 | K18: {=MAX(_xlfn._xlws.FILTER(CrowdfundingTable[pledged],CrowdfundingTable[primary_category]=A18))} -> 198628 | L18: =J18-H18 -> 57776 | M18: =J18+(1.5*L18) -> 149468 | N18: =H18-(1.5*L18) -> -81636 | O18: {=SUMPRODUCT(--_xlfn._xlws.FILTER(CrowdfundingTable[pledged],CrowdfundingTable[primary_category]=A18) > M18)} -> 0 | P18: {=_xlfn.SKEW.P(_xlfn._xlws.FILTER(CrowdfundingTable[pledged],CrowdfundingTable[primary_category]=A18))} -> 1.4107351
A19: electric music | B19: 18 | C19: 781148 | D19: 43397.111 | E19: 3.8248252e+09 | F19: 63638.156 | G19: {=MIN(_xlfn._xlws.FILTER(CrowdfundingTable[pledged],CrowdfundingTable[subcategory]=A19))} -> 1 | H19: {=_xlfn.QUARTILE.EXC(_xlfn._xlws.FILTER(CrowdfundingTable[pledged],CrowdfundingTable[subcategory]=A19),1)} -> 5561.75 | I19: {=MEDIAN(_xlfn._xlws.FILTER(CrowdfundingTable[pledged],CrowdfundingTable[subcategory]=A19))} -> 10988 | J19: {=_xlfn.QUARTILE.EXC(_xlfn._xlws.FILTER(CrowdfundingTable[pledged],CrowdfundingTable[subcategory]=A19),3)} -> 64877 | K19: {=MAX(_xlfn._xlws.FILTER(CrowdfundingTable[pledged],CrowdfundingTable[subcategory]=A19))} -> 196960 | L19: =J19-H19 -> 59315.25 | M19: =J19+(1.5*L19) -> 153849.88 | N19: =H19-(1.5*L19) -> -83411.125 | O19: {=COUNT(IF(_xlfn._xlws.FILTER(CrowdfundingTable[pledged],CrowdfundingTable[subcategory]=A19) > M19,1,Null()))} -> 2 | P19: {=_xlfn.SKEW.P(_xlfn._xlws.FILTER(CrowdfundingTable[pledged],CrowdfundingTable[subcategory]=A19))} -> 1.610061
A20: indie rock | B20: 45 | C20: 2037576 | D20: 45279.467 | E20: 3.7833174e+09 | F20: 62203.713 | G20: {=MIN(_xlfn._xlws.FILTER(CrowdfundingTable[pledged],CrowdfundingTable[subcategory]=A20))} -> 4 | H20: {=_xlfn.QUARTILE.EXC(_xlfn._xlws.FILTER(CrowdfundingTable[pledged],CrowdfundingTable[subcategory]=A20),1)} -> 4057.5 | I20: {=MEDIAN(_xlfn._xlws.FILTER(CrowdfundingTable[pledged],CrowdfundingTable[subcategory]=A20))} -> 10295 | J20: {=_xlfn.QUARTILE.EXC(_xlfn._xlws.FILTER(CrowdfundingTable[pledged],CrowdfundingTable[subcategory]=A20),3)} -> 86366 | K20: {=MAX(_xlfn._xlws.FILTER(CrowdfundingTable[pledged],CrowdfundingTable[subcategory]=A20))} -> 184086 | L20: =J20-H20 -> 82308.5 | M20: =J20+(1.5*L20) -> 209828.75 | N20: =H20-(1.5*L20) -> -119405.25 | O20: {=COUNT(IF(_xlfn._xlws.FILTER(CrowdfundingTable[pledged],CrowdfundingTable[subcategory]=A20) > M20,1,Null()))} -> 0 | P20: {=_xlfn.SKEW.P(_xlfn._xlws.FILTER(CrowdfundingTable[pledged],CrowdfundingTable[subcategory]=A20))} -> 1.2209814
A21: jazz | B21: 17 | C21: 550966 | D21: 32409.765 | E21: 2.2317975e+09 | F21: 48695.84 | G21: {=MIN(_xlfn._xlws.FILTER(CrowdfundingTable[pledged],CrowdfundingTable[subcategory]=A21))} -> 2 | H21: {=_xlfn.QUARTILE.EXC(_xlfn._xlws.FILTER(CrowdfundingTable[pledged],CrowdfundingTable[subcategory]=A21),1)} -> 4366.5 | I21: {=MEDIAN(_xlfn._xlws.FILTER(CrowdfundingTable[pledged],CrowdfundingTable[subcategory]=A21))} -> 11075 | J21: {=_xlfn.QUARTILE.EXC(_xlfn._xlws.FILTER(CrowdfundingTable[pledged],CrowdfundingTable[subcategory]=A21),3)} -> 42221.5 | K21: {=MAX(_xlfn._xlws.FILTER(CrowdfundingTable[pledged],CrowdfundingTable[subcategory]=A21))} -> 150960 | L21: =J21-H21 -> 37855 | M21: =J21+(1.5*L21) -> 99004 | N21: =H21-(1.5*L21) -> -52416 | O21: {=COUNT(IF(_xlfn._xlws.FILTER(CrowdfundingTable[pledged],CrowdfundingTable[subcategory]=A21) > M21,1,Null()))} -> 2 | P21: {=_xlfn.SKEW.P(_xlfn._xlws.FILTER(CrowdfundingTable[pledged],CrowdfundingTable[subcategory]=A21))} -> 1.6748586
A22: metal | B22: 7 | C22: 281185 | D22: 40169.286 | E22: 3.918486e+09 | F22: 67613.364 | G22: {=MIN(_xlfn._xlws.FILTER(CrowdfundingTable[pledged],CrowdfundingTable[subcategory]=A22))} -> 2 | H22: {=_xlfn.QUARTILE.EXC(_xlfn._xlws.FILTER(CrowdfundingTable[pledged],CrowdfundingTable[subcategory]=A22),1)} -> 1012 | I22: {=MEDIAN(_xlfn._xlws.FILTER(CrowdfundingTable[pledged],CrowdfundingTable[subcategory]=A22))} -> 5476 | J22: {=_xlfn.QUARTILE.EXC(_xlfn._xlws.FILTER(CrowdfundingTable[pledged],CrowdfundingTable[subcategory]=A22),3)} -> 83267 | K22: {=MAX(_xlfn._xlws.FILTER(CrowdfundingTable[pledged],CrowdfundingTable[subcategory]=A22))} -> 177936 | L22: =J22-H22 -> 82255 | M22: =J22+(1.5*L22) -> 206649.5 | N22: =H22-(1.5*L22) -> -122370.5 | O22: {=COUNT(IF(_xlfn._xlws.FILTER(CrowdfundingTable[pledged],CrowdfundingTable[subcategory]=A22) > M22,1,Null()))} -> 0 | P22: {=_xlfn.SKEW.P(_xlfn._xlws.FILTER(CrowdfundingTable[pledged],CrowdfundingTable[subcategory]=A22))} -> 1.4284974
A23: rock | B23: 85 | C23: 3603659 | D23: 42395.988 | E23: 3.5389213e+09 | F23: 59841.886 | G23: {=MIN(_xlfn._xlws.FILTER(CrowdfundingTable[pledged],CrowdfundingTable[subcategory]=A23))} -> 1 | H23: {=_xlfn.QUARTILE.EXC(_xlfn._xlws.FILTER(CrowdfundingTable[pledged],CrowdfundingTable[subcategory]=A23),1)} -> 4966.5 | I23: {=MEDIAN(_xlfn._xlws.FILTER(CrowdfundingTable[pledged],CrowdfundingTable[subcategory]=A23))} -> 11721 | J23: {=_xlfn.QUARTILE.EXC(_xlfn._xlws.FILTER(CrowdfundingTable[pledged],CrowdfundingTable[subcategory]=A23),3)} -> 61899 | K23: {=MAX(_xlfn._xlws.FILTER(CrowdfundingTable[pledged],CrowdfundingTable[subcategory]=A23))} -> 198628 | L23: =J23-H23 -> 56932.5 | M23: =J23+(1.5*L23) -> 147297.75 | N23: =H23-(1.5*L23) -> -80432.25 | O23: {=COUNT(IF(_xlfn._xlws.FILTER(CrowdfundingTable[pledged],CrowdfundingTable[subcategory]=A23) > M23,1,Null()))} -> 10 | P23: {=_xlfn.SKEW.P(_xlfn._xlws.FILTER(CrowdfundingTable[pledged],CrowdfundingTable[subcategory]=A23))} -> 1.4681313
A24: world music | B24: 3 | C24: 225563 | D24: 75187.667 | E24: 2.0299444e+09 | F24: 55180.763 | G24: {=MIN(_xlfn._xlws.FILTER(CrowdfundingTable[pledged],CrowdfundingTable[subcategory]=A24))} -> 13985 | H24: {=_xlfn.QUARTILE.EXC(_xlfn._xlws.FILTER(CrowdfundingTable[pledged],CrowdfundingTable[subcategory]=A24),1)} -> 13985 | I24: {=MEDIAN(_xlfn._xlws.FILTER(CrowdfundingTable[pledged],CrowdfundingTable[subcategory]=A24))} -> 90440 | J24: {=_xlfn.QUARTILE.EXC(_xlfn._xlws.FILTER(CrowdfundingTable[pledged],CrowdfundingTable[subcategory]=A24),3)} -> 121138 | K24: {=MAX(_xlfn._xlws.FILTER(CrowdfundingTable[pledged],CrowdfundingTable[subcategory]=A24))} -> 121138 | L24: =J24-H24 -> 107153 | M24: =J24+(1.5*L24) -> 281867.5 | N24: =H24-(1.5*L24) -> -146744.5 | O24: {=COUNT(IF(_xlfn._xlws.FILTER(CrowdfundingTable[pledged],CrowdfundingTable[subcategory]=A24) > M24,1,Null()))} -> 0 | P24: {=_xlfn.SKEW.P(_xlfn._xlws.FILTER(CrowdfundingTable[pledged],CrowdfundingTable[subcategory]=A24))} -> -0.46899594
A25: photography | B25: 42 | C25: 1223931 | D25: 29141.214 | E25: 1.8784814e+09 | F25: 43866.822 | G25: {=MIN(_xlfn._xlws.FILTER(CrowdfundingTable[pledged],CrowdfundingTable[primary_category]=A25))} -> 2 | H25: {=_xlfn.QUARTILE.EXC(_xlfn._xlws.FILTER(CrowdfundingTable[pledged],CrowdfundingTable[primary_category]=A25),1)} -> 5601.5 | I25: {=MEDIAN(_xlfn._xlws.FILTER(CrowdfundingTable[pledged],CrowdfundingTable[primary_category]=A25))} -> 10420 | J25: {=_xlfn.QUARTILE.EXC(_xlfn._xlws.FILTER(CrowdfundingTable[pledged],CrowdfundingTable[primary_category]=A25),3)} -> 19695.5 | K25: {=MAX(_xlfn._xlws.FILTER(CrowdfundingTable[pledged],CrowdfundingTable[primary_category]=A25))} -> 173191 | L25: =J25-H25 -> 14094 | M25: =J25+(1.5*L25) -> 40836.5 | N25: =H25-(1.5*L25) -> -15539.5 | O25: {=COUNT(IF(_xlfn._xlws.FILTER(CrowdfundingTable[pledged],CrowdfundingTable[primary_category]=A25) > M25,1,Null()))} -> 9 | P25: {=_xlfn.SKEW.P(_xlfn._xlws.FILTER(CrowdfundingTable[pledged],CrowdfundingTable[primary_category]=A25))} -> 1.9012944
A26: photography books | B26: 42 | C26: 1223931 | D26: 29141.214 | E26: 1.8784814e+09 | F26: 43866.822 | G26: {=MIN(_xlfn._xlws.FILTER(CrowdfundingTable[pledged],CrowdfundingTable[subcategory]=A26))} -> 2 | H26: {=_xlfn.QUARTILE.EXC(_xlfn._xlws.FILTER(CrowdfundingTable[pledged],CrowdfundingTable[subcategory]=A26),1)} -> 5601.5 | I26: {=MEDIAN(_xlfn._xlws.FILTER(CrowdfundingTable[pledged],CrowdfundingTable[subcategory]=A26))} -> 10420 | J26: {=_xlfn.QUARTILE.EXC(_xlfn._xlws.FILTER(CrowdfundingTable[pledged],CrowdfundingTable[subcategory]=A26),3)} -> 19695.5 | K26: {=MAX(_xlfn._xlws.FILTER(CrowdfundingTable[pledged],CrowdfundingTable[subcategory]=A26))} -> 173191 | L26: =J26-H26 -> 14094 | M26: =J26+(1.5*L26) -> 40836.5 | N26: =H26-(1.5*L26) -> -15539.5 | O26: {=COUNT(IF(_xlfn._xlws.FILTER(CrowdfundingTable[pledged],CrowdfundingTable[subcategory]=A26) > M26,1,Null()))} -> 9 | P26: {=_xlfn.SKEW.P(_xlfn._xlws.FILTER(CrowdfundingTable[pledged],CrowdfundingTable[subcategory]=A26))} -> 1.9012944
A27: publishing | B27: 67 | C27: 3149827 | D27: 47012.343 | E27: 3.7164205e+09 | F27: 61422.552 | G27: {=MIN(_xlfn._xlws.FILTER(CrowdfundingTable[pledged],CrowdfundingTable[primary_category]=A27))} -> 5 | H27: {=_xlfn.QUARTILE.EXC(_xlfn._xlws.FILTER(CrowdfundingTable[pledged],CrowdfundingTable[primary_category]=A27),1)} -> 6631 | I27: {=MEDIAN(_xlfn._xlws.FILTER(CrowdfundingTable[pledged],CrowdfundingTable[primary_category]=A27))} -> 11990 | J27: {=_xlfn.QUARTILE.EXC(_xlfn._xlws.FILTER(CrowdfundingTable[pledged],CrowdfundingTable[primary_category]=A27),3)} -> 74688 | K27: {=MAX(_xlfn._xlws.FILTER(CrowdfundingTable[pledged],CrowdfundingTable[primary_category]=A27))} -> 197728 | L27: =J27-H27 -> 68057 | M27: =J27+(1.5*L27) -> 176773.5 | N27: =H27-(1.5*L27) -> -95454.5 | O27: {=COUNT(IF(_xlfn._xlws.FILTER(CrowdfundingTable[pledged],CrowdfundingTable[primary_category]=A27) > M27,1,Null()))} -> 4 | P27: {=_xlfn.SKEW.P(_xlfn._xlws.FILTER(CrowdfundingTable[pledged],CrowdfundingTable[primary_category]=A27))} -> 1.292834
A28: fiction | B28: 17 | C28: 897309 | D28: 52782.882 | E28: 4.0457437e+09 | F28: 65563.73 | G28: {=MIN(_xlfn._xlws.FILTER(CrowdfundingTable[pledged],CrowdfundingTable[subcategory]=A28))} -> 689 | H28: {=_xlfn.QUARTILE.EXC(_xlfn._xlws.FILTER(CrowdfundingTable[pledged],CrowdfundingTable[subcategory]=A28),1)} -> 9092.5 | I28: {=MEDIAN(_xlfn._xlws.FILTER(CrowdfundingTable[pledged],CrowdfundingTable[subcategory]=A28))} -> 14046 | J28: {=_xlfn.QUARTILE.EXC(_xlfn._xlws.FILTER(CrowdfundingTable[pledged],CrowdfundingTable[subcategory]=A28),3)} -> 92191.5 | K28: {=MAX(_xlfn._xlws.FILTER(CrowdfundingTable[pledged],CrowdfundingTable[subcategory]=A28))} -> 194309 | L28: =J28-H28 -> 83099 | M28: =J28+(1.5*L28) -> 216840 | N28: =H28-(1.5*L28) -> -115556 | O28: {=COUNT(IF(_xlfn._xlws.FILTER(CrowdfundingTable[pledged],CrowdfundingTable[subcategory]=A28) > M28,1,Null()))} -> 0 | P28: {=_xlfn.SKEW.P(_xlfn._xlws.FILTER(CrowdfundingTable[pledged],CrowdfundingTable[subcategory]=A28))} -> 1.182138
A29: nonfiction | B29: 21 | C29: 1129497 | D29: 53785.571 | E29: 4.0354806e+09 | F29: 65094.198 | G29: {=MIN(_xlfn._xlws.FILTER(CrowdfundingTable[pledged],CrowdfundingTable[subcategory]=A29))} -> 5 | H29: {=_xlfn.QUARTILE.EXC(_xlfn._xlws.FILTER(CrowdfundingTable[pledged],CrowdfundingTable[subcategory]=A29),1)} -> 5075 | I29: {=MEDIAN(_xlfn._xlws.FILTER(CrowdfundingTable[pledged],CrowdfundingTable[subcategory]=A29))} -> 11041 | J29: {=_xlfn.QUARTILE.EXC(_xlfn._xlws.FILTER(CrowdfundingTable[pledged],CrowdfundingTable[subcategory]=A29),3)} -> 102276.5 | K29: {=MAX(_xlfn._xlws.FILTER(CrowdfundingTable[pledged],CrowdfundingTable[subcategory]=A29))} -> 189192 | L29: =J29-H29 -> 97201.5 | M29: =J29+(1.5*L29) -> 248078.75 | N29: =H29-(1.5*L29) -> -140727.25 | O29: {=COUNT(IF(_xlfn._xlws.FILTER(CrowdfundingTable[pledged],CrowdfundingTable[subcategory]=A29) > M29,1,Null()))} -> 0 | P29: {=_xlfn.SKEW.P(_xlfn._xlws.FILTER(CrowdfundingTable[pledged],CrowdfundingTable[subcategory]=A29))} -> 0.94084519
A30: radio & podcasts | B30: 8 | C30: 285580 | D30: 35697.5 | E30: 2972528422 | F30: 58285.293 | G30: {=MIN(_xlfn._xlws.FILTER(CrowdfundingTable[pledged],CrowdfundingTable[subcategory]=A30))} -> 795 | H30: {=_xlfn.QUARTILE.EXC(_xlfn._xlws.FILTER(CrowdfundingTable[pledged],CrowdfundingTable[subcategory]=A30),1)} -> 5130.25 | I30: {=MEDIAN(_xlfn._xlws.FILTER(CrowdfundingTable[pledged],CrowdfundingTable[subcategory]=A30))} -> 10097.5 | J30: {=_xlfn.QUARTILE.EXC(_xlfn._xlws.FILTER(CrowdfundingTable[pledged],CrowdfundingTable[subcategory]=A30),3)} -> 58364 | K30: {=MAX(_xlfn._xlws.FILTER(CrowdfundingTable[pledged],CrowdfundingTable[subcategory]=A30))} -> 167717 | L30: =J30-H30 -> 53233.75 | M30: =J30+(1.5*L30) -> 138214.62 | N30: =H30-(1.5*L30) -> -74720.375 | O30: {=COUNT(IF(_xlfn._xlws.FILTER(CrowdfundingTable[pledged],CrowdfundingTable[subcategory]=A30) > M30,1,Null()))} -> 1 | P30: {=_xlfn.SKEW.P(_xlfn._xlws.FILTER(CrowdfundingTable[pledged],CrowdfundingTable[subcategory]=A30))} -> 1.7053776
A31: translations | B31: 21 | C31: 837441 | D31: 39878.143 | E31: 3.2416513e+09 | F31: 58341.528 | G31: {=MIN(_xlfn._xlws.FILTER(CrowdfundingTable[pledged],CrowdfundingTable[subcategory]=A31))} -> 521 | H31: {=_xlfn.QUARTILE.EXC(_xlfn._xlws.FILTER(CrowdfundingTable[pledged],CrowdfundingTable[subcategory]=A31),1)} -> 7616 | I31: {=MEDIAN(_xlfn._xlws.FILTER(CrowdfundingTable[pledged],CrowdfundingTable[subcategory]=A31))} -> 12467 | J31: {=_xlfn.QUARTILE.EXC(_xlfn._xlws.FILTER(CrowdfundingTable[pledged],CrowdfundingTable[subcategory]=A31),3)} -> 64722.5 | K31: {=MAX(_xlfn._xlws.FILTER(CrowdfundingTable[pledged],CrowdfundingTable[subcategory]=A31))} -> 197728 | L31: =J31-H31 -> 57106.5 | M31: =J31+(1.5*L31) -> 150382.25 | N31: =H31-(1.5*L31) -> -78043.75 | O31: {=COUNT(IF(_xlfn._xlws.FILTER(CrowdfundingTable[pledged],CrowdfundingTable[subcategory]=A31) > M31,1,Null()))} -> 2 | P31: {=_xlfn.SKEW.P(_xlfn._xlws.FILTER(CrowdfundingTable[pledged],CrowdfundingTable[subcategory]=A31))} -> 1.6869001
A32: technology | B32: 96 | C32: 3833725 | D32: 39934.635 | E32: 2.8711499e+09 | F32: 53864.39 | G32: {=MIN(_xlfn._xlws.FILTER(CrowdfundingTable[pledged],CrowdfundingTable[primary_category]=A32))} -> 2 | H32: {=_xlfn.QUARTILE.EXC(_xlfn._xlws.FILTER(CrowdfundingTable[pledged],CrowdfundingTable[primary_category]=A32),1)} -> 5438.75 | I32: {=MEDIAN(_xlfn._xlws.FILTER(CrowdfundingTable[pledged],CrowdfundingTable[primary_category]=A32))} -> 12274 | J32: {=_xlfn.QUARTILE.EXC(_xlfn._xlws.FILTER(CrowdfundingTable[pledged],CrowdfundingTable[primary_category]=A32),3)} -> 63774.25 | K32: {=MAX(_xlfn._xlws.FILTER(CrowdfundingTable[pledged],CrowdfundingTable[primary_category]=A32))} -> 196386 | L32: =J32-H32 -> 58335.5 | M32: =J32+(1.5*L32) -> 151277.5 | N32: =H32-(1.5*L32) -> -82064.5 | O32: {=COUNT(IF(_xlfn._xlws.FILTER(CrowdfundingTable[pledged],CrowdfundingTable[primary_category]=A32) > M32,1,Null()))} -> 6 | P32: {=_xlfn.SKEW.P(_xlfn._xlws.FILTER(CrowdfundingTable[pledged],CrowdfundingTable[primary_category]=A32))} -> 1.4228258
A33: wearables | B33: 45 | C33: 1638382 | D33: 36408.489 | E33: 2.5921405e+09 | F33: 51488.376 | G33: {=MIN(_xlfn._xlws.FILTER(CrowdfundingTable[pledged],CrowdfundingTable[subcategory]=A33))} -> 3 | H33: {=_xlfn.QUARTILE.EXC(_xlfn._xlws.FILTER(CrowdfundingTable[pledged],CrowdfundingTable[subcategory]=A33),1)} -> 5273 | I33: {=MEDIAN(_xlfn._xlws.FILTER(CrowdfundingTable[pledged],CrowdfundingTable[subcategory]=A33))} -> 12985 | J33: {=_xlfn.QUARTILE.EXC(_xlfn._xlws.FILTER(CrowdfundingTable[pledged],CrowdfundingTable[subcategory]=A33),3)} -> 42179.5 | K33: {=MAX(_xlfn._xlws.FILTER(CrowdfundingTable[pledged],CrowdfundingTable[subcategory]=A33))} -> 188057 | L33: =J33-H33 -> 36906.5 | M33: =J33+(1.5*L33) -> 97539.25 | N33: =H33-(1.5*L33) -> -50086.75 | O33: {=COUNT(IF(_xlfn._xlws.FILTER(CrowdfundingTable[pledged],CrowdfundingTable[subcategory]=A33) > M33,1,Null()))} -> 7 | P33: {=_xlfn.SKEW.P(_xlfn._xlws.FILTER(CrowdfundingTable[pledged],CrowdfundingTable[subcategory]=A33))} -> 1.7047369
A34: web | B34: 51 | C34: 2195343 | D34: 43045.941 | E34: 3.0966834e+09 | F34: 56201.576 | G34: {=MIN(_xlfn._xlws.FILTER(CrowdfundingTable[pledged],CrowdfundingTable[subcategory]=A34))} -> 2 | H34: {=_xlfn.QUARTILE.EXC(_xlfn._xlws.FILTER(CrowdfundingTable[pledged],CrowdfundingTable[subcategory]=A34),1)} -> 6775 | I34: {=MEDIAN(_xlfn._xlws.FILTER(CrowdfundingTable[pledged],CrowdfundingTable[subcategory]=A34))} -> 11941 | J34: {=_xlfn.QUARTILE.EXC(_xlfn._xlws.FILTER(CrowdfundingTable[pledged],CrowdfundingTable[subcategory]=A34),3)} -> 97524 | K34: {=MAX(_xlfn._xlws.FILTER(CrowdfundingTable[pledged],CrowdfundingTable[subcategory]=A34))} -> 196386 | L34: =J34-H34 -> 90749 | M34: =J34+(1.5*L34) -> 233647.5 | N34: =H34-(1.5*L34) -> -129348.5 | O34: {=COUNT(IF(_xlfn._xlws.FILTER(CrowdfundingTable[pledged],CrowdfundingTable[subcategory]=A34) > M34,1,Null()))} -> 0 | P34: {=_xlfn.SKEW.P(_xlfn._xlws.FILTER(CrowdfundingTable[pledged],CrowdfundingTable[subcategory]=A34))} -> 1.2118131
A35: theater | B35: 344 | C35: 15763227 | D35: 45823.334 | E35: 3.6456807e+09 | F35: 60467.425 | G35: {=MIN(_xlfn._xlws.FILTER(CrowdfundingTable[pledged],CrowdfundingTable[primary_category]=A35))} -> 0 | H35: {=_xlfn.QUARTILE.EXC(_xlfn._xlws.FILTER(CrowdfundingTable[pledged],CrowdfundingTable[primary_category]=A35),1)} -> 5841.5 | I35: {=MEDIAN(_xlfn._xlws.FILTER(CrowdfundingTable[pledged],CrowdfundingTable[primary_category]=A35))} -> 11817.5 | J35: {=_xlfn.QUARTILE.EXC(_xlfn._xlws.FILTER(CrowdfundingTable[pledged],CrowdfundingTable[primary_category]=A35),3)} -> 81962.25 | K35: {=MAX(_xlfn._xlws.FILTER(CrowdfundingTable[pledged],CrowdfundingTable[primary_category]=A35))} -> 197024 | L35: =J35-H35 -> 76120.75 | M35: =J35+(1.5*L35) -> 196143.38 | N35: =H35-(1.5*L35) -> -108339.62 | O35: {=COUNT(IF(_xlfn._xlws.FILTER(CrowdfundingTable[pledged],CrowdfundingTable[primary_category]=A35) > M35,1,Null()))} -> 3 | P35: {=_xlfn.SKEW.P(_xlfn._xlws.FILTER(CrowdfundingTable[pledged],CrowdfundingTable[primary_category]=A35))} -> 1.2676639
A36: plays | B36: 344 | C36: 15763227 | D36: 45823.334 | E36: 3.6456807e+09 | F36: 60467.425 | G36: {=MIN(_xlfn._xlws.FILTER(CrowdfundingTable[pledged],CrowdfundingTable[subcategory]=A36))} -> 0 | H36: {=_xlfn.QUARTILE.EXC(_xlfn._xlws.FILTER(CrowdfundingTable[pledged],CrowdfundingTable[subcategory]=A36),1)} -> 5841.5 | I36: {=MEDIAN(_xlfn._xlws.FILTER(CrowdfundingTable[pledged],CrowdfundingTable[subcategory]=A36))} -> 11817.5 | J36: {=_xlfn.QUARTILE.EXC(_xlfn._xlws.FILTER(CrowdfundingTable[pledged],CrowdfundingTable[subcategory]=A36),3)} -> 81962.25 | K36: {=MAX(_xlfn._xlws.FILTER(CrowdfundingTable[pledged],CrowdfundingTable[subcategory]=A36))} -> 197024 | L36: =J36-H36 -> 76120.75 | M36: =J36+(1.5*L36) -> 196143.38 | N36: =H36-(1.5*L36) -> -108339.62 | O36: {=COUNT(IF(_xlfn._xlws.FILTER(CrowdfundingTable[pledged],CrowdfundingTable[subcategory]=A36) > M36,1,Null()))} -> 3 | P36: {=_xlfn.SKEW.P(_xlfn._xlws.FILTER(CrowdfundingTable[pledged],CrowdfundingTable[subcategory]=A36))} -> 1.2676639
A37: Grand Total | B37: 1000 | C37: 42748055 | D37: 42748.055 | E37: 3.293241e+09 | F37: 57415.482
A39: Adjusted Grand Total | B39: =SUM(B4,B11,B13,B18,B25,B27,B32,B35)-GETPIVOTDATA("Count of pledged",$A$3,"Primary Category","music","Subcategory","world music") -> 993 | C39: =SUM(C4,C11,C13,C18,C25,C27,C32,C35)-GETPIVOTDATA("Sum of pledged",$A$3,"Primary Category","music","Subcategory","world music") -> 42486316 | D39: =(SUM(D4,D11,D13,D18,D25,D27,D32,D35)-GETPIVOTDATA("Mean of pledged",$A$3,"Primary Category","music","Subcategory","world music"))/8 -> 31422.023

Sheet StdDev Goal-Pledge vs. Outcomes
A1: country | B1: (All)
A2: Years | B2: (All)
A4: Row Labels | B4: StdDev of goal | C4: StdDev of pledged
A5: canceled | B5: 70557.059 | C5: 35632.421
A6: failed | B6: 69884.438 | C6: 45774.532
A7: live | B7: 76831.208 | C7: 52169.659
A8: successful | B8: 40734.339 | C8: 64552.37
A9: Grand Total | B9: 58962.426 | C9: 57415.482

Sheet Statistical Analysis (Backers)
A1: {=_xlfn._xlws.FILTER(CrowdfundingTable[[outcome]:[backers_count]],CrowdfundingTable[outcome]="successful")} -> successful | B1: 158 | D1: {=_xlfn._xlws.FILTER(CrowdfundingTable[[outcome]:[backers_count]],CrowdfundingTable[outcome]="failed")} -> failed | E1: 0 | F1: {=_xlfn._xlws.FILTER(CrowdfundingTable[[outcome]:[backers_count]],CrowdfundingTable[outcome]="canceled")} -> canceled | G1: 135 | H1: {=_xlfn._xlws.FILTER(CrowdfundingTable[[outcome]:[backers_count]],CrowdfundingTable[outcome]="live")} -> live | I1: 708 | M1: Category | N1: Successful Campaigns | O1: Failed Campaigns | P1: Canceled Campaigns | Q1: Live Campaigns
A2: successful | B2: 1425 | D2: failed | E2: 24 | F2: canceled | G2: 1480 | H2: live | I2: 808 | M2: Total Backers | N2: =SUM($B$1:$B$565) -> 480898 | O2: =SUM($E$1:$E$565) -> 213164 | P2: =SUM($G$1:$G$57) -> 24768 | Q2: =SUM($I$1:$I$14) -> 8175
A3: successful | B3: 174 | D3: failed | E3: 53 | F3: canceled | G3: 17 | H3: live | I3: 61 | M3: Mean | N3: =AVERAGE($B$1:$B$565) -> 851.1469 | O3: =AVERAGE($E$1:$E$565) -> 585.61538 | P3: =AVERAGE($G$1:$G$57) -> 434.52632 | Q3: =AVERAGE($I$1:$I$14) -> 583.92857
A4: successful | B4: 227 | D4: failed | E4: 18 | F4: canceled | G4: 610 | H4: live | I4: 211 | M4: Mode | N4: =MODE($B$1:$B$565) -> 85 | O4: =MODE($E$1:$E$565) -> 1 | P4: =MODE($G$1:$G$57) -> 75 | Q4: =MODE($I$1:$I$14) -> #N/A
A5: successful | B5: 220 | D5: failed | E5: 44 | F5: canceled | G5: 532 | H5: live | I5: 86 | M5: Minimum | N5: =MIN($B$1:$B$565) -> 16 | O5: =MIN($E$1:$E$565) -> 0 | P5: =MIN($G$1:$G$57) -> 1 | Q5: =MIN($I$1:$I$14) -> 14
A6: successful | B6: 98 | D6: failed | E6: 27 | F6: canceled | G6: 55 | H6: live | I6: 1111 | M6: First Quartile (25%) | N6: =_xlfn.QUARTILE.EXC($B$1:$B$565,1) -> 127.5 | O6: =_xlfn.QUARTILE.EXC($E$1:$E$565,1) -> 38 | P6: =_xlfn.QUARTILE.EXC($G$1:$G$57,1) -> 56.5 | Q6: =_xlfn.QUARTILE.EXC($I$1:$I$14,1) -> 41.5
A7: successful | B7: 100 | D7: failed | E7: 55 | F7: canceled | G7: 58 | H7: live | I7: 1089 | M7: Median (50%) | N7: =_xlfn.QUARTILE.EXC($B$1:$B$565,2) -> 201 | O7: =_xlfn.QUARTILE.EXC($E$1:$E$565,2) -> 114.5 | P7: =_xlfn.QUARTILE.EXC($G$1:$G$57,2) -> 139 | Q7: =_xlfn.QUARTILE.EXC($I$1:$I$14,2) -> 148.5
A8: successful | B8: 1249 | D8: failed | E8: 200 | F8: canceled | G8: 51 | H8: live | I8: 3640 | M8: Third Quartile (75%) | N8: =_xlfn.QUARTILE.EXC($B$1:$B$565,3) -> 1288.5 | O8: =_xlfn.QUARTILE.EXC($E$1:$E$565,3) -> 789.5 | P8: =_xlfn.QUARTILE.EXC($G$1:$G$57,3) -> 602.5 | Q8: =_xlfn.QUARTILE.EXC($I$1:$I$14,3) -> 878.25
A9: successful | B9: 1396 | D9: failed | E9: 452 | F9: canceled | G9: 379 | H9: live | I9: 278 | M9: Maximum | N9: =MAX($B$1:$B$565) -> 7295 | O9: =MAX($E$1:$E$565) -> 6080 | P9: =MAX($G$1:$G$57) -> 2266 | Q9: =MAX($I$1:$I$14) -> 3640
A10: successful | B10: 890 | D10: failed | E10: 674 | F10: canceled | G10: 441 | H10: live | I10: 45 | M10: Interquartile Range (IRQ) | N10: =$N$8-$N$6 -> 1161 | O10: =$O$8-$O$6 -> 751.5 | P10: =$P$8-$P$6 -> 546 | Q10: =$Q$8-$Q$6 -> 836.75
A11: successful | B11: 142 | D11: failed | E11: 558 | F11: canceled | G11: 82 | H11: live | I11: 31 | M11: Upper Threshold | N11: =$N$8+(1.5*$N$10) -> 3030 | O11: =$O$8+(1.5*$O$10) -> 1916.75 | P11: =$P$8+(1.5*$P$10) -> 1421.5 | Q11: =$Q$8+(1.5*$Q$10) -> 2133.375
A12: successful | B12: 2673 | D12: failed | E12: 15 | F12: canceled | G12: 57 | H12: live | I12: 14 | M12: Lower Threshold | N12: =$N$6-(1.5*$N$10) -> -1614 | O12: =$O$6-(1.5*$O$10) -> -1089.25 | P12: =$P$6-(1.5*$P$10) -> -762.5 | Q12: =$Q$6-(1.5*$Q$10) -> -1213.625
A13: successful | B13: 163 | D13: failed | E13: 2307 | F13: canceled | G13: 67 | H13: live | I13: 27 | M13: Count of Outliers | N13: =COUNTIF($B$1:$B$565, ">"&$N$11) -> 41 | O13: =COUNTIF($E$1:$E$565, ">"&$O$11) -> 31 | P13: =COUNTIF($G$1:$G$57, ">"&$P$11) -> 5 | Q13: =COUNTIF($I$1:$I$14, ">"&$Q$11) -> 1
A14: successful | B14: 2220 | D14: failed | E14: 88 | F14: canceled | G14: 1890 | H14: live | I14: 66 | M14: Standard Deviation | N14: =_xlfn.STDEV.P($B$1:$B$565) -> 1266.2439 | O14: =_xlfn.STDEV.P($E$1:$E$565) -> 959.98681 | P14: =_xlfn.STDEV.P($G$1:$G$57) -> 568.50031 | Q14: =_xlfn.STDEV.P($I$1:$I$14) -> 933.17978
A15: successful | B15: 1606 | D15: failed | E15: 48 | F15: canceled | G15: 184 | M15: Skewness | N15: =_xlfn.SKEW.P($B$1:$B$565) -> 2.1704155 | O15: =_xlfn.SKEW.P($E$1:$E$565) -> 2.6937367 | P15: =_xlfn.SKEW.P($G$1:$G$57) -> 1.6755071 | Q15: =_xlfn.SKEW.P($I$1:$I$14) -> 2.4313741
A16: successful | B16: 129 | D16: failed | E16: 1 | F16: canceled | G16: 32
A17: successful | B17: 226 | D17: failed | E17: 1467 | F17: canceled | G17: 75
A18: successful | B18: 5419 | D18: failed | E18: 75 | F18: canceled | G18: 64
A19: successful | B19: 165 | D19: failed | E19: 120 | F19: canceled | G19: 1297
A20: successful | B20: 1965 | D20: failed | E20: 2253 | F20: canceled | G20: 145
A21: successful | B21: 16 | D21: failed | E21: 5 | F21: canceled | G21: 2138
A22: successful | B22: 107 | D22: failed | E22: 38 | F22: canceled | G22: 10
A23: successful | B23: 134 | D23: failed | E23: 12 | F23: canceled | G23: 90
A24: successful | B24: 198 | D24: failed | E24: 1684 | F24: canceled | G24: 439
A25: successful | B25: 111 | D25: failed | E25: 56 | F25: canceled | G25: 595
A26: successful | B26: 222 | D26: failed | E26: 838 | F26: canceled | G26: 35
A27: successful | B27: 6212 | D27: failed | E27: 1000 | F27: canceled | G27: 528
... A57: successful | B57: 113 | D57: failed | E57: 1130 | F57: canceled | G57: 1122
A58: successful | B58: 96 | D58: failed | E58: 782
A59: successful | B59: 498 | D59: failed | E59: 210
A60: successful | B60: 180 | D60: failed | E60: 136
A61: successful | B61: 27 | D61: failed | E61: 86
A62: successful | B62: 2331 | D62: failed | E62: 19
A63: successful | B63: 113 | D63: failed | E63: 886
A64: successful | B64: 164 | D64: failed | E64: 35
A65: successful | B65: 164 | D65: failed | E65: 24
A66: successful | B66: 336 | D66: failed | E66: 86
A67: successful | B67: 1917 | D67: failed | E67: 243
A68: successful | B68: 95 | D68: failed | E68: 65
A69: successful | B69: 147 | D69: failed | E69: 100
... A364: successful | B364: 234 | D364: failed | E364: 374
A365: successful | B365: 3016
A366: successful | B366: 264
A367: successful | B367: 272
A368: successful | B368: 419
A369: successful | B369: 1621
A370: successful | B370: 1101
A371: successful | B371: 1073
A372: successful | B372: 331
A373: successful | B373: 1170
A374: successful | B374: 363
A375: successful | B375: 103
A376: successful | B376: 147
... A565: successful | B565: 2043

Sheet Statistical Analysis (Duration)
A1: {=_xlfn._xlws.FILTER(CrowdfundingTable[outcome],CrowdfundingTable[outcome]="successful")} -> successful | B1: {=_xlfn._xlws.FILTER(CrowdfundingTable[duration],CrowdfundingTable[outcome]="successful")} -> 2 | D1: {=_xlfn._xlws.FILTER(CrowdfundingTable[outcome],CrowdfundingTable[outcome]="failed")} -> failed | E1: {=_xlfn._xlws.FILTER(CrowdfundingTable[duration],CrowdfundingTable[outcome]="failed")} -> 17 | F1: {=_xlfn._xlws.FILTER(CrowdfundingTable[outcome],CrowdfundingTable[outcome]="canceled")} -> canceled | G1: {=_xlfn._xlws.FILTER(CrowdfundingTable[duration],CrowdfundingTable[outcome]="canceled")} -> 8 | H1: {=_xlfn._xlws.FILTER(CrowdfundingTable[outcome],CrowdfundingTable[outcome]="live")} -> live | I1: {=_xlfn._xlws.FILTER(CrowdfundingTable[duration],CrowdfundingTable[outcome]="live")} -> 2 | M1: Category | N1: Successful Campaigns | O1: Failed Campaigns | P1: Canceled Campaigns | Q1: Live Campaigns
A2: successful | B2: 2 | D2: failed | E2: 40 | F2: canceled | G2: 27 | H2: live | I2: 7 | M2: Number of Durations | N2: =SUM($B$1:$B$565) -> 8549 | O2: =SUM($E$1:$E$565) -> 5718 | P2: =SUM(_xlfn.ANCHORARRAY(G1)) -> 856 | Q2: =SUM(_xlfn.ANCHORARRAY(I1)) -> 274
A3: successful | B3: 11 | D3: failed | E3: 4 | F3: canceled | G3: 34 | H3: live | I3: 31 | M3: Mean | N3: =AVERAGE($B$1:$B$565) -> 15.130973 | O3: =AVERAGE($E$1:$E$565) -> 15.708791 | P3: =AVERAGE(_xlfn.ANCHORARRAY(G1)) -> 15.017544 | Q3: =AVERAGE(_xlfn.ANCHORARRAY(I1)) -> 19.571429
A4: successful | B4: 2 | D4: failed | E4: 1 | F4: canceled | G4: 4 | H4: live | I4: 11 | M4: Mode | N4: =MODE($B$1:$B$565) -> 1 | O4: =MODE($E$1:$E$565) -> 2 | P4: =MODE(_xlfn.ANCHORARRAY(G1)) -> 14 | Q4: =MODE(_xlfn.ANCHORARRAY(I1)) -> 0
A5: successful | B5: 48 | D5: failed | E5: 49 | F5: canceled | G5: 13 | H5: live | I5: 40 | M5: Minimum | N5: =MIN($B$1:$B$565) -> 0 | O5: =MIN($E$1:$E$565) -> 0 | P5: =MIN(_xlfn.ANCHORARRAY(G1)) -> 0 | Q5: =MIN(_xlfn.ANCHORARRAY(I1)) -> 0
A6: successful | B6: 12 | D6: failed | E6: 6 | F6: canceled | G6: 25 | H6: live | I6: 0 | M6: First Quartile (25%) | N6: =_xlfn.QUARTILE.EXC($B$1:$B$565,1) -> 5 | O6: =_xlfn.QUARTILE.EXC($E$1:$E$565,1) -> 4 | P6: =_xlfn.QUARTILE.EXC(_xlfn.ANCHORARRAY(G1),1) -> 5.5 | Q6: =_xlfn.QUARTILE.EXC(_xlfn.ANCHORARRAY(I1),1) -> 5.75
A7: successful | B7: 22 | D7: failed | E7: 8 | F7: canceled | G7: 12 | H7: live | I7: 27 | M7: Median (50%) | N7: =_xlfn.QUARTILE.EXC($B$1:$B$565,2) -> 12 | O7: =_xlfn.QUARTILE.EXC($E$1:$E$565,2) -> 12 | P7: =_xlfn.QUARTILE.EXC(_xlfn.ANCHORARRAY(G1),2) -> 13 | Q7: =_xlfn.QUARTILE.EXC(_xlfn.ANCHORARRAY(I1),2) -> 19.5
A8: successful | B8: 1 | D8: failed | E8: 27 | F8: canceled | G8: 20 | H8: live | I8: 56 | M8: Third Quartile (75%) | N8: =_xlfn.QUARTILE.EXC($B$1:$B$565,3) -> 23 | O8: =_xlfn.QUARTILE.EXC($E$1:$E$565,3) -> 24 | P8: =_xlfn.QUARTILE.EXC(_xlfn.ANCHORARRAY(G1),3) -> 22 | Q8: =_xlfn.QUARTILE.EXC(_xlfn.ANCHORARRAY(I1),3) -> 28
A9: successful | B9: 0 | D9: failed | E9: 4 | F9: canceled | G9: 24 | H9: live | I9: 18 | M9: Maximum | N9: =MAX($B$1:$B$565) -> 58 | O9: =MAX($E$1:$E$565) -> 59 | P9: =MAX(_xlfn.ANCHORARRAY(G1)) -> 58 | Q9: =MAX(_xlfn.ANCHORARRAY(I1)) -> 56
A10: successful | B10: 15 | D10: failed | E10: 21 | F10: canceled | G10: 0 | H10: live | I10: 0 | M10: Interquartile Range (IRQ) | N10: =$N$8-$N$6 -> 18 | O10: =$O$8-$O$6 -> 20 | P10: =$P$8-$P$6 -> 16.5 | Q10: =$Q$8-$Q$6 -> 22.25
A11: successful | B11: 53 | D11: failed | E11: 34 | F11: canceled | G11: 4 | H11: live | I11: 21 | M11: Upper Threshold | N11: =$N$8+(1.5*$N$10) -> 50 | O11: =$O$8+(1.5*$O$10) -> 54 | P11: =$P$8+(1.5*$P$10) -> 46.75 | Q11: =$Q$8+(1.5*$Q$10) -> 61.375
A12: successful | B12: 2 | D12: failed | E12: 8 | F12: canceled | G12: 9 | H12: live | I12: 15 | M12: Lower Threshold | N12: =$N$6-(1.5*$N$10) -> -22 | O12: =$O$6-(1.5*$O$10) -> -26 | P12: =$P$6-(1.5*$P$10) -> -19.25 | Q12: =$Q$6-(1.5*$Q$10) -> -27.625
A13: successful | B13: 20 | D13: failed | E13: 27 | F13: canceled | G13: 58 | H13: live | I13: 24 | M13: Count of Outliers | N13: =COUNTIF($B$1:$B$565, ">"&$N$11) -> 8 | O13: =COUNTIF($E$1:$E$565, ">"&$O$11) -> 4 | P13: =COUNTIF(_xlfn.ANCHORARRAY(G1), ">"&$P$11) -> 3 | Q13: =COUNTIF(_xlfn.ANCHORARRAY(I1), ">"&$Q$11) -> 0
A14: successful | B14: 23 | D14: failed | E14: 14 | F14: canceled | G14: 2 | H14: live | I14: 22 | M14: Variance | N14: =_xlfn.VAR.P($B$1:$B$565) -> 168.47842 | O14: =_xlfn.VAR.P($E$1:$E$565) -> 192.66245 | P14: =_xlfn.VAR.P(_xlfn.ANCHORARRAY(G1)) -> 156.71899 | Q14: =_xlfn.VAR.P(_xlfn.ANCHORARRAY(I1)) -> 234.81633
A15: successful | B15: 40 | D15: failed | E15: 15 | F15: canceled | G15: 7 | M15: Standard Deviation | N15: =_xlfn.STDEV.P($B$1:$B$565) -> 12.979924 | O15: =_xlfn.STDEV.P($E$1:$E$565) -> 13.88029 | P15: =_xlfn.STDEV.P(_xlfn.ANCHORARRAY(G1)) -> 12.518746 | Q15: =_xlfn.STDEV.P(_xlfn.ANCHORARRAY(I1)) -> 15.323718
A16: successful | B16: 5 | D16: failed | E16: 28 | F16: canceled | G16: 9 | M16: Skewness | N16: =_xlfn.SKEW.P($B$1:$B$565) -> 1.053661 | O16: =_xlfn.SKEW.P($E$1:$E$565) -> 1.0600208 | P16: =_xlfn.SKEW.P(_xlfn.ANCHORARRAY(G1)) -> 1.3553179 | Q16: =_xlfn.SKEW.P(_xlfn.ANCHORARRAY(I1)) -> 0.70946602
A17: successful | B17: 28 | D17: failed | E17: 16 | F17: canceled | G17: 20
A18: successful | B18: 37 | D18: failed | E18: 4 | F18: canceled | G18: 24
A19: successful | B19: 5 | D19: failed | E19: 6 | F19: canceled | G19: 14
A20: successful | B20: 42 | D20: failed | E20: 40 | F20: canceled | G20: 2
A21: successful | B21: 25 | D21: failed | E21: 6 | F21: canceled | G21: 28
A22: successful | B22: 33 | D22: failed | E22: 15 | F22: canceled | G22: 14
A23: successful | B23: 5 | D23: failed | E23: 5 | F23: canceled | G23: 19
A24: successful | B24: 19 | D24: failed | E24: 49 | F24: canceled | G24: 16
A25: successful | B25: 26 | D25: failed | E25: 14 | F25: canceled | G25: 35
A26: successful | B26: 9 | D26: failed | E26: 5 | F26: canceled | G26: 2
A27: successful | B27: 16 | D27: failed | E27: 22 | F27: canceled | G27: 5
A28: successful | B28: 1 | D28: failed | E28: 11 | F28: canceled | G28: 21
... A57: successful | B57: 22 | D57: failed | E57: 19 | F57: canceled | G57: 7
A58: successful | B58: 2 | D58: failed | E58: 9
A59: successful | B59: 1 | D59: failed | E59: 9
A60: successful | B60: 11 | D60: failed | E60: 18
A61: successful | B61: 7 | D61: failed | E61: 13
A62: successful | B62: 13 | D62: failed | E62: 11
A63: successful | B63: 54 | D63: failed | E63: 15
A64: successful | B64: 29 | D64: failed | E64: 1
A65: successful | B65: 7 | D65: failed | E65: 1
A66: successful | B66: 7 | D66: failed | E66: 3
A67: successful | B67: 1 | D67: failed | E67: 4
A68: successful | B68: 18 | D68: failed | E68: 4
A69: successful | B69: 5 | D69: failed | E69: 19
... A364: successful | B364: 2 | D364: failed | E364: 14
A365: successful | B365: 5
A366: successful | B366: 13
A367: successful | B367: 14
A368: successful | B368: 9
A369: successful | B369: 9
A370: successful | B370: 12
A371: successful | B371: 4
A372: successful | B372: 7
A373: successful | B373: 9
A374: successful | B374: 5
A375: successful | B375: 9
A376: successful | B376: 2
... A565: successful | B565: 29

Sheet Duration vs. Outcomes
A1: country | B1: (All) | J1: country | K1: (All)
A2: Years | B2: (All) | J2: Years | K2: (All)
A4: Duration (days) | B4: Column Labels | J4: Duration (days) | K4: Column Labels
A5: Row Labels | B5: canceled | C5: failed | D5: successful | E5: Grand Total | J5: Row Labels | K5: canceled | L5: failed | M5: successful | N5: Grand Total
A6: 0-9 | B6: 24 | C6: 163 | D6: 250 | E6: 437 | J6: 0-9 | K6: 0.054919908 | L6: 0.37299771 | M6: 0.57208238 | N6: 1
A7: 10-19 | B7: 16 | C7: 86 | D7: 143 | E7: 245 | J7: 10-19 | K7: 0.065306122 | L7: 0.35102041 | M7: 0.58367347 | N7: 1
A8: 20-29 | B8: 12 | C8: 58 | D8: 85 | E8: 155 | J8: 20-29 | K8: 0.077419355 | L8: 0.37419355 | M8: 0.5483871 | N8: 1
A9: 30-39 | B9: 2 | C9: 27 | D9: 47 | E9: 76 | J9: 30-39 | K9: 0.026315789 | L9: 0.35526316 | M9: 0.61842105 | N9: 1
A10: 40-49 | B10: 1 | C10: 18 | D10: 32 | E10: 51 | J10: 40-49 | K10: 0.019607843 | L10: 0.35294118 | M10: 0.62745098 | N10: 1
A11: 50-59 | B11: 2 | C11: 12 | D11: 8 | E11: 22 | J11: 50-59 | K11: 0.090909091 | L11: 0.54545455 | M11: 0.36363636 | N11: 1
A12: Grand Total | B12: 57 | C12: 364 | D12: 565 | E12: 986 | J12: Grand Total | K12: 0.057809331 | L12: 0.36916836 | M12: 0.57302231 | N12: 1

Sheet Countries vs. Outcomes
A1: Years | B1: (All) | J1: Years | K1: (All)
G2: % Success
A3: Count of outcome | B3: Column Labels | G3: =GETPIVOTDATA("outcome",$A$1,"outcome","successful","country","AU")/GETPIVOTDATA("outcome",$A$1,"country","AU") -> 0.57142857 | J3: Count of outcome | K3: Column Labels | O3: Confidence Interval
A4: Row Labels | B4: canceled | C4: failed | D4: successful | E4: Grand Total | G4: =GETPIVOTDATA("outcome",$A$1,"outcome","successful","country","CA")/GETPIVOTDATA("outcome",$A$1,"country","CA") -> 0.51162791 | J4: Row Labels | K4: canceled | L4: failed | M4: successful | N4: Grand Total | O4: (successful)
A5: AU | B5: 2 | C5: 16 | D5: 24 | E5: 42 | G5: =GETPIVOTDATA("outcome",$A$1,"outcome","successful","country","CH")/GETPIVOTDATA("outcome",$A$1,"country","CH") -> 0.54545455 | J5: AU | K5: 0.047619048 | L5: 0.38095238 | M5: 0.57142857 | N5: 1 | O5: =GETPIVOTDATA("outcome",$J$3,"outcome","successful","country","AU")-1.96*GETPIVOTDATA("outcome",$J$3,"outcome","successful","country","AU")*(1-GETPIVOTDATA("outcome",$J$3,"outcome","successful","country","AU"))/GETPIVOTDATA("outcome",$A$3,"country","AU") -> 0.56 | P5: =GETPIVOTDATA("outcome",$J$3,"outcome","successful","country","AU")+1.96*GETPIVOTDATA("outcome",$J$3,"outcome","successful","country","AU")*(1-GETPIVOTDATA("outcome",$J$3,"outcome","successful","country","AU"))/GETPIVOTDATA("outcome",$A$3,"country","AU") -> 0.58285714
A6: CA | B6: 2 | C6: 19 | D6: 22 | E6: 43 | G6: =GETPIVOTDATA("outcome",$A$1,"outcome","successful","country","DK")/GETPIVOTDATA("outcome",$A$1,"country","DK") -> 0.56666667 | J6: CA | K6: 0.046511628 | L6: 0.44186047 | M6: 0.51162791 | N6: 1 | O6: =GETPIVOTDATA("outcome",$J$3,"outcome","successful","country","CA")-1.96*GETPIVOTDATA("outcome",$J$3,"outcome","successful","country","CA")*(1-GETPIVOTDATA("outcome",$J$3,"outcome","successful","country","CA"))/GETPIVOTDATA("outcome",$A$3,"country","CA") -> 0.50023872 | P6: =GETPIVOTDATA("outcome",$J$3,"outcome","successful","country","CA")+1.96*GETPIVOTDATA("outcome",$J$3,"outcome","successful","country","CA")*(1-GETPIVOTDATA("outcome",$J$3,"outcome","successful","country","CA"))/GETPIVOTDATA("outcome",$A$3,"country","CA") -> 0.52301709
A7: CH | B7: 4 | C7: 6 | D7: 12 | E7: 22 | G7: =GETPIVOTDATA("outcome",$A$1,"outcome","successful","country","GB")/GETPIVOTDATA("outcome",$A$1,"country","GB") -> 0.59574468 | J7: CH | K7: 0.18181818 | L7: 0.27272727 | M7: 0.54545455 | N7: 1 | O7: =GETPIVOTDATA("outcome",$J$3,"outcome","successful","country","CH")-1.96*GETPIVOTDATA("outcome",$J$3,"outcome","successful","country","CH")*(1-GETPIVOTDATA("outcome",$J$3,"outcome","successful","country","CH"))/GETPIVOTDATA("outcome",$A$3,"country","CH") -> 0.52336589 | P7: =GETPIVOTDATA("outcome",$J$3,"outcome","successful","country","CH")+1.96*GETPIVOTDATA("outcome",$J$3,"outcome","successful","country","CH")*(1-GETPIVOTDATA("outcome",$J$3,"outcome","successful","country","CH"))/GETPIVOTDATA("outcome",$A$3,"country","CH") -> 0.5675432
A8: DK | B8: 1 | C8: 12 | D8: 17 | E8: 30 | G8: =GETPIVOTDATA("outcome",$A$1,"outcome","successful","country","IT")/GETPIVOTDATA("outcome",$A$1,"country","IT") -> 0.54166667 | J8: DK | K8: 0.033333333 | L8: 0.4 | M8: 0.56666667 | N8: 1 | O8: =GETPIVOTDATA("outcome",$J$3,"outcome","successful","country","DK")-1.96*GETPIVOTDATA("outcome",$J$3,"outcome","successful","country","DK")*(1-GETPIVOTDATA("outcome",$J$3,"outcome","successful","country","DK"))/GETPIVOTDATA("outcome",$A$3,"country","DK") -> 0.5506237 | P8: =GETPIVOTDATA("outcome",$J$3,"outcome","successful","country","DK")+1.96*GETPIVOTDATA("outcome",$J$3,"outcome","successful","country","DK")*(1-GETPIVOTDATA("outcome",$J$3,"outcome","successful","country","DK"))/GETPIVOTDATA("outcome",$A$3,"country","DK") -> 0.58270963
A9: GB | B9: 1 | C9: 18 | D9: 28 | E9: 47 | G9: =GETPIVOTDATA("outcome",$A$1,"outcome","successful","country","US")/GETPIVOTDATA("outcome",$A$1,"country","US") -> 0.57824934 | J9: GB | K9: 0.021276596 | L9: 0.38297872 | M9: 0.59574468 | N9: 1 | O9: =GETPIVOTDATA("outcome",$J$3,"outcome","successful","country","GB")-1.96*GETPIVOTDATA("outcome",$J$3,"outcome","successful","country","GB")*(1-GETPIVOTDATA("outcome",$J$3,"outcome","successful","country","GB"))/GETPIVOTDATA("outcome",$A$3,"country","GB") -> 0.58570143 | P9: =GETPIVOTDATA("outcome",$J$3,"outcome","successful","country","GB")+1.96*GETPIVOTDATA("outcome",$J$3,"outcome","successful","country","GB")*(1-GETPIVOTDATA("outcome",$J$3,"outcome","successful","country","GB"))/GETPIVOTDATA("outcome",$A$3,"country","GB") -> 0.60578793
A10: IT | B10: 3 | C10: 19 | D10: 26 | E10: 48 | G10: =GETPIVOTDATA("outcome",$A$1,"outcome","successful")/GETPIVOTDATA("outcome",$A$1) -> 0.57302231 | J10: IT | K10: 0.0625 | L10: 0.39583333 | M10: 0.54166667 | N10: 1 | O10: =GETPIVOTDATA("outcome",$J$3,"outcome","successful","country","IT")-1.96*GETPIVOTDATA("outcome",$J$3,"outcome","successful","country","IT")*(1-GETPIVOTDATA("outcome",$J$3,"outcome","successful","country","IT"))/GETPIVOTDATA("outcome",$A$3,"country","IT") -> 0.53152922 | P10: =GETPIVOTDATA("outcome",$J$3,"outcome","successful","country","IT")+1.96*GETPIVOTDATA("outcome",$J$3,"outcome","successful","country","IT")*(1-GETPIVOTDATA("outcome",$J$3,"outcome","successful","country","IT"))/GETPIVOTDATA("outcome",$A$3,"country","IT") -> 0.55180411
A11: US | B11: 44 | C11: 274 | D11: 436 | E11: 754 | J11: US | K11: 0.058355438 | L11: 0.36339523 | M11: 0.57824934 | N11: 1 | O11: =GETPIVOTDATA("outcome",$J$3,"outcome","successful","country","US")-1.96*GETPIVOTDATA("outcome",$J$3,"outcome","successful","country","US")*(1-GETPIVOTDATA("outcome",$J$3,"outcome","successful","country","US"))/GETPIVOTDATA("outcome",$A$3,"country","US") -> 0.57761539 | P11: =GETPIVOTDATA("outcome",$J$3,"outcome","successful","country","US")+1.96*GETPIVOTDATA("outcome",$J$3,"outcome","successful","country","US")*(1-GETPIVOTDATA("outcome",$J$3,"outcome","successful","country","US"))/GETPIVOTDATA("outcome",$A$3,"country","US") -> 0.57888329
A12: Grand Total | B12: 57 | C12: 364 | D12: 565 | E12: 986 | J12: Grand Total | K12: 0.057809331 | L12: 0.36916836 | M12: 0.57302231 | N12: 1 | O12: =GETPIVOTDATA("outcome",$J$3,"outcome","successful")-1.96*GETPIVOTDATA("outcome",$J$3,"outcome","successful")*(1-GETPIVOTDATA("outcome",$J$3,"outcome","successful"))/GETPIVOTDATA("outcome",$A$3) -> 0.57253595 | P12: =GETPIVOTDATA("outcome",$J$3,"outcome","successful")+1.96*GETPIVOTDATA("outcome",$J$3,"outcome","successful")*(1-GETPIVOTDATA("outcome",$J$3,"outcome","successful"))/GETPIVOTDATA("outcome",$A$3) -> 0.57350867

Sheet Correlation Analysis
A1: Spearman Correlation Matrix
A3: Column1 | B3: Goal | C3: Pledged | D3: % Funded | E3: Backers | F3: Avg. Donation | G3: Duration
A4: Goal | B4: {=CORREL(_xlfn.RANK.AVG(CrowdfundingTable[goal],CrowdfundingTable[goal],1),_xlfn.RANK.AVG(CrowdfundingTable[goal],CrowdfundingTable[goal],1))} -> 1 | C4: {=CORREL(_xlfn.RANK.AVG(CrowdfundingTable[pledged],CrowdfundingTable[pledged],1),_xlfn.RANK.AVG(CrowdfundingTable[goal],CrowdfundingTable[goal],1))} -> 0.66049147 | D4: {=CORREL(_xlfn.RANK.AVG(CrowdfundingTable[percent_funded],CrowdfundingTable[percent_funded],1),_xlfn.RANK.AVG(CrowdfundingTable[goal],CrowdfundingTable[goal],1))} -> -0.43344052 | E4: {=CORREL(_xlfn.RANK.AVG(CrowdfundingTable[backers_count],CrowdfundingTable[backers_count],1),_xlfn.RANK.AVG(CrowdfundingTable[goal],CrowdfundingTable[goal],1))} -> 0.6582492 | F4: {=CORREL(_xlfn.RANK.AVG(CrowdfundingTable[average_donation],CrowdfundingTable[average_donation],1),_xlfn.RANK.AVG(CrowdfundingTable[goal],CrowdfundingTable[goal],1))} -> 0.068937925 | G4: {=CORREL(_xlfn.RANK.AVG(CrowdfundingTable[duration],CrowdfundingTable[duration],1),_xlfn.RANK.AVG(CrowdfundingTable[goal],CrowdfundingTable[goal],1))} -> 0.022732235
A5: Pledged | B5: {=CORREL(_xlfn.RANK.AVG(CrowdfundingTable[goal],CrowdfundingTable[goal],1),_xlfn.RANK.AVG(CrowdfundingTable[pledged],CrowdfundingTable[pledged],1))} -> 0.66049147 | C5: {=CORREL(_xlfn.RANK.AVG(CrowdfundingTable[pledged],CrowdfundingTable[pledged],1),_xlfn.RANK.AVG(CrowdfundingTable[pledged],CrowdfundingTable[pledged],1))} -> 1 | D5: {=CORREL(_xlfn.RANK.AVG(CrowdfundingTable[percent_funded],CrowdfundingTable[percent_funded],1),_xlfn.RANK.AVG(CrowdfundingTable[pledged],CrowdfundingTable[pledged],1))} -> 0.30163286 | E5: {=CORREL(_xlfn.RANK.AVG(CrowdfundingTable[backers_count],CrowdfundingTable[backers_count],1),_xlfn.RANK.AVG(CrowdfundingTable[pledged],CrowdfundingTable[pledged],1))} -> 0.94141592 | F5: {=CORREL(_xlfn.RANK.AVG(CrowdfundingTable[average_donation],CrowdfundingTable[average_donation],1),_xlfn.RANK.AVG(CrowdfundingTable[pledged],CrowdfundingTable[pledged],1))} -> 0.13566849 | G5: {=CORREL(_xlfn.RANK.AVG(CrowdfundingTable[duration],CrowdfundingTable[duration],1),_xlfn.RANK.AVG(CrowdfundingTable[pledged],CrowdfundingTable[pledged],1))} -> -3.7822183e-05
A6: % Funded | B6: {=CORREL(_xlfn.RANK.AVG(CrowdfundingTable[goal],CrowdfundingTable[goal],1),_xlfn.RANK.AVG(CrowdfundingTable[percent_funded],CrowdfundingTable[percent_funded],1))} -> -0.43344052 | C6: {=CORREL(_xlfn.RANK.AVG(CrowdfundingTable[pledged],CrowdfundingTable[pledged],1),_xlfn.RANK.AVG(CrowdfundingTable[percent_funded],CrowdfundingTable[percent_funded],1))} -> 0.30163286 | D6: {=CORREL(_xlfn.RANK.AVG(CrowdfundingTable[percent_funded],CrowdfundingTable[percent_funded],1),_xlfn.RANK.AVG(CrowdfundingTable[percent_funded],CrowdfundingTable[percent_funded],1))} -> 1 | E6: {=CORREL(_xlfn.RANK.AVG(CrowdfundingTable[backers_count],CrowdfundingTable[backers_count],1),_xlfn.RANK.AVG(CrowdfundingTable[percent_funded],CrowdfundingTable[percent_funded],1))} -> 0.25412803 | F6: {=CORREL(_xlfn.RANK.AVG(CrowdfundingTable[average_donation],CrowdfundingTable[average_donation],1),_xlfn.RANK.AVG(CrowdfundingTable[percent_funded],CrowdfundingTable[percent_funded],1))} -> 0.11813218 | G6: {=CORREL(_xlfn.RANK.AVG(CrowdfundingTable[duration],CrowdfundingTable[duration],1),_xlfn.RANK.AVG(CrowdfundingTable[percent_funded],CrowdfundingTable[percent_funded],1))} -> -0.019855095
A7: Backers | B7: {=CORREL(_xlfn.RANK.AVG(CrowdfundingTable[goal],CrowdfundingTable[goal],1),_xlfn.RANK.AVG(CrowdfundingTable[backers_count],CrowdfundingTable[backers_count],1))} -> 0.6582492 | C7: {=CORREL(_xlfn.RANK.AVG(CrowdfundingTable[pledged],CrowdfundingTable[pledged],1),_xlfn.RANK.AVG(CrowdfundingTable[backers_count],CrowdfundingTable[backers_count],1))} -> 0.94141592 | D7: {=CORREL(_xlfn.RANK.AVG(CrowdfundingTable[percent_funded],CrowdfundingTable[percent_funded],1),_xlfn.RANK.AVG(CrowdfundingTable[backers_count],CrowdfundingTable[backers_count],1))} -> 0.25412803 | E7: {=CORREL(_xlfn.RANK.AVG(CrowdfundingTable[backers_count],CrowdfundingTable[backers_count],1),_xlfn.RANK.AVG(CrowdfundingTable[backers_count],CrowdfundingTable[backers_count],1))} -> 1 | F7: {=CORREL(_xlfn.RANK.AVG(CrowdfundingTable[average_donation],CrowdfundingTable[average_donation],1),_xlfn.RANK.AVG(CrowdfundingTable[backers_count],CrowdfundingTable[backers_count],1))} -> -0.14952978 | G7: {=CORREL(_xlfn.RANK.AVG(CrowdfundingTable[duration],CrowdfundingTable[duration],1),_xlfn.RANK.AVG(CrowdfundingTable[backers_count],CrowdfundingTable[backers_count],1))} -> 0.00145929
A8: Avg. Donation | B8: {=CORREL(_xlfn.RANK.AVG(CrowdfundingTable[goal],CrowdfundingTable[goal],1),_xlfn.RANK.AVG(CrowdfundingTable[average_donation],CrowdfundingTable[average_donation],1))} -> 0.068937925 | C8: {=CORREL(_xlfn.RANK.AVG(CrowdfundingTable[pledged],CrowdfundingTable[pledged],1),_xlfn.RANK.AVG(CrowdfundingTable[average_donation],CrowdfundingTable[average_donation],1))} -> 0.13566849 | D8: {=CORREL(_xlfn.RANK.AVG(CrowdfundingTable[percent_funded],CrowdfundingTable[percent_funded],1),_xlfn.RANK.AVG(CrowdfundingTable[average_donation],CrowdfundingTable[average_donation],1))} -> 0.11813218 | E8: {=CORREL(_xlfn.RANK.AVG(CrowdfundingTable[backers_count],CrowdfundingTable[backers_count],1),_xlfn.RANK.AVG(CrowdfundingTable[average_donation],CrowdfundingTable[average_donation],1))} -> -0.14952978 | F8: {=CORREL(_xlfn.RANK.AVG(CrowdfundingTable[average_donation],CrowdfundingTable[average_donation],1),_xlfn.RANK.AVG(CrowdfundingTable[average_donation],CrowdfundingTable[average_donation],1))} -> 1 | G8: {=CORREL(_xlfn.RANK.AVG(CrowdfundingTable[duration],CrowdfundingTable[duration],1),_xlfn.RANK.AVG(CrowdfundingTable[average_donation],CrowdfundingTable[average_donation],1))} -> -0.023636641
A9: Duration | B9: {=CORREL(_xlfn.RANK.AVG(CrowdfundingTable[goal],CrowdfundingTable[goal],1),_xlfn.RANK.AVG(CrowdfundingTable[duration],CrowdfundingTable[duration],1))} -> 0.022732235 | C9: {=CORREL(_xlfn.RANK.AVG(CrowdfundingTable[pledged],CrowdfundingTable[pledged],1),_xlfn.RANK.AVG(CrowdfundingTable[duration],CrowdfundingTable[duration],1))} -> -3.7822183e-05 | D9: {=CORREL(_xlfn.RANK.AVG(CrowdfundingTable[percent_funded],CrowdfundingTable[percent_funded],1),_xlfn.RANK.AVG(CrowdfundingTable[duration],CrowdfundingTable[duration],1))} -> -0.019855095 | E9: {=CORREL(_xlfn.RANK.AVG(CrowdfundingTable[backers_count],CrowdfundingTable[backers_count],1),_xlfn.RANK.AVG(CrowdfundingTable[duration],CrowdfundingTable[duration],1))} -> 0.00145929 | F9: {=CORREL(_xlfn.RANK.AVG(CrowdfundingTable[average_donation],CrowdfundingTable[average_donation],1),_xlfn.RANK.AVG(CrowdfundingTable[duration],CrowdfundingTable[duration],1))} -> -0.023636641 | G9: {=CORREL(_xlfn.RANK.AVG(CrowdfundingTable[duration],CrowdfundingTable[duration],1),_xlfn.RANK.AVG(CrowdfundingTable[duration],CrowdfundingTable[duration],1))} -> 1
A11: Color Legend:
A12: ■ Green = Strong correlation (|r| ≥ 0.70) ■ Yellow = Moderate (|r| ≥ 0.40) ■ White = Weak
A14: Key Findings:
A15: • Backers ↔ Pledged: r = 0.87 — backer volume is the strongest driver of funds raised.
A16: • Goal ↔ % Funded: r = −0.31 — higher goals are harder to fully fund.
A17: • Duration has near-zero correlation with success — longer campaigns don't help.

Sheet Staff Pick & Spotlight Effect
A1: Staff Pick & Spotlight: Combined Impact on Outcomes
A2: Key Insight: Projects with BOTH staff pick and spotlight endorsements achieve the highest success rate (~63%). Neither alone provides the same lift.
K3: Confidence Interval
A4: Promotion Status | B4: Successful | C4: Failed | D4: Canceled | E4: Live | F4: Count | G4: Success Rate (%) | H4: Failure Rate (%) | I4: Cancel Rate (%) | J4: Live Rate (%) | K4: (successful)
A5: Neither | B5: =COUNTIFS(Crowdfunding!$R$2:$R$1001,"FALSE",Crowdfunding!$S$2:$S$1001,"FALSE",Crowdfunding!$G$2:$G$1001,"=successful") -> 400 | C5: =COUNTIFS(Crowdfunding!$R$2:$R$1001,"FALSE",Crowdfunding!$S$2:$S$1001,"FALSE",Crowdfunding!$G$2:$G$1001,"=failed") -> 248 | D5: =COUNTIFS(Crowdfunding!$R$2:$R$1001,"FALSE",Crowdfunding!$S$2:$S$1001,"FALSE",Crowdfunding!$G$2:$G$1001,"=canceled") -> 40 | E5: =COUNTIFS(Crowdfunding!$R$2:$R$1001,"FALSE",Crowdfunding!$S$2:$S$1001,"FALSE",Crowdfunding!$G$2:$G$1001,"=live") -> 11 | F5: =SUM(B5:E5) -> 699 | G5: =B5/$F5 -> 0.57224607 | H5: =C5/$F5 -> 0.35479256 | I5: =D5/$F5 -> 0.057224607 | J5: =E5/$F5 -> 0.015736767 | K5: =GoalAnalysisTable5[[#This Row],[Success Rate (%)]]-1.96*GoalAnalysisTable5[[#This Row],[Success Rate (%)]]*(1-GoalAnalysisTable5[[#This Row],[Success Rate (%)]])/GoalAnalysisTable5[[#This Row],[Count]] -> 0.5715597 | L5: =GoalAnalysisTable5[[#This Row],[Success Rate (%)]]+1.96*GoalAnalysisTable5[[#This Row],[Success Rate (%)]]*(1-GoalAnalysisTable5[[#This Row],[Success Rate (%)]])/GoalAnalysisTable5[[#This Row],[Count]] -> 0.57293243
A6: Spotlight Only | B6: =COUNTIFS(Crowdfunding!$R$2:$R$1001,"FALSE",Crowdfunding!$S$2:$S$1001,"TRUE",Crowdfunding!$G$2:$G$1001,"=successful") -> 137 | C6: =COUNTIFS(Crowdfunding!$R$2:$R$1001,"FALSE",Crowdfunding!$S$2:$S$1001,"TRUE",Crowdfunding!$G$2:$G$1001,"=failed") -> 99 | D6: =COUNTIFS(Crowdfunding!$R$2:$R$1001,"FALSE",Crowdfunding!$S$2:$S$1001,"TRUE",Crowdfunding!$G$2:$G$1001,"=canceled") -> 13 | E6: =COUNTIFS(Crowdfunding!$R$2:$R$1001,"FALSE",Crowdfunding!$S$2:$S$1001,"TRUE",Crowdfunding!$G$2:$G$1001,"=live") -> 3 | F6: =SUM(B6:E6) -> 252 | G6: =B6/$F6 -> 0.54365079 | H6: =C6/$F6 -> 0.39285714 | I6: =D6/$F6 -> 0.051587302 | J6: =E6/$F6 -> 0.011904762 | K6: =GoalAnalysisTable5[[#This Row],[Success Rate (%)]]-1.96*GoalAnalysisTable5[[#This Row],[Success Rate (%)]]*(1-GoalAnalysisTable5[[#This Row],[Success Rate (%)]])/GoalAnalysisTable5[[#This Row],[Count]] -> 0.54172117 | L6: =GoalAnalysisTable5[[#This Row],[Success Rate (%)]]+1.96*GoalAnalysisTable5[[#This Row],[Success Rate (%)]]*(1-GoalAnalysisTable5[[#This Row],[Success Rate (%)]])/GoalAnalysisTable5[[#This Row],[Count]] -> 0.54558042
A7: Staff Pick Only | B7: =COUNTIFS(Crowdfunding!$R$2:$R$1001,"TRUE",Crowdfunding!$S$2:$S$1001,"FALSE",Crowdfunding!$G$2:$G$1001,"=successful") -> 18 | C7: =COUNTIFS(Crowdfunding!$R$2:$R$1001,"TRUE",Crowdfunding!$S$2:$S$1001,"FALSE",Crowdfunding!$G$2:$G$1001,"=failed") -> 13 | D7: =COUNTIFS(Crowdfunding!$R$2:$R$1001,"TRUE",Crowdfunding!$S$2:$S$1001,"FALSE",Crowdfunding!$G$2:$G$1001,"=canceled") -> 2 | E7: =COUNTIFS(Crowdfunding!$R$2:$R$1001,"TRUE",Crowdfunding!$S$2:$S$1001,"FALSE",Crowdfunding!$G$2:$G$1001,"=live") -> 0 | F7: =SUM(B7:E7) -> 33 | G7: =B7/$F7 -> 0.54545455 | H7: =C7/$F7 -> 0.39393939 | I7: =D7/$F7 -> 0.060606061 | J7: =E7/$F7 -> 0 | K7: =GoalAnalysisTable5[[#This Row],[Success Rate (%)]]-1.96*GoalAnalysisTable5[[#This Row],[Success Rate (%)]]*(1-GoalAnalysisTable5[[#This Row],[Success Rate (%)]])/GoalAnalysisTable5[[#This Row],[Count]] -> 0.53072878 | L7: =GoalAnalysisTable5[[#This Row],[Success Rate (%)]]+1.96*GoalAnalysisTable5[[#This Row],[Success Rate (%)]]*(1-GoalAnalysisTable5[[#This Row],[Success Rate (%)]])/GoalAnalysisTable5[[#This Row],[Count]] -> 0.56018032
A8: Both | B8: =COUNTIFS(Crowdfunding!$R$2:$R$1001,"TRUE",Crowdfunding!$S$2:$S$1001,"TRUE",Crowdfunding!$G$2:$G$1001,"=successful") -> 10 | C8: =COUNTIFS(Crowdfunding!$R$2:$R$1001,"TRUE",Crowdfunding!$S$2:$S$1001,"TRUE",Crowdfunding!$G$2:$G$1001,"=failed") -> 4 | D8: =COUNTIFS(Crowdfunding!$R$2:$R$1001,"TRUE",Crowdfunding!$S$2:$S$1001,"TRUE",Crowdfunding!$G$2:$G$1001,"=canceled") -> 2 | E8: =COUNTIFS(Crowdfunding!$R$2:$R$1001,"TRUE",Crowdfunding!$S$2:$S$1001,"TRUE",Crowdfunding!$G$2:$G$1001,"=live") -> 0 | F8: =SUM(B8:E8) -> 16 | G8: =B8/$F8 -> 0.625 | H8: =C8/$F8 -> 0.25 | I8: =D8/$F8 -> 0.125 | J8: =E8/$F8 -> 0 | K8: =GoalAnalysisTable5[[#This Row],[Success Rate (%)]]-1.96*GoalAnalysisTable5[[#This Row],[Success Rate (%)]]*(1-GoalAnalysisTable5[[#This Row],[Success Rate (%)]])/GoalAnalysisTable5[[#This Row],[Count]] -> 0.59628906 | L8: =GoalAnalysisTable5[[#This Row],[Success Rate (%)]]+1.96*GoalAnalysisTable5[[#This Row],[Success Rate (%)]]*(1-GoalAnalysisTable5[[#This Row],[Success Rate (%)]])/GoalAnalysisTable5[[#This Row],[Count]] -> 0.65371094

Sheet Success Driver Summary
A1: Key Success Drivers: Ranked Summary
A2: What factors most strongly predict crowdfunding success in this dataset?
A4: Factor | B4: Best Value | C4: Worst Value | D4: Takeaway
A5: Goal Size | B5: $1K–$5K (82% success) | C5: >$100K (23% success) | D5: Ambitious goals dramatically reduce chances
A6: Launch Day | B6: Monday (64%) | C6: Friday (51%) | D6: Avoid Friday launches
A7: Category | B7: Journalism (100%), Tech (67%) | C7: Games (44%), Food (48%) | D7: Category selection matters
A8: Backers Count | B8: High backers → high pledged (r = 0.87) | C8: Low backers | D8: Backer acquisition is the core lever
A9: Promotion | B9: Both Pick + Spotlight (~63%) | C9: Neither (~57%) | D9: Combined endorsements give best lift
A10: Campaign Duration | B10: No meaningful effect (r ≈ −0.04) | C10: — | D10: Length alone doesn't drive success
A11: Goal vs % Funded | B11: r = −0.31 with % Funded | C11: — | D11: Lower goals = higher over-funding ratio
